Workbook

Sheet Contents
A3: Specialist homelessness services 2023–24
A5: Data tables
A6: x
A7: These data tables supplement the report, Specialist homelessness services 2023–24 (AIHW 2024), and provide information on people who received assistance from specialist homelessness agencies in 2023–24, the assistance they received and their changes in housing and other circumstances. Data on those who requested services, but were not provided with support are also presented. The data are compiled from the Specialist Homelessness Services Collection (SHSC) which is collated by the AIHW. Please refer to the report for further information about the collection, and information that will help to interpret the data.
A8: Please note that there is the potential for minor revisions of data in this report. Please check the online version at <www.aihw.gov.au> for any amendments.
A10: Framework
A11: =OVERVIEW.1!A2 -> Table OVERVIEW.1: Agencies contributing support periods, by jurisdiction, 2011–12 to 2023–24
A12: =OVERVIEW.2!A2 -> Table OVERVIEW.2: Agencies by number of clients, by jurisdiction, 2023–24
A13: =OVERVIEW.3!A2 -> Table OVERVIEW.3: Clients of Specialist Homelessness Services by service type provided or referred, state and territory, 2023–24
A15: All clients
A16: ='CLIENTS.1'!A2 -> Table CLIENTS.1: Clients and support periods, by age and sex, and by state and territory, 2023–24
A17: ='CLIENTS.2'!A2 -> Table CLIENTS.2: Clients, by new and returning client status, and by state and territory, 2023–24
A18: ='CLIENTS.3'!A2 -> Table CLIENTS.3: Clients, by country of birth (country group), and by state and territory, 2023–24
A19: ='CLIENTS.4'!A2 -> Table CLIENTS.4: Clients by country of birth (top 10), and by state and territory, 2023–24
A20: ='CLIENTS.5'!A2 -> Table CLIENTS.5: Clients born overseas, by year of arrival, 2023–24
A21: ='CLIENTS.6'!A2 -> Table CLIENTS.6: Clients born overseas, by Remoteness Area, 2023–24
A22: ='CLIENTS.7'!A2 -> Table CLIENTS.7: Clients by main language spoken at home other than English (top 10), 2023–24
A23: ='CLIENTS.8'!A2 -> Table CLIENTS.8: Clients by broad group of main language spoken at home (other than English) and proficiency of spoken English, 2023–24
A24: ='CLIENTS.9'!A2 -> Table CLIENTS.9: Clients, by presenting unit type at the beginning of support, and by state and territory, 2023–24
A25: ='CLIENTS.10'!A2 -> Table CLIENTS.10: Clients, by living arrangement, and by state and territory, 2023–24
A26: ='CLIENTS.11'!A2 -> Table CLIENTS.11: Clients, by housing situation at first presentation, and by state and territory, 2023–24
A27: ='CLIENTS.12'!A2 -> Table CLIENTS.12: Clients, by homeless status at first presentation, by client groups, 2019–20 to 2023–24
A28: ='CLIENTS.13'!A2 -> Table CLIENTS.13: Clients who first presented to an agency reporting no shelter/improvised dwelling (rough sleepers), by dwelling type, 2023–24
A29: ='CLIENTS.14'!A2 -> Table CLIENTS.14: Clients, by homelessness status in the month before the first support period, by state and territory, 2023–24
A30: ='CLIENTS.15'!A2 -> Table CLIENTS.15: Clients, by source of referral at the beginning of support, and by state and territory, 2023–24
A31: ='CLIENTS.16'!A2 -> Table CLIENTS.16: Clients aged 15 and over, by main source of income, and by state and territory, 2023–24
A32: ='CLIENTS.17'!A2 -> Table CLIENTS.17: Clients by National Disability Insurance Scheme status, and by state and territory, 2023–24
A33: ='CLIENTS.18'!A2 -> Table CLIENTS.18: Clients, by educational enrolment status at beginning of support and age, and by state and territory, 2023–24
A34: ='CLIENTS.19'!A2 -> Table CLIENTS.19: Clients aged 15 or over, by labour force status, and by state and territory, 2023–24
A35: ='CLIENTS.20'!A2 -> Table CLIENTS.20: Clients, by educational enrolment status at beginning of support and labour force status, and by state and territory, 2023–24
A36: ='CLIENTS.21'!A2 -> Table CLIENTS.21: Clients, by reasons for seeking assistance, and by state and territory, 2023–24
A37: ='CLIENTS.22'!A2 -> Table CLIENTS.22: Clients, by main reasons for seeking assistance, and by state and territory, 2023–24
A38: ='CLIENTS.23'!A2 -> Table CLIENTS.23: Clients, by homeless status at first presentation and main reasons for seeking assistance, 2023–24
A39: ='CLIENTS.24'!A2 -> Table CLIENTS.24: Clients, by need for services and assistance and service provision status, and by state and territory, 2023–24
A40: ='CLIENTS.25'!A2 -> Table CLIENTS.25: Clients, by total nights of accommodation, and by state and territory, 2023–24
A41: ='CLIENTS.26'!A2 -> Table CLIENTS.26: Average amount of financial assistance provided to clients, by type of financial assistance, and by state and territory, 2023–24
A42: ='CLIENTS.27'!A2 -> Table CLIENTS.27: Clients, by number of support periods, and by state and territory, 2023–24
A43: ='CLIENTS.28'!A2 -> Table CLIENTS.28: Support periods, by indicative duration over the reporting period, and by state and territory, 2023–24
A44: ='CLIENTS.29'!A2 -> Table CLIENTS.29: Clients, by total days of support, and by state and territory, 2023–24
A45: ='CLIENTS.30'!A2 -> Table CLIENTS.30: Clients with any closed support period, by reason support period ended, and by state and territory, 2023–24
A46: ='CLIENTS.31'!A2 -> Table CLIENTS.31: Clients with closed support, by housing situation at first presentation and at end of support, and by state and territory, 2023–24
A47: ='CLIENTS.32'!A2 -> Table CLIENTS.32: Clients with closed support and known housing situation at both first presentation and end of support, by housing situation at first presentation and at end of support, and by state and territory, 2023–24
A48: ='CLIENTS.33'!A2 -> Table CLIENTS.33: Clients by educational enrolment status, and by state and territory, 2023–24
A49: ='CLIENTS.34'!A2 -> Table CLIENTS.34: Clients aged 15 and over, by labour force status at the end and start of support, and by state and territory, 2023–24
A50: ='CLIENTS.35'!A2 -> Table CLIENTS.35: Clients aged 15 and over, by main source of income at the end and start of support, and by state and territory, 2023–24
A51: ='CLIENTS.36'!A2 -> Table CLIENTS.36: Clients with closed support, by case management plan status, and by state and territory, 2023–24
A52: ='CLIENTS.37'!A2 -> Table CLIENTS.37: Clients with closed support, by client groups and case management plan status (per cent), 2019–20 to 2023–24
A53: ='CLIENTS.38'!A2 -> Table CLIENTS.38: Amount of financial assistance provided to clients (total dollars), by age, and by type of financial assistance, 2023–24
A54: ='CLIENTS.39'!A2 -> Table CLIENTS.39: New clients, by homeless status at first presentation and main reasons for seeking assistance, 2023–24
A55: ='CLIENTS.40'!A2 -> Table CLIENTS.40: New clients, by service user group, and by state and territory, 2023–24
A57: Client location
A58: ='CLIENTLOC.1'!A2 -> Table CLIENTLOC.1: Clients, by Statistical Area Level 4 (SA4)(locality/suburb in the week before), by client characteristics at first presentation, 2023–24
A60: Remoteness Area
A61: ='REG.1'!A2 -> Table REG.1: Clients, by Remoteness Area, by main reasons for seeking assistance, 2023–24
A62: ='REG.2'!A2 -> Table REG.2: Clients and support periods, by Remoteness Area and by age and sex, 2023–24
A63: ='REG.3'!A2 -> Table REG.3: Clients and support periods, by Remoteness Area, and sex, and by state and territory, 2023–24
A64: ='REG.4'!A2 -> Table REG.4: Clients, by Remoteness Area, and by need for services and assistance and service provision status, 2023–24
A65: ='REG.5'!A2 -> Table REG.5: Clients with closed support, by Remoteness Area, and by housing situation at first presentation and at end of support, 2023–24
A66: ='REG.6'!A2 -> Table REG.6: Clients with closed support and known housing situation at both first presentation and end of support, by Remoteness Area, and by housing situation at first presentation and at end of support, 2023–24
A67: ='REG.7'!A2 -> Table REG.7: Client service use patterns, by agency geographic area, 2017–18 to 2023–24
A69: Unassisted instances
A70: =UNASSISTED.1!A2 -> Table UNASSISTED.1: Daily average unassisted requests, by state and territory, 2023–24
A71: =UNASSISTED.2!A2 -> Table UNASSISTED.2: Unassisted requests, by age and sex, and by state and territory, 2023–24
A72: =UNASSISTED.3!A2 -> Table UNASSISTED.3: Daily average unassisted requests, by presenting unit type and age and sex, and by state and territory, 2023–24
A73: =UNASSISTED.4!A2 -> Table UNASSISTED.4: Daily average unassisted requests, by type of service requested and sex, and by state and territory, 2023–24
A74: =UNASSISTED.5!A2 -> Table UNASSISTED.5: Daily average unassisted requests, by type of service requested and presenting unit type, and by state and territory, 2023–24
A75: =UNASSISTED.6!A2 -> Table UNASSISTED.6: Daily average unassisted requests, by reason service was not provided and type of service requested, and by state and territory, 2023–24
A76: =UNASSISTED.7!A2 -> Table UNASSISTED.7: Unassisted requests, by presenting type and age and sex, 2023–24
A78: Client groups
A79: ='CLIENTS.41'!A2 -> Table CLIENTS.41: Clients by client groups, by sex, and by state and territory, 2023–24
A80: ='CLIENTS.42'!A2 -> Table CLIENTS.42: Clients by client groups, by new and returning client status, by age and sex, and by state and territory, 2023–24
A81: ='CLIENTS.43'!A2 -> Table CLIENTS.43: Clients by client groups, by Indigenous status and sex, and by state and territory, 2023–24
A82: ='CLIENTS.44'!A2 -> Table CLIENTS.44: Clients by client groups, by presenting unit type and sex, and by state and territory, 2023–24
A83: ='CLIENTS.45'!A2 -> Table CLIENTS.45: Clients by client groups, by living arrangement and sex, and by state and territory, 2023–24
A84: ='CLIENTS.46'!A2 -> Table CLIENTS.46: Clients by client groups, by Remoteness Area, and by state and territory, 2023–24
A85: ='CLIENTS.47'!A2 -> Table CLIENTS.47: Clients by client groups, by selected vulnerability characteristics, and by state and territory, 2023–24
A86: ='CLIENTS.48'!A2 -> Table CLIENTS.48: Clients by client groups, by service use patterns, and by state and territory, 2017–18 to 2023–24
A88: Indigenous clients - additional tables
A89: =INDIGENOUS.1!A2 -> Table INDIGENOUS.1: Clients and support periods, by Indigenous status and by age and sex, 2023–24
A90: =INDIGENOUS.2!A2 -> Table INDIGENOUS.2: Clients and support periods, by Indigenous status and sex, and by state and territory, 2023–24
A91: =INDIGENOUS.3!A2 -> Table INDIGENOUS.3: Clients, by Indigenous status, and by need for services and assistance and service provision status, 2023–24
A92: =INDIGENOUS.4!A2 -> Table INDIGENOUS.4: Clients with closed support, by Indigenous status, and by housing situation at first presentation and at end of support, 2023–24
A93: =INDIGENOUS.5!A2 -> Table INDIGENOUS.5: Clients with closed support and known housing situation at both first presentation and end of support, by Indigenous status, and by housing situation at first presentation and at end of support, 2023–24
A94: =INDIGENOUS.6!A2 -> Table INDIGENOUS.6: Clients, by Indigenous status and Remoteness Area, 2023–24
A95: =INDIGENOUS.7!A2 -> Table INDIGENOUS.7: New and returning clients, by Indigenous status and by age, 2023–24
A96: =INDIGENOUS.8!A2 -> Table INDIGENOUS.8: Clients, by Indigenous status and main reasons (top 10) for seeking assistance, 2023–24
A97: =INDIGENOUS.9!A2 -> Table INDIGENOUS.9: Clients, by Indigenous status, by sex and presenting unit type, 2023–24
A98: =INDIGENOUS.10!A2 -> Table INDIGENOUS.10: Clients, by Indigenous status, by sex and living arrangement, 2023–24
A100: Young people presenting alone - additional tables
A101: =YOUNG.1!A2 -> Table YOUNG.1: Young people presenting alone, by age and sex, 2023–24
A102: =YOUNG.2!A2 -> Table YOUNG.2: Young people presenting alone, by need for services and assistance and service provision status, 2023–24(a)
A103: =YOUNG.3!A2 -> Table YOUNG.3: Young people presenting alone (closed support), by housing situation at first presentation and at the end of support, 2023–24
A104: =YOUNG.4!A2 -> Table YOUNG.4: Young people presenting alone (closed support) with known housing situation at both first presentation and end of support, by housing situation at first presentation and at the end of support, 2023–24
A105: =YOUNG.5!A2 -> Table YOUNG.5: Young people presenting alone, by main reasons (top 10) for seeking assistance, 2023–24
A106: =YOUNG.6!A2 -> Table YOUNG.6: Young people presenting alone, by homeless status at first presentation and main reasons (top 10) for seeking assistance, 2023–24
A107: =YOUNG.7!A2 -> Table YOUNG.7: Young people presenting alone, by education enrolment status at beginning of support, 2023–24
A109: Children on a care and protection order - additional tables
A110: ='CPO.1'!A2 -> Table CPO.1: Children on a care and protection order, by age and sex, 2023–24
A111: ='CPO.2'!A2 -> Table CPO.2: Children on a care and protection order, by need for services and assistance and service provision status, 2023–24(a)
A112: ='CPO.3'!A2 -> Table CPO.3: Children on a care and protection order (closed support), by housing situation at first presentation and at the end of support, 2023–24
...

Sheet Explanatory notes
A1: Explanatory notes
A3: These tables relate to all clients who were assisted in the 2023–24 reporting period by specialist homelessness agencies.
A4: Further information about the Specialist Homelessness Services Collection is available in the national data report <https://www.aihw.gov.au/reports-statistics/health-welfare-services/homelessness-services/reports>.
A6: Client, support period, and presenting unit data
A7: Data presented in these tables are mainly based on 'clients', with some data based on 'support periods' or 'client groups' (or 'presenting units'—which identify clients who present together to a specialist homelessness agency, including clients who present alone—and receive a service). Information on clients who are homeless, at risk of homelessness or part of a specialist interest group, is mostly client-level data and information on agencies, unmet demand and trends data is predominantly support period data.
A8: Due to improvements in agency response and SLK validity rates, data for 2017–18 onwards were not weighted. As the aim of the imputation strategy was to account for low rates of agency response and SLK validity in previous years, unweighted data for 2017–18 onwards are directly comparable with weighted data for 2011–12 to 2016–17. Comparisons between years of counts of clients and support periods should use weighted data for 2011–12 to 2016–17 and unweighted data from 2017–18 onwards.
A10: Client-level data
A11: An individual client may have had more than one support period —either from the same agency or from a different agency. Data from individual clients who received services from different agencies and/or at different times are matched based on a statistical linkage key (SLK). All analyses based on client data include only those clients for whom full and valid SLK data (i.e. date of birth, sex, and alpha code based on selected letters of name) are available.
A12: Clients who have more than one support period during 2023–24 may present with different characteristics in these different support periods. For example, their main reason for seeking assistance may be 'family and domestic violence' in their first support period, and 'housing crisis' in the second. Where there are multiple responses to a question, some information presented is based on the client's response to the question when they first became a client of an agency in 2023–24. Other information is based on a counting methodology that analyses the client's responses and, where these are different responses, determines the response provided most often and the client's longest support period for each month in 2023–24. The methodology is conceptually based on the client's journey during the course of the 2023–24 reporting period regardless of their movement between jurisdictions. Annual client-level data presented by jurisdiction should be interpreted with caution as the information is representative of clients who presented to that jurisdiction at any time during the reporting period and may not represent the clients’ characteristics exhibited when they attended for services in that particular jurisdiction.
A13: Detailed information on how specific variables were derived can be found in the 'Technical information' page which is associated with this publication on the AIHW’s website <www.aihw.gov.au>.
A15: Data quality
A16: The 2023–24 Specialist Homelessness Services Collection Data Quality Statement is available from <http://meteor.aihw.gov.au>.
... A36: In 2016–17, the Australian Capital Territory introduced a new central intake service delivery model. In practice, this system requires agency workers to provide assistance of some kind to all presenting individuals. Therefore, caution should be used when comparing data over time and with data for other states and territories, particularly data relating to unassisted requests.

Sheet Derivation notes
A1: Derivation notes
A3: Further information about the Specialist Homelessness Services Collection is available in the national data report <https://www.aihw.gov.au/reports-statistics/health-welfare-services/homelessness-services/reports>.
A5: Clients at risk of homelessness
A6: In 2022–23, an improvement was introduced to the classification of clients at risk of homelessness. Clients with unknown tenure and an occupancy condition that is ‘other’, ‘unknown’ or ‘not applicable’ are now classified as ‘not stated’ rather than ‘at risk – other’. The change resulted in a reduction in the number of clients with an ‘at risk’ homelessness status and a corresponding increase in the number of ‘not stated’ clients. The change has been applied to all years of data in the collection meaning data is not comparable to publications released prior to September 2023.
A8: Young people presenting alone
A9: Young people are defined as any client aged 15–24 who presented to a specialist homelessness agency alone in their first support period.
A11: Children on a care and protection order
A12: A client is identified as being under a care or protection order if they are aged under 18 and have provided any of the following information in any support period (any month within the support period) during the reporting period (either the week before, at the beginning of the support period or during support).
A13: They reported that they were under a care and protection order and that they had the following care arrangements • residential care • family group home • relatives/kin/friends who are reimbursed • foster care • other home-based care (reimbursed) • relatives/kin/friends who are not reimbursed • independent living • other living arrangements • parents; or They have reported ‘Transition from foster care/child safety residential placements’ as a reason for seeking assistance, or main reason for seeking assistance.
A15: Clients leaving care
A16: A client is identified as transitioning from care arrangements if in their first support period during the reporting period (either the week before or at the beginning of the support period):Their dwelling type was recorded as: • hospital (excluding psychiatric) • psychiatric hospital or unit • disability support • rehabilitation • aged care facility; or One of their reasons for seeking assistance was: • transition from foster care/child safety residential placements • transition from other care arrangements.
A18: Clients exiting custodial arrangements
... A41: • Their dwelling type was recorded as rehabilitation • Their formal referral source to the specialist homelessness agency was a drug and alcohol service • During their support they required drug/alcohol counselling • They have been in a rehabilitation facility/institution in the last 12 months • They have reported 'problematic drug or substance abuse' or 'problematic alcohol use' as a reason for seeking assistance or main reason for seeking assistance.

Sheet OVERVIEW.1
A1: Table of contents
A2: Table OVERVIEW.1: Agencies contributing support periods, by jurisdiction, 2011–12 to 2023–24
A4: Year | B4: NSW | C4: Vic | D4: Qld | E4: WA | F4: SA | G4: Tas | H4: ACT | I4: NT | J4: Australia
A5: 2011–12 | B5: 359 | C5: 479 | D5: 226 | E5: 192 | F5: 93 | G5: 34 | H5: 44 | I5: 59 | J5: 1486
A6: 2012–13 | B6: 359 | C6: 491 | D6: 230 | E6: 193 | F6: 91 | G6: 36 | H6: 38 | I6: 64 | J6: 1502
A7: 2013–14 | B7: 354 | C7: 495 | D7: 226 | E7: 195 | F7: 92 | G7: 38 | H7: 41 | I7: 66 | J7: 1507
A8: 2014–15 | B8: 389 | C8: 495 | D8: 228 | E8: 193 | F8: 93 | G8: 45 | H8: 39 | I8: 66 | J8: 1548
A9: 2015–16 | B9: 300 | C9: 492 | D9: 230 | E9: 197 | F9: 91 | G9: 49 | H9: 37 | I9: 64 | J9: 1460
A10: 2016–17 | B10: 330 | C10: 516 | D10: 236 | E10: 189 | F10: 94 | G10: 45 | H10: 42 | I10: 66 | J10: 1518
A11: 2017–18 | B11: 331 | C11: 546 | D11: 245 | E11: 177 | F11: 92 | G11: 51 | H11: 37 | I11: 71 | J11: 1550
A12: 2018–19 | B12: 339 | C12: 569 | D12: 248 | E12: 178 | F12: 90 | G12: 49 | H12: 37 | I12: 73 | J12: 1583
A13: 2019–20 | B13: 341 | C13: 595 | D13: 258 | E13: 177 | F13: 86 | G13: 50 | H13: 43 | I13: 75 | J13: 1625
A14: 2020–21 | B14: 335 | C14: 635 | D14: 257 | E14: 201 | F14: 85 | G14: 58 | H14: 44 | I14: 83 | J14: 1698
A15: 2021–22 | B15: 332 | C15: 643 | D15: 261 | E15: 205 | F15: 71 | G15: 61 | H15: 44 | I15: 81 | J15: 1698
A16: 2022–23 | B16: 334 | C16: 655 | D16: 267 | E16: 205 | F16: 71 | G16: 66 | H16: 46 | I16: 79 | J16: 1723
A17: 2023–24 | B17: 345 | C17: 664 | D17: 290 | E17: 206 | F17: 71 | G17: 70 | H17: 47 | I17: 81 | J17: 1774
A19: Note: Count of SHSC agencies who contributed support periods during the reference year.

Sheet OVERVIEW.2
A1: Table of contents
A2: Table OVERVIEW.2: Agencies by number of clients, by jurisdiction, 2023–24
A4: Number of clients | B4: NSW | C4: Vic | D4: Qld | E4: WA | F4: SA | G4: Tas | H4: ACT | I4: NT
A5: 0 to 99 | B5: 109 | C5: 356 | D5: 151 | E5: 122 | F5: 28 | G5: 39 | H5: 33 | I5: 46
A6: 100 to 199 | B6: 98 | C6: 136 | D6: 62 | E6: 45 | F6: 12 | G6: 14 | H6: 11 | I6: 20
A7: 200 to 299 | B7: 52 | C7: 59 | D7: 28 | E7: 17 | F7: 10 | G7: 2 | H7: 2 | I7: 6
A8: 300 to 599 | B8: 55 | C8: 58 | D8: 25 | E8: 16 | F8: 12 | G8: 10 | H8: — | I8: 7
A9: 600 to 1,499 | B9: 31 | C9: 35 | D9: 20 | E9: 4 | F9: 3 | G9: 4 | H9: — | I9: 1
A10: 1,500 or more | B10: — | C10: 20 | D10: 4 | E10: 2 | F10: 6 | G10: 1 | H10: 1 | I10: 1
A11: Total | B11: 345 | C11: 664 | D11: 290 | E11: 206 | F11: 71 | G11: 70 | H11: 47 | I11: 81
A13: Note
A14: — nil or rounded to zero

Sheet OVERVIEW.3
A1: Table of contents
A2: Table OVERVIEW.3: Clients of Specialist Homelessness Services by service type provided or referred, state and territory, 2023–24
B4: Clients | C4: Clients | D4: Clients | E4: Per cent | F4: Per cent
A5: State/ territory | B5: Accommodation services | C5: Only services other than accommodation | D5: Total | E5: Accommodation services | F5: Only services other than accommodation
A6: NSW | B6: 34522 | C6: 32979 | D6: 67501 | E6: 51.1 | F6: 48.9
A7: Vic | B7: 52063 | C7: 49596 | D7: 101659 | E7: 51.2 | F7: 48.8
A8: Qld | B8: 31164 | C8: 17525 | D8: 48689 | E8: 64 | F8: 36
A9: WA | B9: 15876 | C9: 9092 | D9: 24968 | E9: 63.6 | F9: 36.4
A10: SA | B10: 8475 | C10: 10240 | D10: 18715 | E10: 45.3 | F10: 54.7
A11: Tas | B11: 5756 | C11: 884 | D11: 6640 | E11: 86.7 | F11: 13.3
A12: ACT | B12: 2632 | C12: 1370 | D12: 4002 | E12: 65.8 | F12: 34.2
A13: NT | B13: 5921 | C13: 4132 | D13: 10053 | E13: 58.9 | F13: 41.1
A15: Notes
A16: 1. Clients who were provided and/or referred any 'Accommodation provision' or 'Assistance to sustain housing tenure' in the reporting period are recorded under 'Accommodation services'.
A17: 2. Clients who were only provided and/or referred services other than accommodation services in the reporting period are recorded under 'Only services other than accommodation'.
A18: 3. Denominator: clients provided and/or referred any service.
A19: 4. Clients in 2023–24 who were not provided or referred any service: 914.

Sheet CLIENTS.1
A1: Table of contents
A2: Table CLIENTS.1: Clients and support periods, by age and sex, and by state and territory, 2023–24
D4: Males | E4: Males | F4: Females | G4: Females | H4: All clients | I4: All clients
A5: State/territory | B5: Data type | C5: Age group | D5: Number | E5: Per cent | F5: Number | G5: Per cent | H5: Number | I5: Per cent
A6: National | B6: All clients | C6: 0–9 | D6: 22215 | E6: 19.7 | F6: 21334 | G6: 12.8 | H6: 43549 | I6: 15.5
A7: National | B7: All clients | C7: 10–14 | D7: 8526 | E7: 7.6 | F7: 9203 | G7: 5.5 | H7: 17729 | I7: 6.3
A8: National | B8: All clients | C8: 15–17 | D8: 6430 | E8: 5.7 | F8: 9295 | G8: 5.6 | H8: 15725 | I8: 5.6
A9: National | B9: All clients | C9: 18–24 | D9: 12696 | E9: 11.2 | F9: 24635 | G9: 14.7 | H9: 37331 | I9: 13.3
A10: National | B10: All clients | C10: 25–34 | D10: 15816 | E10: 14 | F10: 34643 | G10: 20.7 | H10: 50459 | I10: 18
A11: National | B11: All clients | C11: 35–44 | D11: 18197 | E11: 16.1 | F11: 32381 | G11: 19.4 | H11: 50578 | I11: 18.1
A12: National | B12: All clients | C12: 45–54 | D12: 15134 | E12: 13.4 | F12: 20087 | G12: 12 | H12: 35221 | I12: 12.6
A13: National | B13: All clients | C13: 55–64 | D13: 8676 | E13: 7.7 | F13: 9577 | G13: 5.7 | H13: 18253 | I13: 6.5
A14: National | B14: All clients | C14: 65+ | D14: 5183 | E14: 4.6 | F14: 6050 | G14: 3.6 | H14: 11233 | I14: 4
A15: National | B15: All clients | C15: Total | D15: 112873 | E15: 100 | F15: 167205 | G15: 100 | H15: 280078 | I15: 100
A16: National | B16: All clients | C16: Sex as % of total | D16: 112873 | E16: 40.3 | F16: 167205 | G16: 59.7 | H16: 280078 | I16: 100
A17: National | B17: Clients (per 10,000 ERP)(a) | C17: 0–9 | D17: 138.2 | E17: . . | F17: 140.3 | G17: . . | H17: 139.2 | I17: . .
A18: National | B18: Clients (per 10,000 ERP)(a) | C18: 10–14 | D18: 100.1 | E18: . . | F18: 114.2 | G18: . . | H18: 107 | I18: . .
A19: National | B19: Clients (per 10,000 ERP)(a) | C19: 15–17 | D19: 128.6 | E19: . . | F19: 197.4 | G19: . . | H19: 161.9 | I19: . .
A20: National | B20: Clients (per 10,000 ERP)(a) | C20: 18–24 | D20: 103.5 | E20: . . | F20: 215.7 | G20: . . | H20: 157.6 | I20: . .
A21: National | B21: Clients (per 10,000 ERP)(a) | C21: 25–34 | D21: 80.6 | E21: . . | F21: 177.5 | G21: . . | H21: 128.9 | I21: . .
A22: National | B22: Clients (per 10,000 ERP)(a) | C22: 35–44 | D22: 98.7 | E22: . . | F22: 172.6 | G22: . . | H22: 135.9 | I22: . .
A23: National | B23: Clients (per 10,000 ERP)(a) | C23: 45–54 | D23: 93.1 | E23: . . | F23: 120.2 | G23: . . | H23: 106.8 | I23: . .
A24: National | B24: Clients (per 10,000 ERP)(a) | C24: 55–64 | D24: 58.3 | E24: . . | F24: 61.6 | G24: . . | H24: 60 | I24: . .
A25: National | B25: Clients (per 10,000 ERP)(a) | C25: 65+ | D25: 24.3 | E25: . . | F25: 24.9 | G25: . . | H25: 24.6 | I25: . .
A26: National | B26: Clients (per 10,000 ERP)(a) | C26: Total | D26: 85.3 | E26: . . | F26: 124.6 | G26: . . | H26: 105.1 | I26: . .
A27: National | B27: Support periods | C27: 0–9 | D27: 31047 | E27: 16.4 | F27: 29827 | G27: 10.2 | H27: 60874 | I27: 12.7
A28: National | B28: Support periods | C28: 10–14 | D28: 11523 | E28: 6.1 | F28: 12374 | G28: 4.3 | H28: 23897 | I28: 5
A29: National | B29: Support periods | C29: 15–17 | D29: 9615 | E29: 5.1 | F29: 15044 | G29: 5.2 | H29: 24659 | I29: 5.1
A30: National | B30: Support periods | C30: 18–24 | D30: 23188 | E30: 12.2 | F30: 46988 | G30: 16.1 | H30: 70176 | I30: 14.6
A31: National | B31: Support periods | C31: 25–34 | D31: 28756 | E31: 15.2 | F31: 65198 | G31: 22.4 | H31: 93954 | I31: 19.5
A32: National | B32: Support periods | C32: 35–44 | D32: 34557 | E32: 18.2 | F32: 61189 | G32: 21 | H32: 95746 | I32: 19.9
A33: National | B33: Support periods | C33: 45–54 | D33: 28467 | E33: 15 | F33: 35670 | G33: 12.3 | H33: 64137 | I33: 13.3
A34: National | B34: Support periods | C34: 55–64 | D34: 14737 | E34: 7.8 | F34: 15676 | G34: 5.4 | H34: 30413 | I34: 6.3
A35: National | B35: Support periods | C35: 65+ | D35: 7882 | E35: 4.2 | F35: 9105 | G35: 3.1 | H35: 16987 | I35: 3.5
A36: National | B36: Support periods | C36: Not stated | D36: 2070 | E36: . . | F36: 2707 | G36: . . | H36: 4777 | I36: . .
A37: National | B37: Support periods | C37: Total | D37: 191842 | E37: 100 | F37: 293778 | G37: 100 | H37: 485620 | I37: 100
A38: National | B38: Support periods | C38: Sex as % of total | D38: 191842 | E38: 39.5 | F38: 293778 | G38: 60.5 | H38: 485620 | I38: 100
A39: NSW | B39: All clients | C39: 0–9 | D39: 5564 | E39: 20.2 | F39: 5501 | G39: 13.6 | H39: 11065 | I39: 16.3
A40: NSW | B40: All clients | C40: 10–14 | D40: 2316 | E40: 8.4 | F40: 2615 | G40: 6.5 | H40: 4931 | I40: 7.3
A41: NSW | B41: All clients | C41: 15–17 | D41: 2378 | E41: 8.7 | F41: 3557 | G41: 8.8 | H41: 5935 | I41: 8.7
A42: NSW | B42: All clients | C42: 18–24 | D42: 3860 | E42: 14 | F42: 7267 | G42: 18 | H42: 11127 | I42: 16.4
A43: NSW | B43: All clients | C43: 25–34 | D43: 3247 | E43: 11.8 | F43: 7260 | G43: 18 | H43: 10507 | I43: 15.5
A44: NSW | B44: All clients | C44: 35–44 | D44: 3737 | E44: 13.6 | F44: 6621 | G44: 16.4 | H44: 10358 | I44: 15.3
A45: NSW | B45: All clients | C45: 45–54 | D45: 3394 | E45: 12.3 | F45: 4338 | G45: 10.7 | H45: 7732 | I45: 11.4
A46: NSW | B46: All clients | C46: 55–64 | D46: 1943 | E46: 7.1 | F46: 2020 | G46: 5 | H46: 3963 | I46: 5.8
A47: NSW | B47: All clients | C47: 65+ | D47: 1047 | E47: 3.8 | F47: 1226 | G47: 3 | H47: 2273 | I47: 3.3
A48: NSW | B48: All clients | C48: Total | D48: 27486 | E48: 100 | F48: 40405 | G48: 100 | H48: 67891 | I48: 100
A49: NSW | B49: All clients | C49: Sex as % of total | D49: 27486 | E49: 40.5 | F49: 40405 | G49: 59.5 | H49: 67891 | I49: 100
A50: NSW | B50: Clients (per 10,000 ERP)(a) | C50: Total | D50: 66.2 | E50: . . | F50: 96.3 | G50: . . | H50: 81.4 | I50: . .
A51: NSW | B51: Support periods | C51: 0–9 | D51: 6783 | E51: 18.3 | F51: 6803 | G51: 11.8 | H51: 13586 | I51: 14.4
A52: NSW | B52: Support periods | C52: 10–14 | D52: 2776 | E52: 7.5 | F52: 3284 | G52: 5.7 | H52: 6060 | I52: 6.4
A53: NSW | B53: Support periods | C53: 15–17 | D53: 3489 | E53: 9.4 | F53: 5561 | G53: 9.7 | H53: 9050 | I53: 9.6
A54: NSW | B54: Support periods | C54: 18–24 | D54: 5908 | E54: 15.9 | F54: 11636 | G54: 20.2 | H54: 17544 | I54: 18.5
A55: NSW | B55: Support periods | C55: 25–34 | D55: 4324 | E55: 11.6 | F55: 10297 | G55: 17.9 | H55: 14621 | I55: 15.5
A56: NSW | B56: Support periods | C56: 35–44 | D56: 5249 | E56: 14.1 | F56: 9486 | G56: 16.5 | H56: 14735 | I56: 15.6
A57: NSW | B57: Support periods | C57: 45–54 | D57: 4758 | E57: 12.8 | F57: 6214 | G57: 10.8 | H57: 10972 | I57: 11.6
A58: NSW | B58: Support periods | C58: 55–64 | D58: 2585 | E58: 7 | F58: 2675 | G58: 4.7 | H58: 5260 | I58: 5.6
A59: NSW | B59: Support periods | C59: 65+ | D59: 1284 | E59: 3.5 | F59: 1510 | G59: 2.6 | H59: 2794 | I59: 3
A60: NSW | B60: Support periods | C60: Not stated | D60: 853 | E60: . . | F60: 828 | G60: . . | H60: 1681 | I60: . .
A61: NSW | B61: Support periods | C61: Total | D61: 38009 | E61: 100 | F61: 58294 | G61: 100 | H61: 96303 | I61: 100
A62: NSW | B62: Support periods | C62: Sex as % of total | D62: 38009 | E62: 39.5 | F62: 58294 | G62: 60.5 | H62: 96303 | I62: 100
A63: Vic | B63: All clients | C63: 0–9 | D63: 7187 | E63: 16.9 | F63: 6878 | G63: 11.6 | H63: 14065 | I63: 13.8
A64: Vic | B64: All clients | C64: 10–14 | D64: 2915 | E64: 6.9 | F64: 3040 | G64: 5.1 | H64: 5955 | I64: 5.8
A65: Vic | B65: All clients | C65: 15–17 | D65: 1877 | E65: 4.4 | F65: 2382 | G65: 4 | H65: 4259 | I65: 4.2
A66: Vic | B66: All clients | C66: 18–24 | D66: 4383 | E66: 10.3 | F66: 7461 | G66: 12.5 | H66: 11844 | I66: 11.6
A67: Vic | B67: All clients | C67: 25–34 | D67: 7007 | E67: 16.5 | F67: 12883 | G67: 21.6 | H67: 19890 | I67: 19.5
A68: Vic | B68: All clients | C68: 35–44 | D68: 7722 | E68: 18.2 | F68: 12624 | G68: 21.2 | H68: 20346 | I68: 20
A69: Vic | B69: All clients | C69: 45–54 | D69: 5889 | E69: 13.9 | F69: 7890 | G69: 13.3 | H69: 13779 | I69: 13.5
A70: Vic | B70: All clients | C70: 55–64 | D70: 3337 | E70: 7.9 | F70: 3783 | G70: 6.4 | H70: 7120 | I70: 7
A71: Vic | B71: All clients | C71: 65+ | D71: 2115 | E71: 5 | F71: 2591 | G71: 4.4 | H71: 4706 | I71: 4.6
A72: Vic | B72: All clients | C72: Total | D72: 42432 | E72: 100 | F72: 59532 | G72: 100 | H72: 101964 | I72: 100
A73: Vic | B73: All clients | C73: Sex as % of total | D73: 42432 | E73: 41.6 | F73: 59532 | G73: 58.4 | H73: 101964 | I73: 100
A74: Vic | B74: Clients (per 10,000 ERP)(a) | C74: Total | D74: 125.8 | E74: . . | F74: 172.7 | G74: . . | H74: 149.5 | I74: . .
A75: Vic | B75: Support periods | C75: 0–9 | D75: 10991 | E75: 12.9 | F75: 10458 | G75: 8.5 | H75: 21449 | I75: 10.3
A76: Vic | B76: Support periods | C76: 10–14 | D76: 4344 | E76: 5.1 | F76: 4466 | G76: 3.6 | H76: 8810 | I76: 4.2
A77: Vic | B77: Support periods | C77: 15–17 | D77: 3022 | E77: 3.5 | F77: 4282 | G77: 3.5 | H77: 7304 | I77: 3.5
A78: Vic | B78: Support periods | C78: 18–24 | D78: 10181 | E78: 11.9 | F78: 18032 | G78: 14.7 | H78: 28213 | I78: 13.6
A79: Vic | B79: Support periods | C79: 25–34 | D79: 15207 | E79: 17.8 | F79: 29424 | G79: 24 | H79: 44631 | I79: 21.4
A80: Vic | B80: Support periods | C80: 35–44 | D80: 17740 | E80: 20.7 | F80: 28630 | G80: 23.3 | H80: 46370 | I80: 22.3
A81: Vic | B81: Support periods | C81: 45–54 | D81: 13715 | E81: 16 | F81: 16091 | G81: 13.1 | H81: 29806 | I81: 14.3
A82: Vic | B82: Support periods | C82: 55–64 | D82: 6633 | E82: 7.8 | F82: 6966 | G82: 5.7 | H82: 13599 | I82: 6.5
A83: Vic | B83: Support periods | C83: 65+ | D83: 3665 | E83: 4.3 | F83: 4333 | G83: 3.5 | H83: 7998 | I83: 3.8
A84: Vic | B84: Support periods | C84: Not stated | D84: 541 | E84: . . | F84: 764 | G84: . . | H84: 1305 | I84: . .
A85: Vic | B85: Support periods | C85: Total | D85: 86039 | E85: 100 | F85: 123446 | G85: 100 | H85: 209485 | I85: 100
A86: Vic | B86: Support periods | C86: Sex as % of total | D86: 86039 | E86: 41.1 | F86: 123446 | G86: 58.9 | H86: 209485 | I86: 100
A87: Qld | B87: All clients | C87: 0–9 | D87: 4471 | E87: 22.4 | F87: 4089 | G87: 14.2 | H87: 8560 | I87: 17.5
A88: Qld | B88: All clients | C88: 10–14 | D88: 1582 | E88: 7.9 | F88: 1596 | G88: 5.5 | H88: 3178 | I88: 6.5
A89: Qld | B89: All clients | C89: 15–17 | D89: 1048 | E89: 5.2 | F89: 1444 | G89: 5 | H89: 2492 | I89: 5.1
A90: Qld | B90: All clients | C90: 18–24 | D90: 2152 | E90: 10.8 | F90: 4380 | G90: 15.2 | H90: 6532 | I90: 13.4
A91: Qld | B91: All clients | C91: 25–34 | D91: 2486 | E91: 12.4 | F91: 6184 | G91: 21.5 | H91: 8670 | I91: 17.8
A92: Qld | B92: All clients | C92: 35–44 | D92: 3140 | E92: 15.7 | F92: 5400 | G92: 18.7 | H92: 8540 | I92: 17.5
A93: Qld | B93: All clients | C93: 45–54 | D93: 2758 | E93: 13.8 | F93: 3337 | G93: 11.6 | H93: 6095 | I93: 12.5
A94: Qld | B94: All clients | C94: 55–64 | D94: 1467 | E94: 7.3 | F94: 1474 | G94: 5.1 | H94: 2941 | I94: 6
A95: Qld | B95: All clients | C95: 65+ | D95: 899 | E95: 4.5 | F95: 911 | G95: 3.2 | H95: 1810 | I95: 3.7
A96: Qld | B96: All clients | C96: Total | D96: 20003 | E96: 100 | F96: 28815 | G96: 100 | H96: 48818 | I96: 100
A97: Qld | B97: All clients | C97: Sex as % of total | D97: 20003 | E97: 41 | F97: 28815 | G97: 59 | H97: 48818 | I97: 100
A98: Qld | B98: Clients (per 10,000 ERP)(a) | C98: Total | D98: 74 | E98: . . | F98: 104.5 | G98: . . | H98: 89.4 | I98: . .
A99: Qld | B99: Support periods | C99: 0–9 | D99: 5513 | E99: 20.5 | F99: 5049 | G99: 12.4 | H99: 10562 | I99: 15.6
A100: Qld | B100: Support periods | C100: 10–14 | D100: 1889 | E100: 7 | F100: 1881 | G100: 4.6 | H100: 3770 | I100: 5.6
A101: Qld | B101: Support periods | C101: 15–17 | D101: 1344 | E101: 5 | F101: 1928 | G101: 4.7 | H101: 3272 | I101: 4.8
...

Sheet CLIENTS.2
A1: Table of contents
A2: Table CLIENTS.2: Clients, by new and returning client status, and by state and territory, 2023–24
C4: Males | D4: Males | E4: Females | F4: Females | G4: All clients | H4: All clients
A5: State/territory | B5: New or returning clients | C5: Number | D5: Per cent | E5: Number | F5: Per cent | G5: Number | H5: Per cent
A6: National | B6: New clients | C6: 43143 | D6: 38.2 | E6: 59060 | F6: 35.3 | G6: 102203 | H6: 36.5
A7: National | B7: Returning clients | C7: 69730 | D7: 61.8 | E7: 108145 | F7: 64.7 | G7: 177875 | H7: 63.5
A8: National | B8: Total | C8: 112873 | D8: 100 | E8: 167205 | F8: 100 | G8: 280078 | H8: 100
A9: NSW | B9: New clients | C9: 11428 | D9: 41.6 | E9: 15762 | F9: 39 | G9: 27190 | H9: 40
A10: NSW | B10: Returning clients | C10: 16058 | D10: 58.4 | E10: 24643 | F10: 61 | G10: 40701 | H10: 60
A11: NSW | B11: Total | C11: 27486 | D11: 100 | E11: 40405 | F11: 100 | G11: 67891 | H11: 100
A12: Vic | B12: New clients | C12: 15114 | D12: 35.6 | E12: 20073 | F12: 33.7 | G12: 35187 | H12: 34.5
A13: Vic | B13: Returning clients | C13: 27318 | D13: 64.4 | E13: 39459 | F13: 66.3 | G13: 66777 | H13: 65.5
A14: Vic | B14: Total | C14: 42432 | D14: 100 | E14: 59532 | F14: 100 | G14: 101964 | H14: 100
A15: Qld | B15: New clients | C15: 8291 | D15: 41.4 | E15: 10808 | F15: 37.5 | G15: 19099 | H15: 39.1
A16: Qld | B16: Returning clients | C16: 11712 | D16: 58.6 | E16: 18007 | F16: 62.5 | G16: 29719 | H16: 60.9
A17: Qld | B17: Total | C17: 20003 | D17: 100 | E17: 28815 | F17: 100 | G17: 48818 | H17: 100
... A32: NT | B32: Total | C32: 3378 | D32: 100 | E32: 6702 | F32: 100 | G32: 10080 | H32: 100
A34: Notes
A35: 1. New clients are defined as clients who have received a service from an SHSC agency in the financial year for the first time, having never received support in any previous year.
A36: 2. Returning clients are defined as clients who have received a service from an SHSC agency in the financial year plus at least 1 previous year since July 2011.

Sheet CLIENTS.3
A1: Table of contents
A2: Table CLIENTS.3: Clients, by country of birth (country group), and by state and territory, 2023–24
A4: State/ territory | B4: Country of birth | C4: Clients | D4: Per cent
A5: National | B5: Australia (includes External Territories) | C5: 236930 | D5: 86.6
A6: National | B6: Oceania and Antarctica | C6: 6664 | D6: 2.4
A7: National | B7: UK and Ireland | C7: 2266 | D7: 0.8
A8: National | B8: Western and Northern Europe | C8: 643 | D8: 0.2
A9: National | B9: Southern and Eastern Europe | C9: 2110 | D9: 0.8
A10: National | B10: North Africa and the Middle East | C10: 6969 | D10: 2.5
A11: National | B11: South-East Asia | C11: 4835 | D11: 1.8
A12: National | B12: North-East Asia | C12: 1650 | D12: 0.6
A13: National | B13: Southern and Central Asia | C13: 4994 | D13: 1.8
A14: National | B14: Northern America | C14: 567 | D14: 0.2
A15: National | B15: South and Central America and Carribean | C15: 1045 | D15: 0.4
A16: National | B16: Sub-Saharan Africa | C16: 5041 | D16: 1.8
A17: National | B17: Not stated | C17: 6364 | D17: . .
A18: National | B18: Total | C18: 280078 | D18: 100
A19: NSW | B19: Australia (includes External Territories) | C19: 58717 | D19: 88.4
A20: NSW | B20: Oceania and Antarctica | C20: 1544 | D20: 2.3
A21: NSW | B21: UK and Ireland | C21: 463 | D21: 0.7
A22: NSW | B22: Western and Northern Europe | C22: 167 | D22: 0.3
A23: NSW | B23: Southern and Eastern Europe | C23: 456 | D23: 0.7
A24: NSW | B24: North Africa and the Middle East | C24: 1612 | D24: 2.4
A25: NSW | B25: South-East Asia | C25: 1048 | D25: 1.6
A26: NSW | B26: North-East Asia | C26: 478 | D26: 0.7
A27: NSW | B27: Southern and Central Asia | C27: 895 | D27: 1.3
A28: NSW | B28: Northern America | C28: 156 | D28: 0.2
A29: NSW | B29: South and Central America and Carribean | C29: 305 | D29: 0.5
A30: NSW | B30: Sub-Saharan Africa | C30: 556 | D30: 0.8
A31: NSW | B31: Not stated | C31: 1494 | D31: . .
A32: NSW | B32: Total | C32: 67891 | D32: 100
A33: Vic | B33: Australia (includes External Territories) | C33: 81005 | D33: 81.6
A34: Vic | B34: Oceania and Antarctica | C34: 2379 | D34: 2.4
A35: Vic | B35: UK and Ireland | C35: 825 | D35: 0.8
A36: Vic | B36: Western and Northern Europe | C36: 259 | D36: 0.3
A37: Vic | B37: Southern and Eastern Europe | C37: 1138 | D37: 1.1
A38: Vic | B38: North Africa and the Middle East | C38: 4113 | D38: 4.1
A39: Vic | B39: South-East Asia | C39: 2463 | D39: 2.5
A40: Vic | B40: North-East Asia | C40: 702 | D40: 0.7
A41: Vic | B41: Southern and Central Asia | C41: 2968 | D41: 3
A42: Vic | B42: Northern America | C42: 191 | D42: 0.2
A43: Vic | B43: South and Central America and Carribean | C43: 405 | D43: 0.4
A44: Vic | B44: Sub-Saharan Africa | C44: 2840 | D44: 2.9
A45: Vic | B45: Not stated | C45: 2676 | D45: . .
A46: Vic | B46: Total | C46: 101964 | D46: 100
A47: Qld | B47: Australia (includes External Territories) | C47: 42283 | D47: 88.5
A48: Qld | B48: Oceania and Antarctica | C48: 2013 | D48: 4.2
A49: Qld | B49: UK and Ireland | C49: 368 | D49: 0.8
A50: Qld | B50: Western and Northern Europe | C50: 112 | D50: 0.2
A51: Qld | B51: Southern and Eastern Europe | C51: 222 | D51: 0.5
A52: Qld | B52: North Africa and the Middle East | C52: 493 | D52: 1
A53: Qld | B53: South-East Asia | C53: 529 | D53: 1.1
A54: Qld | B54: North-East Asia | C54: 214 | D54: 0.4
A55: Qld | B55: Southern and Central Asia | C55: 403 | D55: 0.8
A56: Qld | B56: Northern America | C56: 100 | D56: 0.2
A57: Qld | B57: South and Central America and Carribean | C57: 179 | D57: 0.4
A58: Qld | B58: Sub-Saharan Africa | C58: 836 | D58: 1.8
A59: Qld | B59: Not stated | C59: 1066 | D59: . .
A60: Qld | B60: Total | C60: 48818 | D60: 100
A61: WA | B61: Australia (includes External Territories) | C61: 21849 | D61: 89
A62: WA | B62: Oceania and Antarctica | C62: 487 | D62: 2
A63: WA | B63: UK and Ireland | C63: 377 | D63: 1.5
A64: WA | B64: Western and Northern Europe | C64: 60 | D64: 0.2
A65: WA | B65: Southern and Eastern Europe | C65: 135 | D65: 0.5
A66: WA | B66: North Africa and the Middle East | C66: 303 | D66: 1.2
A67: WA | B67: South-East Asia | C67: 378 | D67: 1.5
A68: WA | B68: North-East Asia | C68: 148 | D68: 0.6
A69: WA | B69: Southern and Central Asia | C69: 235 | D69: 1
A70: WA | B70: Northern America | C70: 58 | D70: 0.2
A71: WA | B71: South and Central America and Carribean | C71: 59 | D71: 0.2
A72: WA | B72: Sub-Saharan Africa | C72: 459 | D72: 1.9
A73: WA | B73: Not stated | C73: 445 | D73: . .
A74: WA | B74: Total | C74: 24993 | D74: 100
A75: SA | B75: Australia (includes External Territories) | C75: 17289 | D75: 92.4
A76: SA | B76: Oceania and Antarctica | C76: 132 | D76: 0.7
A77: SA | B77: UK and Ireland | C77: 136 | D77: 0.7
A78: SA | B78: Western and Northern Europe | C78: 21 | D78: 0.1
A79: SA | B79: Southern and Eastern Europe | C79: 91 | D79: 0.5
A80: SA | B80: North Africa and the Middle East | C80: 218 | D80: 1.2
A81: SA | B81: South-East Asia | C81: 208 | D81: 1.1
A82: SA | B82: North-East Asia | C82: 63 | D82: 0.3
A83: SA | B83: Southern and Central Asia | C83: 263 | D83: 1.4
A84: SA | B84: Northern America | C84: 30 | D84: 0.2
A85: SA | B85: South and Central America and Carribean | C85: 59 | D85: 0.3
A86: SA | B86: Sub-Saharan Africa | C86: 201 | D86: 1.1
A87: SA | B87: Not stated | C87: 6 | D87: . .
A88: SA | B88: Total | C88: 18717 | D88: 100
A89: Tas | B89: Australia (includes External Territories) | C89: 5879 | D89: 93.4
A90: Tas | B90: Oceania and Antarctica | C90: 43 | D90: 0.7
A91: Tas | B91: UK and Ireland | C91: 68 | D91: 1.1
A92: Tas | B92: Western and Northern Europe | C92: 8 | D92: 0.1
A93: Tas | B93: Southern and Eastern Europe | C93: 25 | D93: 0.4
A94: Tas | B94: North Africa and the Middle East | C94: 35 | D94: 0.6
A95: Tas | B95: South-East Asia | C95: 45 | D95: 0.7
A96: Tas | B96: North-East Asia | C96: 11 | D96: 0.2
A97: Tas | B97: Southern and Central Asia | C97: 77 | D97: 1.2
A98: Tas | B98: Northern America | C98: 18 | D98: 0.3
A99: Tas | B99: South and Central America and Carribean | C99: 7 | D99: 0.1
A100: Tas | B100: Sub-Saharan Africa | C100: 78 | D100: 1.2
A101: Tas | B101: Not stated | C101: 378 | D101: . .
...

Sheet CLIENTS.4
A1: Table of contents
A2: Table CLIENTS.4: Clients by country of birth (top 10), and by state and territory, 2023–24
A4: State/ territory | B4: Country of birth | C4: Clients | D4: Per cent
A5: National | B5: Australia | C5: 236810 | D5: 86.5
A6: National | B6: New Zealand | C6: 4543 | D6: 1.7
A7: National | B7: England | C7: 1727 | D7: 0.6
A8: National | B8: India | C8: 1620 | D8: 0.6
A9: National | B9: Afghanistan | C9: 1563 | D9: 0.6
A10: National | B10: Sudan | C10: 1461 | D10: 0.5
A11: National | B11: Philippines | C11: 1361 | D11: 0.5
A12: National | B12: Iran | C12: 1242 | D12: 0.5
A13: National | B13: Vietnam | C13: 1030 | D13: 0.4
A14: National | B14: China (excludes SARs(a) and Taiwan) | C14: 1030 | D14: 0.4
A15: National | B15: Others | C15: 21327 | D15: 7.8
A16: National | B16: Not stated | C16: 6364 | D16: . .
A17: National | B17: Total clients | C17: 280078 | D17: 100
A18: NSW | B18: Australia | C18: 58685 | D18: 88.4
A19: NSW | B19: New Zealand | C19: 955 | D19: 1.4
A20: NSW | B20: Philippines | C20: 402 | D20: 0.6
A21: NSW | B21: England | C21: 341 | D21: 0.5
A22: NSW | B22: Lebanon | C22: 340 | D22: 0.5
A23: NSW | B23: Iraq | C23: 274 | D23: 0.4
A24: NSW | B24: Afghanistan | C24: 273 | D24: 0.4
A25: NSW | B25: Iran | C25: 273 | D25: 0.4
A26: NSW | B26: China (excludes SARs(a) and Taiwan) | C26: 263 | D26: 0.4
A27: NSW | B27: Fiji | C27: 253 | D27: 0.4
A28: NSW | B28: Others | C28: 4338 | D28: 6.5
A29: NSW | B29: Not stated | C29: 1494 | D29: . .
A30: NSW | B30: Total clients | C30: 67891 | D30: 100
A31: Vic | B31: Australia | C31: 80984 | D31: 81.6
A32: Vic | B32: New Zealand | C32: 1704 | D32: 1.7
A33: Vic | B33: India | C33: 1000 | D33: 1
A34: Vic | B34: Sudan | C34: 995 | D34: 1
A35: Vic | B35: Afghanistan | C35: 970 | D35: 1
A36: Vic | B36: Iran | C36: 729 | D36: 0.7
A37: Vic | B37: Ethiopia | C37: 694 | D37: 0.7
A38: Vic | B38: Vietnam | C38: 672 | D38: 0.7
A39: Vic | B39: England | C39: 618 | D39: 0.6
A40: Vic | B40: Somalia | C40: 585 | D40: 0.6
A41: Vic | B41: Others | C41: 10337 | D41: 10.4
A42: Vic | B42: Not stated | C42: 2676 | D42: . .
A43: Vic | B43: Total clients | C43: 101964 | D43: 100
A44: Qld | B44: Australia | C44: 42246 | D44: 88.5
A45: Qld | B45: New Zealand | C45: 1314 | D45: 2.8
A46: Qld | B46: Papua New Guinea | C46: 440 | D46: 0.9
A47: Qld | B47: England | C47: 296 | D47: 0.6
A48: Qld | B48: Philippines | C48: 220 | D48: 0.5
A49: Qld | B49: India | C49: 150 | D49: 0.3
A50: Qld | B50: Iran | C50: 121 | D50: 0.3
A51: Qld | B51: Sudan | C51: 119 | D51: 0.2
A52: Qld | B52: Ethiopia | C52: 115 | D52: 0.2
A53: Qld | B53: Somalia | C53: 111 | D53: 0.2
A54: Qld | B54: Others | C54: 2620 | D54: 5.5
A55: Qld | B55: Not stated | C55: 1066 | D55: . .
A56: Qld | B56: Total clients | C56: 48818 | D56: 100
A57: WA | B57: Australia | C57: 21838 | D57: 89
A58: WA | B58: New Zealand | C58: 430 | D58: 1.8
A59: WA | B59: England | C59: 284 | D59: 1.2
A60: WA | B60: India | C60: 113 | D60: 0.5
A61: WA | B61: Philippines | C61: 102 | D61: 0.4
A62: WA | B62: China (excludes SARs(a) and Taiwan) | C62: 98 | D62: 0.4
A63: WA | B63: South Africa | C63: 80 | D63: 0.3
A64: WA | B64: Sudan | C64: 69 | D64: 0.3
A65: WA | B65: Malaysia | C65: 62 | D65: 0.3
A66: WA | B66: Afghanistan | C66: 56 | D66: 0.2
A67: WA | B67: Others | C67: 1416 | D67: 5.8
A68: WA | B68: Not stated | C68: 445 | D68: . .
A69: WA | B69: Total clients | C69: 24993 | D69: 100
A70: SA | B70: Australia | C70: 17289 | D70: 92.4
A71: SA | B71: England | C71: 115 | D71: 0.6
A72: SA | B72: New Zealand | C72: 103 | D72: 0.6
A73: SA | B73: India | C73: 93 | D73: 0.5
A74: SA | B74: Afghanistan | C74: 84 | D74: 0.4
A75: SA | B75: Philippines | C75: 70 | D75: 0.4
A76: SA | B76: Sudan | C76: 60 | D76: 0.3
A77: SA | B77: Iran | C77: 50 | D77: 0.3
A78: SA | B78: Pakistan | C78: 40 | D78: 0.2
A79: SA | B79: China (excludes SARs(a) and Taiwan) | C79: 40 | D79: 0.2
A80: SA | B80: Others | C80: 767 | D80: 4.1
A81: SA | B81: Not stated | C81: 6 | D81: . .
A82: SA | B82: Total clients | C82: 18717 | D82: 100
A83: Tas | B83: Australia | C83: 5877 | D83: 93.4
A84: Tas | B84: England | C84: 57 | D84: 0.9
A85: Tas | B85: Afghanistan | C85: 45 | D85: 0.7
A86: Tas | B86: Ethiopia | C86: 37 | D86: 0.6
A87: Tas | B87: New Zealand | C87: 30 | D87: 0.5
A88: Tas | B88: Philippines | C88: 25 | D88: 0.4
A89: Tas | B89: Eritrea | C89: 17 | D89: 0.3
A90: Tas | B90: United States of America | C90: 11 | D90: 0.2
A91: Tas | B91: India | C91: 11 | D91: 0.2
A92: Tas | B92: Sudan | C92: 9 | D92: 0.1
A93: Tas | B93: Others | C93: 175 | D93: 2.8
A94: Tas | B94: Not stated | C94: 378 | D94: . .
A95: Tas | B95: Total clients | C95: 6672 | D95: 100
A96: ACT | B96: Australia | C96: 3052 | D96: 77.3
A97: ACT | B97: Sudan | C97: 65 | D97: 1.6
A98: ACT | B98: Sri Lanka | C98: 45 | D98: 1.1
A99: ACT | B99: Afghanistan | C99: 37 | D99: 0.9
A100: ACT | B100: South Sudan | C100: 33 | D100: 0.8
A101: ACT | B101: New Zealand | C101: 32 | D101: 0.8
...

Sheet CLIENTS.5
A1: Table of contents
A2: Table CLIENTS.5: Clients born overseas, by year of arrival, 2023–24
A4: Year of arrival | B4: Number | C4: Per cent
A5: 2020 – 2024 | B5: 4558 | C5: 16.1
A6: 2015 – 2019 | B6: 5413 | C6: 19.1
A7: 2014 or before | B7: 18398 | C7: 64.9
A8: Not stated | B8: 8415 | C8: . .
A9: Total | B9: 36784 | C9: 100
A11: Notes
A12: 1. Excludes clients whose country of birth was Australia (including External Territories) or whose country of birth was not stated.
A13: 2. Per cent calculations based on total clients less 'Not stated'.
A14: . . not applicable

Sheet CLIENTS.6
A1: Table of contents
A2: Table CLIENTS.6: Clients born overseas, by Remoteness Area, 2023–24
A4: Remoteness Area | B4: Number | C4: Per cent
A5: Major cities | B5: 32072 | C5: 87.2
A6: Inner regional | B6: 3067 | C6: 8.3
A7: Outer regional | B7: 1417 | C7: 3.9
A8: Remote | B8: 171 | C8: 0.5
A9: Very remote | B9: 57 | C9: 0.2
A10: Total | B10: 36784 | C10: 100
A12: Notes
A13: 1. Remoteness Area is assigned using the Australian Bureau of Statistics classification, Australian Statistical Geography Standard (ASGS), 2021.
A14: 2. Agencies participating in the SHSC are assigned to a Statistical Area 2 (SA2) based on their postcode, suburb, and state. SA2 is then mapped to Remoteness Area using a second concordance. Clients are assigned a Remoteness Area based on the SHS agency where they first sought support.
A15: 3. Excludes clients whose country of birth was Australia (including External Territories) or whose country of birth was not stated.

Sheet CLIENTS.7
A1: Table of contents
A2: Table CLIENTS.7: Clients by main language spoken at home other than English (top 10), 2023–24
A4: Main language spoken at home | B4: Number | C4: Per cent
A5: Aboriginal English so described | B5: 8910 | C5: 21.3
A6: Arabic | B6: 4641 | C6: 11.1
A7: Persian (excluding Dari) | B7: 1141 | C7: 2.7
A8: Dari | B8: 1116 | C8: 2.7
A9: Vietnamese | B9: 1102 | C9: 2.6
A10: Somali | B10: 1040 | C10: 2.5
A11: Mandarin | B11: 922 | C11: 2.2
A12: Spanish | B12: 859 | C12: 2.1
A13: Dinka | B13: 846 | C13: 2
A14: Other Australian Indigenous Languages nec | B14: 788 | C14: 1.9
A15: Northern European Languages (excluding English) (balance of) | B15: 408 | C15: 1
A16: Southern European Languages (balance of) | B16: 1331 | C16: 3.2
... A24: Other Languages (excluding African Languages)(b) | B24: 2114 | C24: 5
A25: English only | B25: 223163 | C25: . .
A26: Not stated | B26: 13614 | C26: . .
A27: Total | B27: 278676 | C27: 100
A29: (a) 'African Languages' is a narrow group classification of languages under the broad group 'Other Languages'.
A30: (b) 'Other Languages (excluding African Languages)' includes all other narrow groups under the broad group 'Other Languages'.
A31: Notes
A32: 1. Languages and broad groups of languages are based on the Australian Standard Classification of Languages (ASCL), 2016 (ABS Catalogue 1267.0).
A33: 2. The top 10 main languages spoken at home other than English are listed in descending order.
A34: 3. 'Balance of' refers to the remainder of languages in the broad groups excluding those already listed in the top 10.
A35: 4. Percentages are calculated using total clients excluding those whose main language spoken at home was not stated or English only.
A36: 5. Excludes 1,402 clients who only had support period(s) starting before 1 July 2019.
A37: . . not applicable

Sheet CLIENTS.8
A1: Table of contents
A2: Table CLIENTS.8: Clients by broad group of main language spoken at home (other than English) and proficiency of spoken English, 2023–24
A4: Data type | B4: Main language other than English spoken at home | C4: Very well | D4: Well | E4: Not well | F4: Not at all | G4: Not stated
A5: Number | B5: Northern European Languages (excluding English) | C5: 276 | D5: 79 | E5: 10 | F5: 31 | G5: —
A6: Number | B6: Southern European Languages | C6: 1099 | D6: 561 | E6: 240 | F6: 51 | G6: 149
A7: Number | B7: Eastern European Languages | C7: 596 | D7: 329 | E7: 156 | F7: 56 | G7: 78
A8: Number | B8: Southwest And Central Asian Languages | C8: 2219 | D8: 2167 | E8: 1776 | F8: 653 | G8: 904
A9: Number | B9: Southern Asian Languages | C9: 1001 | D9: 1069 | E9: 356 | F9: 55 | G9: 219
A10: Number | B10: Southeast Asian Languages | C10: 1054 | D10: 1242 | E10: 814 | F10: 213 | G10: 394
A11: Number | B11: Eastern Asian Languages | C11: 423 | D11: 554 | E11: 467 | F11: 193 | G11: 145
A12: Number | B12: Australian Indigenous Languages | C12: 3974 | D12: 7967 | E12: 469 | F12: 42 | G12: 612
A13: Number | B13: African Languages(a) | C13: 1363 | D13: 1432 | E13: 726 | F13: 217 | G13: 406
A14: Number | B14: Other Languages (excluding African Languages)(b) | C14: 1029 | D14: 609 | E14: 110 | F14: 35 | G14: 167
A15: Per cent | B15: Northern European Languages (excluding English) | C15: 69.7 | D15: 19.9 | E15: 2.5 | F15: 7.8 | G15: . .
A16: Per cent | B16: Southern European Languages | C16: 56.3 | D16: 28.8 | E16: 12.3 | F16: 2.6 | G16: . .
A17: Per cent | B17: Eastern European Languages | C17: 52.4 | D17: 28.9 | E17: 13.7 | F17: 4.9 | G17: . .
A18: Per cent | B18: Southwest And Central Asian Languages | C18: 32.6 | D18: 31.8 | E18: 26.1 | F18: 9.6 | G18: . .
A19: Per cent | B19: Southern Asian Languages | C19: 40.3 | D19: 43.1 | E19: 14.3 | F19: 2.2 | G19: . .
A20: Per cent | B20: Southeast Asian Languages | C20: 31.7 | D20: 37.4 | E20: 24.5 | F20: 6.4 | G20: . .
A21: Per cent | B21: Eastern Asian Languages | C21: 25.8 | D21: 33.8 | E21: 28.5 | F21: 11.8 | G21: . .
A22: Per cent | B22: Australian Indigenous Languages | C22: 31.9 | D22: 64 | E22: 3.8 | F22: 0.3 | G22: . .
A23: Per cent | B23: African Languages(a) | C23: 36.5 | D23: 38.3 | E23: 19.4 | F23: 5.8 | G23: . .
A24: Per cent | B24: Other Languages (excluding African Languages)(b) | C24: 57.7 | D24: 34.2 | E24: 6.2 | F24: 2 | G24: . .
A26: (a) 'African Languages' is a narrow group classification of languages under the broad group 'Other Languages'.
A27: (b) 'Other Languages (excluding African Languages)' includes all other narrow groups under the broad group 'Other Languages'.
A28: Notes
A29: 1. Broad groups of languages are based on the Australian Standard Classification of Languages (ASCL), 2016 (ABS Catalogue 1267.0).
A30: 2. Percentages are calculated using clients by broad language group as the denominator, excluding those whose proficiency in spoken English was not stated.
A31: 3. Excludes 1,402 clients who only had support period(s) starting before 1 July 2019.
A32: 4. Excludes clients whose main language spoken at home was English or who were under 5 years of age.
A33: . . not applicable

Sheet CLIENTS.9
A1: Table of contents
A2: Table CLIENTS.9: Clients, by presenting unit type at the beginning of support, and by state and territory, 2023–24
A4: State/territory | B4: Presenting unit type | C4: Number | D4: Per cent
A5: National | B5: Alone/not part of family | C5: 177806 | D5: 63.5
A6: National | B6: Couple with child/ren | C6: 12448 | D6: 4.4
A7: National | B7: Single with child/ren | C7: 80027 | D7: 28.6
A8: National | B8: Couple without children | C8: 5652 | D8: 2
A9: National | B9: Other family group | C9: 2154 | D9: 0.8
A10: National | B10: Other group | C10: 1991 | D10: 0.7
A11: National | B11: Total | C11: 280078 | D11: 100
A12: NSW | B12: Alone/not part of family | C12: 42012 | D12: 61.9
A13: NSW | B13: Couple with child/ren | C13: 2536 | D13: 3.7
A14: NSW | B14: Single with child/ren | C14: 21213 | D14: 31.2
A15: NSW | B15: Couple without children | C15: 1234 | D15: 1.8
A16: NSW | B16: Other family group | C16: 550 | D16: 0.8
... A67: NT | B67: Total | C67: 10080 | D67: 100
A69: Notes
A70: 1. The presenting unit type at the beginning of support. This data item indicates the group of people with whom the client presents to the Specialist Homelessness Services agency. After identifying the presenting unit head, the client identifies the relationship to that unit head.
A71: 2. For data quality issues, refer to the Explanatory Notes.

Sheet CLIENTS.10
A1: Table of contents
A2: Table CLIENTS.10: Clients, by living arrangement, and by state and territory, 2023–24
C4: Males | D4: Males | E4: Females | F4: Females | G4: All clients | H4: All clients
A5: State/territory | B5: Living Arrangement | C5: Number | D5: Per cent | E5: Number | F5: Per cent | G5: Number | H5: Per cent
A6: National | B6: Lone person | C6: 48122 | D6: 44.3 | E6: 42842 | F6: 26.7 | G6: 90964 | H6: 33.8
A7: National | B7: One parent with child/ren | C7: 26689 | D7: 24.6 | E7: 65630 | F7: 40.9 | G7: 92319 | H7: 34.3
A8: National | B8: Couple with child/ren | C8: 10839 | D8: 10 | E8: 16974 | F8: 10.6 | G8: 27813 | H8: 10.3
A9: National | B9: Couple without child/ren | C9: 4723 | D9: 4.4 | E9: 7337 | F9: 4.6 | G9: 12060 | H9: 4.5
A10: National | B10: Other family | C10: 12198 | D10: 11.2 | E10: 20045 | F10: 12.5 | G10: 32243 | H10: 12
A11: National | B11: Group | C11: 5985 | D11: 5.5 | E11: 7648 | F11: 4.8 | G11: 13633 | H11: 5.1
A12: National | B12: Not stated | C12: 4317 | D12: . . | E12: 6729 | F12: . . | G12: 11046 | H12: . .
A13: National | B13: Total | C13: 112873 | D13: 100 | E13: 167205 | F13: 100 | G13: 280078 | H13: 100
A14: NSW | B14: Lone person | C14: 12165 | D14: 46.5 | E14: 11931 | F14: 30.4 | G14: 24096 | H14: 36.9
A15: NSW | B15: One parent with child/ren | C15: 6918 | D15: 26.5 | E15: 16329 | F15: 41.7 | G15: 23247 | H15: 35.6
A16: NSW | B16: Couple with child/ren | C16: 2445 | D16: 9.4 | E16: 3647 | F16: 9.3 | G16: 6092 | H16: 9.3
A17: NSW | B17: Couple without child/ren | C17: 1089 | D17: 4.2 | E17: 1661 | F17: 4.2 | G17: 2750 | H17: 4.2
A18: NSW | B18: Other family | C18: 2435 | D18: 9.3 | E18: 4091 | F18: 10.4 | G18: 6526 | H18: 10
A19: NSW | B19: Group | C19: 1082 | D19: 4.1 | E19: 1529 | F19: 3.9 | G19: 2611 | H19: 4
A20: NSW | B20: Not stated | C20: 1352 | D20: . . | E20: 1217 | F20: . . | G20: 2569 | H20: . .
A21: NSW | B21: Total | C21: 27486 | D21: 100 | E21: 40405 | F21: 100 | G21: 67891 | H21: 100
A22: Vic | B22: Lone person | C22: 18856 | D22: 46.5 | E22: 14949 | F22: 26.8 | G22: 33805 | H22: 35.1
A23: Vic | B23: One parent with child/ren | C23: 9395 | D23: 23.2 | E23: 23237 | F23: 41.6 | G23: 32632 | H23: 33.8
A24: Vic | B24: Couple with child/ren | C24: 3703 | D24: 9.1 | E24: 5746 | F24: 10.3 | G24: 9449 | H24: 9.8
A25: Vic | B25: Couple without child/ren | C25: 1853 | D25: 4.6 | E25: 2737 | F25: 4.9 | G25: 4590 | H25: 4.8
A26: Vic | B26: Other family | C26: 4248 | D26: 10.5 | E26: 6439 | F26: 11.5 | G26: 10687 | H26: 11.1
A27: Vic | B27: Group | C27: 2503 | D27: 6.2 | E27: 2737 | F27: 4.9 | G27: 5240 | H27: 5.4
A28: Vic | B28: Not stated | C28: 1874 | D28: . . | E28: 3687 | F28: . . | G28: 5561 | H28: . .
A29: Vic | B29: Total | C29: 42432 | D29: 100 | E29: 59532 | F29: 100 | G29: 101964 | H29: 100
A30: Qld | B30: Lone person | C30: 8133 | D30: 41.6 | E30: 7164 | F30: 25.4 | G30: 15297 | H30: 32.1
A31: Qld | B31: One parent with child/ren | C31: 5656 | D31: 28.9 | E31: 12903 | F31: 45.8 | G31: 18559 | H31: 38.9
A32: Qld | B32: Couple with child/ren | C32: 2421 | D32: 12.4 | E32: 3195 | F32: 11.3 | G32: 5616 | H32: 11.8
A33: Qld | B33: Couple without child/ren | C33: 881 | D33: 4.5 | E33: 1158 | F33: 4.1 | G33: 2039 | H33: 4.3
A34: Qld | B34: Other family | C34: 1702 | D34: 8.7 | E34: 2669 | F34: 9.5 | G34: 4371 | H34: 9.2
A35: Qld | B35: Group | C35: 776 | D35: 4 | E35: 1065 | F35: 3.8 | G35: 1841 | H35: 3.9
A36: Qld | B36: Not stated | C36: 434 | D36: . . | E36: 661 | F36: . . | G36: 1095 | H36: . .
A37: Qld | B37: Total | C37: 20003 | D37: 100 | E37: 28815 | F37: 100 | G37: 48818 | H37: 100
A38: WA | B38: Lone person | C38: 2618 | D38: 32.3 | E38: 3151 | F38: 19.8 | G38: 5769 | H38: 24.1
A39: WA | B39: One parent with child/ren | C39: 1924 | D39: 23.7 | E39: 6165 | F39: 38.8 | G39: 8089 | H39: 33.7
A40: WA | B40: Couple with child/ren | C40: 843 | D40: 10.4 | E40: 1801 | F40: 11.3 | G40: 2644 | H40: 11
A41: WA | B41: Couple without child/ren | C41: 316 | D41: 3.9 | E41: 712 | F41: 4.5 | G41: 1028 | H41: 4.3
A42: WA | B42: Other family | C42: 1890 | D42: 23.3 | E42: 3368 | F42: 21.2 | G42: 5258 | H42: 21.9
A43: WA | B43: Group | C43: 514 | D43: 6.3 | E43: 684 | F43: 4.3 | G43: 1198 | H43: 5
A44: WA | B44: Not stated | C44: 421 | D44: . . | E44: 586 | F44: . . | G44: 1007 | H44: . .
A45: WA | B45: Total | C45: 8526 | D45: 100 | E45: 16467 | F45: 100 | G45: 24993 | H45: 100
A46: SA | B46: Lone person | C46: 2821 | D46: 37.8 | E46: 2634 | F46: 24.2 | G46: 5455 | H46: 29.7
A47: SA | B47: One parent with child/ren | C47: 1611 | D47: 21.6 | E47: 3842 | F47: 35.3 | G47: 5453 | H47: 29.7
A48: SA | B48: Couple with child/ren | C48: 879 | D48: 11.8 | E48: 1451 | F48: 13.3 | G48: 2330 | H48: 12.7
A49: SA | B49: Couple without child/ren | C49: 369 | D49: 4.9 | E49: 641 | F49: 5.9 | G49: 1010 | H49: 5.5
A50: SA | B50: Other family | C50: 1105 | D50: 14.8 | E50: 1728 | F50: 15.9 | G50: 2833 | H50: 15.4
A51: SA | B51: Group | C51: 684 | D51: 9.2 | E51: 602 | F51: 5.5 | G51: 1286 | H51: 7
A52: SA | B52: Not stated | C52: 142 | D52: . . | E52: 208 | F52: . . | G52: 350 | H52: . .
A53: SA | B53: Total | C53: 7611 | D53: 100 | E53: 11106 | F53: 100 | G53: 18717 | H53: 100
A54: Tas | B54: Lone person | C54: 1795 | D54: 61.2 | E54: 1375 | F54: 37.6 | G54: 3170 | H54: 48.1
A55: Tas | B55: One parent with child/ren | C55: 471 | D55: 16.1 | E55: 1345 | F55: 36.8 | G55: 1816 | H55: 27.6
A56: Tas | B56: Couple with child/ren | C56: 126 | D56: 4.3 | E56: 226 | F56: 6.2 | G56: 352 | H56: 5.3
A57: Tas | B57: Couple without child/ren | C57: 110 | D57: 3.8 | E57: 167 | F57: 4.6 | G57: 277 | H57: 4.2
A58: Tas | B58: Other family | C58: 219 | D58: 7.5 | E58: 299 | F58: 8.2 | G58: 518 | H58: 7.9
A59: Tas | B59: Group | C59: 211 | D59: 7.2 | E59: 247 | F59: 6.8 | G59: 458 | H59: 6.9
A60: Tas | B60: Not stated | C60: 43 | D60: . . | E60: 38 | F60: . . | G60: 81 | H60: . .
A61: Tas | B61: Total | C61: 2975 | D61: 100 | E61: 3697 | F61: 100 | G61: 6672 | H61: 100
A62: ACT | B62: Lone person | C62: 1043 | D62: 59.8 | E62: 894 | F62: 40.2 | G62: 1937 | H62: 48.8
A63: ACT | B63: One parent with child/ren | C63: 347 | D63: 19.9 | E63: 878 | F63: 39.5 | G63: 1225 | H63: 30.9
A64: ACT | B64: Couple with child/ren | C64: 131 | D64: 7.5 | E64: 169 | F64: 7.6 | G64: 300 | H64: 7.6
A65: ACT | B65: Couple without child/ren | C65: 45 | D65: 2.6 | E65: 57 | F65: 2.6 | G65: 102 | H65: 2.6
A66: ACT | B66: Other family | C66: 110 | D66: 6.3 | E66: 155 | F66: 7 | G66: 265 | H66: 6.7
A67: ACT | B67: Group | C67: 68 | D67: 3.9 | E67: 71 | F67: 3.2 | G67: 139 | H67: 3.5
A68: ACT | B68: Not stated | C68: 6 | D68: . . | E68: 32 | F68: . . | G68: 38 | H68: . .
A69: ACT | B69: Total | C69: 1750 | D69: 100 | E69: 2256 | F69: 100 | G69: 4006 | H69: 100
A70: NT | B70: Lone person | C70: 1540 | D70: 46.8 | E70: 1371 | F70: 21.6 | G70: 2911 | H70: 30.2
A71: NT | B71: One parent with child/ren | C71: 493 | D71: 15 | E71: 1515 | F71: 23.9 | G71: 2008 | H71: 20.9
A72: NT | B72: Couple with child/ren | C72: 354 | D72: 10.8 | E72: 881 | F72: 13.9 | G72: 1235 | H72: 12.8
A73: NT | B73: Couple without child/ren | C73: 119 | D73: 3.6 | E73: 318 | F73: 5 | G73: 437 | H73: 4.5
A74: NT | B74: Other family | C74: 564 | D74: 17.1 | E74: 1450 | F74: 22.9 | G74: 2014 | H74: 20.9
A75: NT | B75: Group | C75: 219 | D75: 6.7 | E75: 803 | F75: 12.7 | G75: 1022 | H75: 10.6
A76: NT | B76: Not stated | C76: 89 | D76: . . | E76: 364 | F76: . . | G76: 453 | H76: . .
A77: NT | B77: Total | C77: 3378 | D77: 100 | E77: 6702 | F77: 100 | G77: 10080 | H77: 100
A79: Notes
A80: 1. The living arrangement at the beginning of support. This data item indicates the group of people with whom the client lives.
A81: 2. Per cent calculations based on total clients less 'Not stated'.
A82: . . not applicable

Sheet CLIENTS.11
A1: Table of contents
A2: Table CLIENTS.11: Clients, by housing situation at first presentation, and by state and territory, 2023–24
A4: State/territory | B4: Homeless/At risk | C4: Housing situation | D4: Males | E4: Females | F4: All clients (number) | G4: All clients (per cent)
A5: National | B5: Homeless | C5: Homeless | G5: 47.6
A6: National | B6: Homeless | C6: No shelter or improvised/inadequate dwelling | D6: 18836 | E6: 12385 | F6: 31221 | G6: 11.1
A7: National | B7: Homeless | C7: Short-term temporary accommodation | D7: 22829 | E7: 28961 | F7: 51790 | G7: 18.5
A8: National | B8: Homeless | C8: House, townhouse or flat — couch surfer or with no tenure | D8: 16044 | E8: 24494 | F8: 40538 | G8: 14.5
A9: National | B9: Homeless | C9: Other | D9: 850 | E9: 882 | F9: 1732 | G9: 0.6
A10: National | B10: At risk | C10: At risk | G10: 52.4
A11: National | B11: At risk | C11: Public or community housing — renter or rent free | D11: 12298 | E11: 24713 | F11: 37011 | G11: 13.2
A12: National | B12: At risk | C12: Private or other housing — renter, rent free or owner | D12: 29073 | E12: 60018 | F12: 89091 | G12: 31.8
A13: National | B13: At risk | C13: Institutional settings | D13: 6393 | E13: 2538 | F13: 8931 | G13: 3.2
A14: National | B14: At risk | C14: Other | D14: 1138 | E14: 1974 | F14: 3112 | G14: 1.1
A15: National | B15: Not stated | C15: Not stated | D15: 5412 | E15: 11240 | F15: 16652 | G15: 5.9
A16: National | B16: Total | C16: Total | D16: 112873 | E16: 167205 | F16: 280078 | G16: 100
A17: NSW | B17: Homeless | C17: Homeless | G17: 52.6
A18: NSW | B18: Homeless | C18: No shelter or improvised/inadequate dwelling | D18: 3369 | E18: 2063 | F18: 5432 | G18: 8
A19: NSW | B19: Homeless | C19: Short-term temporary accommodation | D19: 8185 | E19: 9711 | F19: 17896 | G19: 26.4
A20: NSW | B20: Homeless | C20: House, townhouse or flat — couch surfer or with no tenure | D20: 4079 | E20: 6423 | F20: 10502 | G20: 15.5
A21: NSW | B21: Homeless | C21: Other | D21: 137 | E21: 131 | F21: 268 | G21: 0.4
A22: NSW | B22: At risk | C22: At risk | G22: 47.4
A23: NSW | B23: At risk | C23: Public or community housing — renter or rent free | D23: 2709 | E23: 4993 | F23: 7702 | G23: 11.3
A24: NSW | B24: At risk | C24: Private or other housing — renter, rent free or owner | D24: 6736 | E24: 14206 | F24: 20942 | G24: 30.8
A25: NSW | B25: At risk | C25: Institutional settings | D25: 791 | E25: 637 | F25: 1428 | G25: 2.1
A26: NSW | B26: At risk | C26: Other | D26: 271 | E26: 386 | F26: 657 | G26: 1
A27: NSW | B27: Not stated | C27: Not stated | D27: 1209 | E27: 1855 | F27: 3064 | G27: 4.5
A28: NSW | B28: Total | C28: Total | D28: 27486 | E28: 40405 | F28: 67891 | G28: 100
A29: Vic | B29: Homeless | C29: Homeless | G29: 40.4
A30: Vic | B30: Homeless | C30: No shelter or improvised/inadequate dwelling | D30: 6318 | E30: 3421 | F30: 9739 | G30: 9.6
A31: Vic | B31: Homeless | C31: Short-term temporary accommodation | D31: 6597 | E31: 7922 | F31: 14519 | G31: 14.2
A32: Vic | B32: Homeless | C32: House, townhouse or flat — couch surfer or with no tenure | D32: 5389 | E32: 7086 | F32: 12475 | G32: 12.2
A33: Vic | B33: Homeless | C33: Other | D33: 339 | E33: 298 | F33: 637 | G33: 0.6
A34: Vic | B34: At risk | C34: At risk | G34: 59.6
A35: Vic | B35: At risk | C35: Public or community housing — renter or rent free | D35: 3256 | E35: 6053 | F35: 9309 | G35: 9.1
A36: Vic | B36: At risk | C36: Private or other housing — renter, rent free or owner | D36: 13038 | E36: 26324 | F36: 39362 | G36: 38.6
A37: Vic | B37: At risk | C37: Institutional settings | D37: 4282 | E37: 999 | F37: 5281 | G37: 5.2
A38: Vic | B38: At risk | C38: Other | D38: 410 | E38: 785 | F38: 1195 | G38: 1.2
A39: Vic | B39: Not stated | C39: Not stated | D39: 2803 | E39: 6644 | F39: 9447 | G39: 9.3
A40: Vic | B40: Total | C40: Total | D40: 42432 | E40: 59532 | F40: 101964 | G40: 100
A41: Qld | B41: Homeless | C41: Homeless | G41: 55.8
A42: Qld | B42: Homeless | C42: No shelter or improvised/inadequate dwelling | D42: 4694 | E42: 3447 | F42: 8141 | G42: 16.7
A43: Qld | B43: Homeless | C43: Short-term temporary accommodation | D43: 4031 | E43: 5611 | F43: 9642 | G43: 19.8
A44: Qld | B44: Homeless | C44: House, townhouse or flat — couch surfer or with no tenure | D44: 3112 | E44: 5043 | F44: 8155 | G44: 16.7
A45: Qld | B45: Homeless | C45: Other | D45: 216 | E45: 265 | F45: 481 | G45: 1
A46: Qld | B46: At risk | C46: At risk | G46: 44.2
A47: Qld | B47: At risk | C47: Public or community housing — renter or rent free | D47: 2212 | E47: 4314 | F47: 6526 | G47: 13.4
A48: Qld | B48: At risk | C48: Private or other housing — renter, rent free or owner | D48: 4692 | E48: 8582 | F48: 13274 | G48: 27.2
A49: Qld | B49: At risk | C49: Institutional settings | D49: 378 | E49: 339 | F49: 717 | G49: 1.5
A50: Qld | B50: At risk | C50: Other | D50: 129 | E50: 244 | F50: 373 | G50: 0.8
A51: Qld | B51: Not stated | C51: Not stated | D51: 539 | E51: 970 | F51: 1509 | G51: 3.1
A52: Qld | B52: Total | C52: Total | D52: 20003 | E52: 28815 | F52: 48818 | G52: 100
A53: WA | B53: Homeless | C53: Homeless | G53: 42.3
A54: WA | B54: Homeless | C54: No shelter or improvised/inadequate dwelling | D54: 1573 | E54: 1410 | F54: 2983 | G54: 11.9
A55: WA | B55: Homeless | C55: Short-term temporary accommodation | D55: 1422 | E55: 2489 | F55: 3911 | G55: 15.6
A56: WA | B56: Homeless | C56: House, townhouse or flat — couch surfer or with no tenure | D56: 1047 | E56: 2034 | F56: 3081 | G56: 12.3
A57: WA | B57: Homeless | C57: Other | D57: 21 | E57: 39 | F57: 60 | G57: 0.2
A58: WA | B58: At risk | C58: At risk | G58: 57.7
A59: WA | B59: At risk | C59: Public or community housing — renter or rent free | D59: 2208 | E59: 4864 | F59: 7072 | G59: 28.3
A60: WA | B60: At risk | C60: Private or other housing — renter, rent free or owner | D60: 1556 | E60: 4569 | F60: 6125 | G60: 24.5
A61: WA | B61: At risk | C61: Institutional settings | D61: 170 | E61: 136 | F61: 306 | G61: 1.2
A62: WA | B62: At risk | C62: Other | D62: 53 | E62: 132 | F62: 185 | G62: 0.7
A63: WA | B63: Not stated | C63: Not stated | D63: 476 | E63: 794 | F63: 1270 | G63: 5.1
A64: WA | B64: Total | C64: Total | D64: 8526 | E64: 16467 | F64: 24993 | G64: 100
A65: SA | B65: Homeless | C65: Homeless | G65: 47.2
A66: SA | B66: Homeless | C66: No shelter or improvised/inadequate dwelling | D66: 1413 | E66: 931 | F66: 2344 | G66: 12.5
A67: SA | B67: Homeless | C67: Short-term temporary accommodation | D67: 1279 | E67: 1489 | F67: 2768 | G67: 14.8
A68: SA | B68: Homeless | C68: House, townhouse or flat — couch surfer or with no tenure | D68: 1314 | E68: 2005 | F68: 3319 | G68: 17.7
A69: SA | B69: Homeless | C69: Other | D69: 100 | E69: 88 | F69: 188 | G69: 1
A70: SA | B70: At risk | C70: At risk | G70: 52.8
A71: SA | B71: At risk | C71: Public or community housing — renter or rent free | D71: 663 | E71: 1393 | F71: 2056 | G71: 11
A72: SA | B72: At risk | C72: Private or other housing — renter, rent free or owner | D72: 2043 | E72: 4377 | F72: 6420 | G72: 34.3
A73: SA | B73: At risk | C73: Institutional settings | D73: 427 | E73: 220 | F73: 647 | G73: 3.5
A74: SA | B74: At risk | C74: Other | D74: 207 | E74: 294 | F74: 501 | G74: 2.7
A75: SA | B75: Not stated | C75: Not stated | D75: 165 | E75: 309 | F75: 474 | G75: 2.5
A76: SA | B76: Total | C76: Total | D76: 7611 | E76: 11106 | F76: 18717 | G76: 100
A77: Tas | B77: Homeless | C77: Homeless | G77: 60.2
A78: Tas | B78: Homeless | C78: No shelter or improvised/inadequate dwelling | D78: 556 | E78: 374 | F78: 930 | G78: 13.9
A79: Tas | B79: Homeless | C79: Short-term temporary accommodation | D79: 587 | E79: 586 | F79: 1173 | G79: 17.6
A80: Tas | B80: Homeless | C80: House, townhouse or flat — couch surfer or with no tenure | D80: 684 | E80: 1100 | F80: 1784 | G80: 26.7
A81: Tas | B81: Homeless | C81: Other | D81: 19 | E81: 17 | F81: 36 | G81: 0.5
A82: Tas | B82: At risk | C82: At risk | G82: 39.8
A83: Tas | B83: At risk | C83: Public or community housing — renter or rent free | D83: 295 | E83: 407 | F83: 702 | G83: 10.5
A84: Tas | B84: At risk | C84: Private or other housing — renter, rent free or owner | D84: 539 | E84: 1037 | F84: 1576 | G84: 23.6
A85: Tas | B85: At risk | C85: Institutional settings | D85: 179 | E85: 80 | F85: 259 | G85: 3.9
A86: Tas | B86: At risk | C86: Other | D86: 25 | E86: 33 | F86: 58 | G86: 0.9
A87: Tas | B87: Not stated | C87: Not stated | D87: 91 | E87: 63 | F87: 154 | G87: 2.3
A88: Tas | B88: Total | C88: Total | D88: 2975 | E88: 3697 | F88: 6672 | G88: 100
A89: ACT | B89: Homeless | C89: Homeless | G89: 55.6
A90: ACT | B90: Homeless | C90: No shelter or improvised/inadequate dwelling | D90: 270 | E90: 145 | F90: 415 | G90: 10.4
A91: ACT | B91: Homeless | C91: Short-term temporary accommodation | D91: 455 | E91: 510 | F91: 965 | G91: 24.1
A92: ACT | B92: Homeless | C92: House, townhouse or flat — couch surfer or with no tenure | D92: 292 | E92: 461 | F92: 753 | G92: 18.8
A93: ACT | B93: Homeless | C93: Other | D93: 9 | E93: 6 | F93: 15 | G93: 0.4
A94: ACT | B94: At risk | C94: At risk | G94: 44.4
A95: ACT | B95: At risk | C95: Public or community housing — renter or rent free | D95: 290 | E95: 330 | F95: 620 | G95: 15.5
A96: ACT | B96: At risk | C96: Private or other housing — renter, rent free or owner | D96: 299 | E96: 598 | F96: 897 | G96: 22.4
A97: ACT | B97: At risk | C97: Institutional settings | D97: 74 | E97: 80 | F97: 154 | G97: 3.8
A98: ACT | B98: At risk | C98: Other | D98: 17 | E98: 24 | F98: 41 | G98: 1
A99: ACT | B99: Not stated | C99: Not stated | D99: 44 | E99: 102 | F99: 146 | G99: 3.6
A100: ACT | B100: Total | C100: Total | D100: 1750 | E100: 2256 | F100: 4006 | G100: 100
A101: NT | B101: Homeless | C101: Homeless | G101: 50.2
...

Sheet CLIENTS.12
A1: Table of contents
A2: Table CLIENTS.12: Clients, by homeless status at first presentation, by client groups, 2019–20 to 2023–24
A4: Data type | B4: Client group | C4: Homeless status first reported | D4: 2019–20 | E4: 2020–21 | F4: 2021–22 | G4: 2022–23 | H4: 2023–24
A5: Number | B5: All clients | C5: Homeless | D5: 116934 | E5: 114463 | F5: 113815 | G5: 119909 | H5: 125281
A6: Number | B6: All clients | C6: At risk | D6: 144303 | E6: 136553 | F6: 134468 | G6: 133992 | H6: 138145
A7: Number | B7: Indigenous clients | C7: Homeless | D7: 31538 | E7: 33374 | F7: 33199 | G7: 35226 | H7: 38290
A8: Number | B8: Indigenous clients | C8: At risk | D8: 35413 | E8: 35693 | F8: 35564 | G8: 35141 | H8: 36577
A9: Number | B9: Young people presenting alone | C9: Homeless | D9: 20430 | E9: 20462 | F9: 19599 | G9: 19839 | H9: 20577
A10: Number | B10: Young people presenting alone | C10: At risk | D10: 17632 | E10: 17390 | F10: 16415 | G10: 15939 | H10: 15525
A11: Number | B11: Children on a care and protection order | C11: Homeless | D11: 4056 | E11: 4013 | F11: 3850 | G11: 3880 | H11: 4206
A12: Number | B12: Children on a care and protection order | C12: At risk | D12: 4384 | E12: 3944 | F12: 3709 | G12: 3645 | H12: 3714
A13: Number | B13: Clients leaving care | C13: Homeless | D13: 1826 | E13: 1723 | F13: 1686 | G13: 1675 | H13: 1649
A14: Number | B14: Clients leaving care | C14: At risk | D14: 4799 | E14: 4510 | F14: 4235 | G14: 4360 | H14: 4473
A15: Number | B15: Clients exiting custodial arrangements | C15: Homeless | D15: 3126 | E15: 3105 | F15: 2940 | G15: 2732 | H15: 2666
A16: Number | B16: Clients exiting custodial arrangements | C16: At risk | D16: 6171 | E16: 5638 | F16: 5899 | G16: 6212 | H16: 6073
... A68: Per cent | B68: Clients in Remote/Very remote areas | C68: At risk | D68: 69.3 | E68: 69.5 | F68: 70.2 | G68: 68.3 | H68: 61.6
A70: Notes
A71: 1. Clients are considered to be homeless if they are living in any of the following circumstances: • No shelter or improvised dwelling: includes where dwelling type is no dwelling/street/park/in the open, motor vehicle, improvised building/dwelling, caravan, cabin, boat or tent; or tenure type is renting or living rent-free in a caravan park. • Short-term temporary accommodation: dwelling type is boarding/rooming house, emergency accommodation, hotel/motel/bed and breakfast; or tenure type is renting or living rent-free in boarding/rooming house, renting or living rent-free in emergency accommodation, or renting or living rent-free in transitional housing. • House, townhouse or flat (couch surfing or with no tenure): dwelling type is House/townhouse/flat, and tenure type is no tenure or conditions of occupancy is couch surfing.
A72: 2. Clients are considered to be at risk of homelessness if they are living in any of the following circumstances: • Public or community housing (renter or rent free): dwelling type is house/townhouse/flat and tenure type is renter or rent-free in public housing, or renter or rent-free in community housing. • Private or other housing (renter, rent-free or owner): dwelling type is house/townhouse/flat and tenure type is renter or rent free in private housing, life tenure scheme, owner-shared equity or rent/buy scheme, owner-being purchased/with mortgage, owner-fully owned, or other renter or rent free. • Institutional settings: dwelling type is hospital, psychiatric hospital/unit, disability support, rehabilitation, boarding school/residential college, adult correctional facility, youth/juvenile justice correctional centre, aged care facility or immigration detention centre.
A73: 3. The denominator for the proportions exclude clients whose homeless status at first presentation was not stated.

Sheet CLIENTS.13
A1: Table of contents
A2: Table CLIENTS.13: Clients who first presented to an agency reporting no shelter/improvised dwelling (rough sleepers), by dwelling type, 2023–24
A4: Dwelling type | B4: Number | C4: Per cent
A5: House/townhouse/flat | B5: 68 | C5: 0.2
A6: Caravan | B6: 3368 | C6: 10.8
A7: Tent | B7: 2548 | C7: 8.2
A8: Cabin | B8: 1064 | C8: 3.4
A9: Boat | B9: 85 | C9: 0.3
A10: Improvised building/dwelling | B10: 1889 | C10: 6.1
A11: No dwelling/street/park/in the open | B11: 15393 | C11: 49.3
A12: Motor vehicle | B12: 6727 | C12: 21.6
A13: Emergency accommodation | B13: 37 | C13: 0.1
A14: Hotel/motel/bed and breakfast | B14: 1 | C14: 0
A15: Other | B15: 21 | C15: 0.1
A16: Not stated | B16: 20 | C16: . .
A17: Total | B17: 31221 | C17: 100
A19: Notes
A20: 1. Rough sleeper: clients with the housing situation 'No shelter or improvised/inadequate dwelling' at the beginning of their first support period.
A21: 2. Per cent calculations based on total clients less 'Not stated'.
A22: . . not applicable

Sheet CLIENTS.14
A1: Table of contents
A2: Table CLIENTS.14: Clients, by homelessness status in the month before the first support period, by state and territory, 2023–24
A4: State/ territory | B4: Homelessness status in the month before the client's first support period | C4: Number | D4: Per cent
A5: National | B5: Homeless in previous month | C5: 113531 | D5: 42.4
A6: National | B6: Sleeping rough or in non-conventional accommodation | C6: 50284 | D6: 18.8
A7: National | B7: Short-term or emergency accommodation, due to a lack of other options | C7: 63247 | D7: 23.6
A8: National | B8: Not homeless in previous month | C8: 154139 | D8: 57.6
A9: National | B9: Not stated | C9: 12408 | D9: . .
A10: National | B10: Total | C10: 280078 | D10: 100
A11: NSW | B11: Homeless in previous month | C11: 32268 | D11: 49.8
A12: NSW | B12: Sleeping rough or in non-conventional accommodation | C12: 12349 | D12: 19.1
A13: NSW | B13: Short-term or emergency accommodation, due to a lack of other options | C13: 19919 | D13: 30.8
A14: NSW | B14: Not homeless in previous month | C14: 32466 | D14: 50.2
A15: NSW | B15: Not stated | C15: 3157 | D15: . .
A16: NSW | B16: Total | C16: 67891 | D16: 100
A17: Vic | B17: Homeless in previous month | C17: 31101 | D17: 32.3
A18: Vic | B18: Sleeping rough or in non-conventional accommodation | C18: 12684 | D18: 13.2
A19: Vic | B19: Short-term or emergency accommodation, due to a lack of other options | C19: 18417 | D19: 19.1
A20: Vic | B20: Not homeless in previous month | C20: 65199 | D20: 67.7
A21: Vic | B21: Not stated | C21: 5664 | D21: . .
A22: Vic | B22: Total | C22: 101964 | D22: 100
A23: Qld | B23: Homeless in previous month | C23: 24289 | D23: 51.1
A24: Qld | B24: Sleeping rough or in non-conventional accommodation | C24: 11899 | D24: 25.1
A25: Qld | B25: Short-term or emergency accommodation, due to a lack of other options | C25: 12390 | D25: 26.1
A26: Qld | B26: Not homeless in previous month | C26: 23209 | D26: 48.9
A27: Qld | B27: Not stated | C27: 1320 | D27: . .
A28: Qld | B28: Total | C28: 48818 | D28: 100
A29: WA | B29: Homeless in previous month | C29: 8596 | D29: 36
A30: WA | B30: Sleeping rough or in non-conventional accommodation | C30: 4439 | D30: 18.6
A31: WA | B31: Short-term or emergency accommodation, due to a lack of other options | C31: 4157 | D31: 17.4
A32: WA | B32: Not homeless in previous month | C32: 15294 | D32: 64
A33: WA | B33: Not stated | C33: 1103 | D33: . .
A34: WA | B34: Total | C34: 24993 | D34: 100
A35: SA | B35: Homeless in previous month | C35: 9218 | D35: 50.8
A36: SA | B36: Sleeping rough or in non-conventional accommodation | C36: 4631 | D36: 25.5
A37: SA | B37: Short-term or emergency accommodation, due to a lack of other options | C37: 4587 | D37: 25.3
A38: SA | B38: Not homeless in previous month | C38: 8932 | D38: 49.2
A39: SA | B39: Not stated | C39: 567 | D39: . .
A40: SA | B40: Total | C40: 18717 | D40: 100
A41: Tas | B41: Homeless in previous month | C41: 3714 | D41: 56.4
A42: Tas | B42: Sleeping rough or in non-conventional accommodation | C42: 1596 | D42: 24.2
A43: Tas | B43: Short-term or emergency accommodation, due to a lack of other options | C43: 2118 | D43: 32.2
A44: Tas | B44: Not homeless in previous month | C44: 2871 | D44: 43.6
A45: Tas | B45: Not stated | C45: 87 | D45: . .
A46: Tas | B46: Total | C46: 6672 | D46: 100
A47: ACT | B47: Homeless in previous month | C47: 2057 | D47: 52.9
A48: ACT | B48: Sleeping rough or in non-conventional accommodation | C48: 961 | D48: 24.7
A49: ACT | B49: Short-term or emergency accommodation, due to a lack of other options | C49: 1096 | D49: 28.2
A50: ACT | B50: Not homeless in previous month | C50: 1832 | D50: 47.1
A51: ACT | B51: Not stated | C51: 117 | D51: . .
A52: ACT | B52: Total | C52: 4006 | D52: 100
A53: NT | B53: Homeless in previous month | C53: 4189 | D53: 43.9
A54: NT | B54: Sleeping rough or in non-conventional accommodation | C54: 2761 | D54: 28.9
A55: NT | B55: Short-term or emergency accommodation, due to a lack of other options | C55: 1428 | D55: 15
A56: NT | B56: Not homeless in previous month | C56: 5361 | D56: 56.1
A57: NT | B57: Not stated | C57: 530 | D57: . .
A58: NT | B58: Total | C58: 10080 | D58: 100
A60: Notes
A61: 1. Clients of specialist homelessness services may have multiple housing situations in the month before their first support period. If a client was considered to be 'Homeless in previous month' and had multiple housing situations across both 'Sleeping rough or in non-conventional accommodation' and 'Short-term or emergency accommodation, due to a lack of other options' then they are counted as 'Sleeping rough or in non-conventional accommodation'.
A62: 2. Per cent calculations based on total clients less 'Not stated'.
A63: . . not applicable

Sheet CLIENTS.15
A1: Table of contents
A2: Table CLIENTS.15: Clients, by source of referral at the beginning of support, and by state and territory, 2023–24
C4: Males | D4: Males | E4: Females | F4: Females | G4: All clients | H4: All clients
A5: State/territory | B5: Formal referral source | C5: Number | D5: Per cent | E5: Number | F5: Per cent | G5: Number | H5: Per cent
A6: National | B6: Specialist Homelessness Agency/outreach worker | C6: 18817 | D6: 16.8 | E6: 24580 | F6: 14.8 | G6: 43397 | H6: 15.6
A7: National | B7: Telephone/crisis referral agency | C7: 2473 | D7: 2.2 | E7: 3786 | F7: 2.3 | G7: 6259 | H7: 2.3
A8: National | B8: Centrelink or employment service case worker | C8: 616 | D8: 0.6 | E8: 891 | F8: 0.5 | G8: 1507 | H8: 0.5
A9: National | B9: Child protection agency | C9: 1069 | D9: 1 | E9: 2370 | F9: 1.4 | G9: 3439 | H9: 1.2
A10: National | B10: Family and child support agency | C10: 1332 | D10: 1.2 | E10: 3029 | F10: 1.8 | G10: 4361 | H10: 1.6
A11: National | B11: Hospital | C11: 1710 | D11: 1.5 | E11: 3037 | F11: 1.8 | G11: 4747 | H11: 1.7
A12: National | B12: Mental health service | C12: 1122 | D12: 1 | E12: 1951 | F12: 1.2 | G12: 3073 | H12: 1.1
A13: National | B13: Disability support service | C13: 495 | D13: 0.4 | E13: 554 | F13: 0.3 | G13: 1049 | H13: 0.4
A14: National | B14: Drug and alcohol service | C14: 664 | D14: 0.6 | E14: 571 | F14: 0.3 | G14: 1235 | H14: 0.4
A15: National | B15: Aged care service | C15: 96 | D15: 0.1 | E15: 124 | F15: 0.1 | G15: 220 | H15: 0.1
A16: National | B16: Social housing | C16: 3522 | D16: 3.2 | E16: 4918 | F16: 3 | G16: 8440 | H16: 3
A17: National | B17: Youth/juvenile justice correctional centre | C17: 240 | D17: 0.2 | E17: 117 | F17: 0.1 | G17: 357 | H17: 0.1
... A28: National | B28: No formal referral | C28: 42024 | D28: 37.6 | E28: 57967 | F28: 35 | G28: 99991 | H28: 36
A29: National | B29: Not stated | C29: 1116 | D29: . . | E29: 1375 | F29: . . | G29: 2491 | H29: . .
A30: National | B30: Total | C30: 112873 | D30: 100 | E30: 167205 | F30: 100 | G30: 280078 | H30: 100
A31: NSW | B31: Specialist Homelessness Agency/outreach worker | C31: 4746 | D31: 17.5 | E31: 6352 | F31: 15.9 | G31: 11098 | H31: 16.5
A32: NSW | B32: Telephone/crisis referral agency | C32: 1121 | D32: 4.1 | E32: 1442 | F32: 3.6 | G32: 2563 | H32: 3.8
A33: NSW | B33: Centrelink or employment service case worker | C33: 165 | D33: 0.6 | E33: 263 | F33: 0.7 | G33: 428 | H33: 0.6
A34: NSW | B34: Child protection agency | C34: 297 | D34: 1.1 | E34: 652 | F34: 1.6 | G34: 949 | H34: 1.4
A35: NSW | B35: Family and child support agency | C35: 480 | D35: 1.8 | E35: 995 | F35: 2.5 | G35: 1475 | H35: 2.2
A36: NSW | B36: Hospital | C36: 392 | D36: 1.4 | E36: 590 | F36: 1.5 | G36: 982 | H36: 1.5
A37: NSW | B37: Mental health service | C37: 359 | D37: 1.3 | E37: 724 | F37: 1.8 | G37: 1083 | H37: 1.6
A38: NSW | B38: Disability support service | C38: 108 | D38: 0.4 | E38: 161 | F38: 0.4 | G38: 269 | H38: 0.4
A39: NSW | B39: Drug and alcohol service | C39: 202 | D39: 0.7 | E39: 206 | F39: 0.5 | G39: 408 | H39: 0.6
A40: NSW | B40: Aged care service | C40: 21 | D40: 0.1 | E40: 21 | F40: 0.1 | G40: 42 | H40: 0.1
A41: NSW | B41: Social housing | C41: 1415 | D41: 5.2 | E41: 1748 | F41: 4.4 | G41: 3163 | H41: 4.7
... A53: NSW | B53: No formal referral | C53: 8416 | D53: 31 | E53: 11572 | F53: 28.9 | G53: 19988 | H53: 29.8
A54: NSW | B54: Not stated | C54: 365 | D54: . . | E54: 419 | F54: . . | G54: 784 | H54: . .
A55: NSW | B55: Total | C55: 27486 | D55: 100 | E55: 40405 | F55: 100 | G55: 67891 | H55: 100
A56: Vic | B56: Specialist Homelessness Agency/outreach worker | C56: 7426 | D56: 17.7 | E56: 9793 | F56: 16.6 | G56: 17219 | H56: 17
A57: Vic | B57: Telephone/crisis referral agency | C57: 508 | D57: 1.2 | E57: 846 | F57: 1.4 | G57: 1354 | H57: 1.3
A58: Vic | B58: Centrelink or employment service case worker | C58: 94 | D58: 0.2 | E58: 113 | F58: 0.2 | G58: 207 | H58: 0.2
A59: Vic | B59: Child protection agency | C59: 231 | D59: 0.5 | E59: 473 | F59: 0.8 | G59: 704 | H59: 0.7
A60: Vic | B60: Family and child support agency | C60: 372 | D60: 0.9 | E60: 929 | F60: 1.6 | G60: 1301 | H60: 1.3
A61: Vic | B61: Hospital | C61: 410 | D61: 1 | E61: 466 | F61: 0.8 | G61: 876 | H61: 0.9
A62: Vic | B62: Mental health service | C62: 342 | D62: 0.8 | E62: 548 | F62: 0.9 | G62: 890 | H62: 0.9
A63: Vic | B63: Disability support service | C63: 195 | D63: 0.5 | E63: 198 | F63: 0.3 | G63: 393 | H63: 0.4
A64: Vic | B64: Drug and alcohol service | C64: 257 | D64: 0.6 | E64: 150 | F64: 0.3 | G64: 407 | H64: 0.4
A65: Vic | B65: Aged care service | C65: 46 | D65: 0.1 | E65: 65 | F65: 0.1 | G65: 111 | H65: 0.1
A66: Vic | B66: Social housing | C66: 509 | D66: 1.2 | E66: 816 | F66: 1.4 | G66: 1325 | H66: 1.3
... A78: Vic | B78: No formal referral | C78: 15183 | D78: 36.1 | E78: 20245 | F78: 34.3 | G78: 35428 | H78: 35.1
A79: Vic | B79: Not stated | C79: 416 | D79: . . | E79: 537 | F79: . . | G79: 953 | H79: . .
A80: Vic | B80: Total | C80: 42432 | D80: 100 | E80: 59532 | F80: 100 | G80: 101964 | H80: 100
A81: Qld | B81: Specialist Homelessness Agency/outreach worker | C81: 3589 | D81: 18.1 | E81: 4267 | F81: 14.9 | G81: 7856 | H81: 16.2
A82: Qld | B82: Telephone/crisis referral agency | C82: 346 | D82: 1.7 | E82: 664 | F82: 2.3 | G82: 1010 | H82: 2.1
A83: Qld | B83: Centrelink or employment service case worker | C83: 73 | D83: 0.4 | E83: 117 | F83: 0.4 | G83: 190 | H83: 0.4
A84: Qld | B84: Child protection agency | C84: 128 | D84: 0.6 | E84: 233 | F84: 0.8 | G84: 361 | H84: 0.7
A85: Qld | B85: Family and child support agency | C85: 301 | D85: 1.5 | E85: 625 | F85: 2.2 | G85: 926 | H85: 1.9
A86: Qld | B86: Hospital | C86: 291 | D86: 1.5 | E86: 457 | F86: 1.6 | G86: 748 | H86: 1.5
A87: Qld | B87: Mental health service | C87: 188 | D87: 0.9 | E87: 265 | F87: 0.9 | G87: 453 | H87: 0.9
A88: Qld | B88: Disability support service | C88: 71 | D88: 0.4 | E88: 73 | F88: 0.3 | G88: 144 | H88: 0.3
A89: Qld | B89: Drug and alcohol service | C89: 60 | D89: 0.3 | E89: 53 | F89: 0.2 | G89: 113 | H89: 0.2
A90: Qld | B90: Aged care service | C90: 14 | D90: 0.1 | E90: 12 | F90: 0 | G90: 26 | H90: 0.1
A91: Qld | B91: Social housing | C91: 1379 | D91: 7 | E91: 1935 | F91: 6.8 | G91: 3314 | H91: 6.8
... A103: Qld | B103: No formal referral | C103: 7657 | D103: 38.6 | E103: 10014 | F103: 35 | G103: 17671 | H103: 36.5
A104: Qld | B104: Not stated | C104: 189 | D104: . . | E104: 212 | F104: . . | G104: 401 | H104: . .
A105: Qld | B105: Total | C105: 20003 | D105: 100 | E105: 28815 | F105: 100 | G105: 48818 | H105: 100
A106: WA | B106: Specialist Homelessness Agency/outreach worker | C106: 905 | D106: 10.7 | E106: 1273 | F106: 7.8 | G106: 2178 | H106: 8.8
A107: WA | B107: Telephone/crisis referral agency | C107: 130 | D107: 1.5 | E107: 252 | F107: 1.5 | G107: 382 | H107: 1.5
A108: WA | B108: Centrelink or employment service case worker | C108: 246 | D108: 2.9 | E108: 340 | F108: 2.1 | G108: 586 | H108: 2.4
A109: WA | B109: Child protection agency | C109: 303 | D109: 3.6 | E109: 761 | F109: 4.6 | G109: 1064 | H109: 4.3
A110: WA | B110: Family and child support agency | C110: 95 | D110: 1.1 | E110: 249 | F110: 1.5 | G110: 344 | H110: 1.4
A111: WA | B111: Hospital | C111: 444 | D111: 5.2 | E111: 888 | F111: 5.4 | G111: 1332 | H111: 5.4
A112: WA | B112: Mental health service | C112: 82 | D112: 1 | E112: 219 | F112: 1.3 | G112: 301 | H112: 1.2
A113: WA | B113: Disability support service | C113: 35 | D113: 0.4 | E113: 39 | F113: 0.2 | G113: 74 | H113: 0.3
A114: WA | B114: Drug and alcohol service | C114: 81 | D114: 1 | E114: 99 | F114: 0.6 | G114: 180 | H114: 0.7
A115: WA | B115: Aged care service | C115: 4 | D115: 0 | E115: 9 | F115: 0.1 | G115: 13 | H115: 0.1
A116: WA | B116: Social housing | C116: 58 | D116: 0.7 | E116: 111 | F116: 0.7 | G116: 169 | H116: 0.7
... A128: WA | B128: No formal referral | C128: 3785 | D128: 44.7 | E128: 6047 | F128: 36.9 | G128: 9832 | H128: 39.6
A129: WA | B129: Not stated | C129: 67 | D129: . . | E129: 95 | F129: . . | G129: 162 | H129: . .
A130: WA | B130: Total | C130: 8526 | D130: 100 | E130: 16467 | F130: 100 | G130: 24993 | H130: 100
A131: SA | B131: Specialist Homelessness Agency/outreach worker | C131: 608 | D131: 8 | E131: 876 | F131: 7.9 | G131: 1484 | H131: 8
A132: SA | B132: Telephone/crisis referral agency | C132: 250 | D132: 3.3 | E132: 377 | F132: 3.4 | G132: 627 | H132: 3.4
A133: SA | B133: Centrelink or employment service case worker | C133: 16 | D133: 0.2 | E133: 16 | F133: 0.1 | G133: 32 | H133: 0.2
A134: SA | B134: Child protection agency | C134: 28 | D134: 0.4 | E134: 85 | F134: 0.8 | G134: 113 | H134: 0.6
A135: SA | B135: Family and child support agency | C135: 17 | D135: 0.2 | E135: 56 | F135: 0.5 | G135: 73 | H135: 0.4
A136: SA | B136: Hospital | C136: 33 | D136: 0.4 | E136: 139 | F136: 1.3 | G136: 172 | H136: 0.9
A137: SA | B137: Mental health service | C137: 39 | D137: 0.5 | E137: 80 | F137: 0.7 | G137: 119 | H137: 0.6
A138: SA | B138: Disability support service | C138: 34 | D138: 0.4 | E138: 41 | F138: 0.4 | G138: 75 | H138: 0.4
A139: SA | B139: Drug and alcohol service | C139: 10 | D139: 0.1 | E139: 12 | F139: 0.1 | G139: 22 | H139: 0.1
A140: SA | B140: Aged care service | C140: 2 | D140: 0 | E140: 4 | F140: 0 | G140: 6 | H140: 0
A141: SA | B141: Social housing | C141: 46 | D141: 0.6 | E141: 111 | F141: 1 | G141: 157 | H141: 0.8
... A153: SA | B153: No formal referral | C153: 4188 | D153: 55.2 | E153: 6443 | F153: 58.2 | G153: 10631 | H153: 57
A154: SA | B154: Not stated | C154: 23 | D154: . . | E154: 39 | F154: . . | G154: 62 | H154: . .
A155: SA | B155: Total | C155: 7611 | D155: 100 | E155: 11106 | F155: 100 | G155: 18717 | H155: 100
A156: Tas | B156: Specialist Homelessness Agency/outreach worker | C156: 1234 | D156: 42 | E156: 1582 | F156: 43.2 | G156: 2816 | H156: 42.7
A157: Tas | B157: Telephone/crisis referral agency | C157: 11 | D157: 0.4 | E157: 10 | F157: 0.3 | G157: 21 | H157: 0.3
A158: Tas | B158: Centrelink or employment service case worker | C158: n.p. | D158: n.p. | E158: n.p. | F158: n.p. | G158: 14 | H158: 0.2
A159: Tas | B159: Child protection agency | C159: 16 | D159: 0.5 | E159: 23 | F159: 0.6 | G159: 39 | H159: 0.6
A160: Tas | B160: Family and child support agency | C160: 14 | D160: 0.5 | E160: 37 | F160: 1 | G160: 51 | H160: 0.8
A161: Tas | B161: Hospital | C161: 37 | D161: 1.3 | E161: 31 | F161: 0.8 | G161: 68 | H161: 1
A162: Tas | B162: Mental health service | C162: 43 | D162: 1.5 | E162: 41 | F162: 1.1 | G162: 84 | H162: 1.3
A163: Tas | B163: Disability support service | C163: 22 | D163: 0.7 | E163: 10 | F163: 0.3 | G163: 32 | H163: 0.5
A164: Tas | B164: Drug and alcohol service | C164: 10 | D164: 0.3 | E164: 11 | F164: 0.3 | G164: 21 | H164: 0.3
A165: Tas | B165: Aged care service | C165: n.p. | D165: n.p. | E165: n.p. | F165: n.p. | G165: n.p. | H165: n.p.
A166: Tas | B166: Social housing | C166: 46 | D166: 1.6 | E166: 42 | F166: 1.1 | G166: 88 | H166: 1.3
...

Sheet CLIENTS.16
A1: Table of contents
A2: Table CLIENTS.16: Clients aged 15 and over, by main source of income, and by state and territory, 2023–24
C4: Males | D4: Males | E4: Females | F4: Females | G4: All clients | H4: All clients
A5: State/territory | B5: Main source of income | C5: Number | D5: Per cent | E5: Number | F5: Per cent | G5: Number | H5: Per cent
A6: National | B6: JobSeeker payment | C6: 28629 | D6: 38.3 | E6: 26686 | F6: 21.9 | G6: 55315 | H6: 28.2
A7: National | B7: Parenting payment | C7: 1848 | D7: 2.5 | E7: 31833 | F7: 26.2 | G7: 33681 | H7: 17.1
A8: National | B8: Disability support pension (Centrelink) | C8: 14452 | D8: 19.4 | E8: 14520 | F8: 11.9 | G8: 28972 | H8: 14.8
A9: National | B9: Youth allowance | C9: 4826 | D9: 6.5 | E9: 8030 | F9: 6.6 | G9: 12856 | H9: 6.5
A10: National | B10: Austudy/ABSTUDY | C10: 224 | D10: 0.3 | E10: 532 | F10: 0.4 | G10: 756 | H10: 0.4
A11: National | B11: Age pension | C11: 3132 | D11: 4.2 | E11: 3691 | F11: 3 | G11: 6823 | H11: 3.5
A12: National | B12: Sickness allowance | C12: 68 | D12: 0.1 | E12: 82 | F12: 0.1 | G12: 150 | H12: 0.1
A13: National | B13: Carer allowance | C13: 242 | D13: 0.3 | E13: 954 | F13: 0.8 | G13: 1196 | H13: 0.6
A14: National | B14: Carer Payment | C14: 802 | D14: 1.1 | E14: 3007 | F14: 2.5 | G14: 3809 | H14: 1.9
A15: National | B15: DVA pension or payment | C15: 225 | D15: 0.3 | E15: 164 | F15: 0.1 | G15: 389 | H15: 0.2
A16: National | B16: Other government pensions and allowances nec | C16: 764 | D16: 1 | E16: 2897 | F16: 2.4 | G16: 3661 | H16: 1.9
A17: National | B17: Employee income | C17: 7006 | D17: 9.4 | E17: 16788 | F17: 13.8 | G17: 23794 | H17: 12.1
... A21: National | B21: Nil income | C21: 9710 | D21: 13 | E21: 8973 | F21: 7.4 | G21: 18683 | H21: 9.5
A22: National | B22: Not stated | C22: 7454 | D22: . . | E22: 14949 | F22: . . | G22: 22403 | H22: . .
A23: National | B23: Total | C23: 82132 | D23: 100 | E23: 136668 | F23: 100 | G23: 218800 | H23: 100
A24: NSW | B24: JobSeeker payment | C24: 6834 | D24: 38.4 | E24: 5958 | F24: 19.9 | G24: 12792 | H24: 26.8
A25: NSW | B25: Parenting payment | C25: 402 | D25: 2.3 | E25: 7418 | F25: 24.8 | G25: 7820 | H25: 16.4
A26: NSW | B26: Disability support pension (Centrelink) | C26: 3435 | D26: 19.3 | E26: 3467 | F26: 11.6 | G26: 6902 | H26: 14.5
A27: NSW | B27: Youth allowance | C27: 1722 | D27: 9.7 | E27: 2752 | F27: 9.2 | G27: 4474 | H27: 9.4
A28: NSW | B28: Austudy/ABSTUDY | C28: 71 | D28: 0.4 | E28: 175 | F28: 0.6 | G28: 246 | H28: 0.5
A29: NSW | B29: Age pension | C29: 666 | D29: 3.7 | E29: 802 | F29: 2.7 | G29: 1468 | H29: 3.1
A30: NSW | B30: Sickness allowance | C30: 12 | D30: 0.1 | E30: 13 | F30: 0 | G30: 25 | H30: 0.1
A31: NSW | B31: Carer allowance | C31: 62 | D31: 0.3 | E31: 248 | F31: 0.8 | G31: 310 | H31: 0.6
A32: NSW | B32: Carer Payment | C32: 187 | D32: 1.1 | E32: 679 | F32: 2.3 | G32: 866 | H32: 1.8
A33: NSW | B33: DVA pension or payment | C33: 34 | D33: 0.2 | E33: 21 | F33: 0.1 | G33: 55 | H33: 0.1
A34: NSW | B34: Other government pensions and allowances nec | C34: 230 | D34: 1.3 | E34: 581 | F34: 1.9 | G34: 811 | H34: 1.7
... A39: NSW | B39: Nil income | C39: 1884 | D39: 10.6 | E39: 2713 | F39: 9.1 | G39: 4597 | H39: 9.6
A40: NSW | B40: Not stated | C40: 1800 | D40: . . | E40: 2346 | F40: . . | G40: 4146 | H40: . .
A41: NSW | B41: Total | C41: 19606 | D41: 100 | E41: 32289 | F41: 100 | G41: 51895 | H41: 100
A42: Vic | B42: JobSeeker payment | C42: 9536 | D42: 33.2 | E42: 8084 | F42: 19.6 | G42: 17620 | H42: 25.2
A43: Vic | B43: Parenting payment | C43: 672 | D43: 2.3 | E43: 9766 | F43: 23.7 | G43: 10438 | H43: 14.9
A44: Vic | B44: Disability support pension (Centrelink) | C44: 5582 | D44: 19.4 | E44: 5810 | F44: 14.1 | G44: 11392 | H44: 16.3
A45: Vic | B45: Youth allowance | C45: 1163 | D45: 4 | E45: 1831 | F45: 4.4 | G45: 2994 | H45: 4.3
A46: Vic | B46: Austudy/ABSTUDY | C46: 66 | D46: 0.2 | E46: 159 | F46: 0.4 | G46: 225 | H46: 0.3
A47: Vic | B47: Age pension | C47: 1286 | D47: 4.5 | E47: 1560 | F47: 3.8 | G47: 2846 | H47: 4.1
A48: Vic | B48: Sickness allowance | C48: 19 | D48: 0.1 | E48: 27 | F48: 0.1 | G48: 46 | H48: 0.1
A49: Vic | B49: Carer allowance | C49: 92 | D49: 0.3 | E49: 356 | F49: 0.9 | G49: 448 | H49: 0.6
A50: Vic | B50: Carer Payment | C50: 338 | D50: 1.2 | E50: 1150 | F50: 2.8 | G50: 1488 | H50: 2.1
A51: Vic | B51: DVA pension or payment | C51: 77 | D51: 0.3 | E51: 73 | F51: 0.2 | G51: 150 | H51: 0.2
A52: Vic | B52: Other government pensions and allowances nec | C52: 222 | D52: 0.8 | E52: 882 | F52: 2.1 | G52: 1104 | H52: 1.6
... A57: Vic | B57: Nil income | C57: 5572 | D57: 19.4 | E57: 3221 | F57: 7.8 | G57: 8793 | H57: 12.6
A58: Vic | B58: Not stated | C58: 3604 | D58: . . | E58: 8378 | F58: . . | G58: 11982 | H58: . .
A59: Vic | B59: Total | C59: 32330 | D59: 100 | E59: 49614 | F59: 100 | G59: 81944 | H59: 100
A60: Qld | B60: JobSeeker payment | C60: 5396 | D60: 41.5 | E60: 4820 | F60: 22.5 | G60: 10216 | H60: 29.7
A61: Qld | B61: Parenting payment | C61: 421 | D61: 3.2 | E61: 6721 | F61: 31.4 | G61: 7142 | H61: 20.7
A62: Qld | B62: Disability support pension (Centrelink) | C62: 2610 | D62: 20.1 | E62: 2326 | F62: 10.9 | G62: 4936 | H62: 14.3
A63: Qld | B63: Youth allowance | C63: 967 | D63: 7.4 | E63: 1504 | F63: 7 | G63: 2471 | H63: 7.2
A64: Qld | B64: Austudy/ABSTUDY | C64: 27 | D64: 0.2 | E64: 74 | F64: 0.3 | G64: 101 | H64: 0.3
A65: Qld | B65: Age pension | C65: 572 | D65: 4.4 | E65: 598 | F65: 2.8 | G65: 1170 | H65: 3.4
A66: Qld | B66: Sickness allowance | C66: 5 | D66: 0 | E66: 5 | F66: 0 | G66: 10 | H66: 0
A67: Qld | B67: Carer allowance | C67: 37 | D67: 0.3 | E67: 128 | F67: 0.6 | G67: 165 | H67: 0.5
A68: Qld | B68: Carer Payment | C68: 130 | D68: 1 | E68: 526 | F68: 2.5 | G68: 656 | H68: 1.9
A69: Qld | B69: DVA pension or payment | C69: 83 | D69: 0.6 | E69: 32 | F69: 0.1 | G69: 115 | H69: 0.3
A70: Qld | B70: Other government pensions and allowances nec | C70: 113 | D70: 0.9 | E70: 445 | F70: 2.1 | G70: 558 | H70: 1.6
... A75: Qld | B75: Nil income | C75: 1032 | D75: 7.9 | E75: 1368 | F75: 6.4 | G75: 2400 | H75: 7
A76: Qld | B76: Not stated | C76: 933 | D76: . . | E76: 1705 | F76: . . | G76: 2638 | H76: . .
A77: Qld | B77: Total | C77: 13950 | D77: 100 | E77: 23130 | F77: 100 | G77: 37080 | H77: 100
A78: WA | B78: JobSeeker payment | C78: 2611 | D78: 51 | E78: 3222 | F78: 25.9 | G78: 5833 | H78: 33.3
A79: WA | B79: Parenting payment | C79: 124 | D79: 2.4 | E79: 3978 | F79: 32 | G79: 4102 | H79: 23.4
A80: WA | B80: Disability support pension (Centrelink) | C80: 725 | D80: 14.2 | E80: 976 | F80: 7.9 | G80: 1701 | H80: 9.7
A81: WA | B81: Youth allowance | C81: 275 | D81: 5.4 | E81: 655 | F81: 5.3 | G81: 930 | H81: 5.3
A82: WA | B82: Austudy/ABSTUDY | C82: 22 | D82: 0.4 | E82: 51 | F82: 0.4 | G82: 73 | H82: 0.4
A83: WA | B83: Age pension | C83: 217 | D83: 4.2 | E83: 307 | F83: 2.5 | G83: 524 | H83: 3
A84: WA | B84: Sickness allowance | C84: 27 | D84: 0.5 | E84: 31 | F84: 0.2 | G84: 58 | H84: 0.3
A85: WA | B85: Carer allowance | C85: 15 | D85: 0.3 | E85: 100 | F85: 0.8 | G85: 115 | H85: 0.7
A86: WA | B86: Carer Payment | C86: 34 | D86: 0.7 | E86: 198 | F86: 1.6 | G86: 232 | H86: 1.3
A87: WA | B87: DVA pension or payment | C87: 6 | D87: 0.1 | E87: 14 | F87: 0.1 | G87: 20 | H87: 0.1
A88: WA | B88: Other government pensions and allowances nec | C88: 45 | D88: 0.9 | E88: 371 | F88: 3 | G88: 416 | H88: 2.4
A89: WA | B89: Employee income | C89: 369 | D89: 7.2 | E89: 1518 | F89: 12.2 | G89: 1887 | H89: 10.8
A90: WA | B90: Unincorporated business income | C90: — | D90: — | E90: 12 | F90: 0.1 | G90: 12 | H90: 0.1
A91: WA | B91: Other income nec | C91: 215 | D91: 4.2 | E91: 221 | F91: 1.8 | G91: 436 | H91: 2.5
A92: WA | B92: Awaiting government benefit | C92: 73 | D92: 1.4 | E92: 149 | F92: 1.2 | G92: 222 | H92: 1.3
A93: WA | B93: Nil income | C93: 365 | D93: 7.1 | E93: 615 | F93: 5 | G93: 980 | H93: 5.6
A94: WA | B94: Not stated | C94: 503 | D94: . . | E94: 1004 | F94: . . | G94: 1507 | H94: . .
A95: WA | B95: Total | C95: 5626 | D95: 100 | E95: 13422 | F95: 100 | G95: 19048 | H95: 100
A96: SA | B96: JobSeeker payment | C96: 2173 | D96: 41.8 | E96: 2133 | F96: 25.4 | G96: 4306 | H96: 31.6
A97: SA | B97: Parenting payment | C97: 124 | D97: 2.4 | E97: 1903 | F97: 22.6 | G97: 2027 | H97: 14.9
A98: SA | B98: Disability support pension (Centrelink) | C98: 1021 | D98: 19.6 | E98: 949 | F98: 11.3 | G98: 1970 | H98: 14.5
A99: SA | B99: Youth allowance | C99: 364 | D99: 7 | E99: 594 | F99: 7.1 | G99: 958 | H99: 7
A100: SA | B100: Austudy/ABSTUDY | C100: 27 | D100: 0.5 | E100: 47 | F100: 0.6 | G100: 74 | H100: 0.5
A101: SA | B101: Age pension | C101: 129 | D101: 2.5 | E101: 158 | F101: 1.9 | G101: 287 | H101: 2.1
A102: SA | B102: Sickness allowance | C102: 4 | D102: 0.1 | E102: 3 | F102: 0 | G102: 7 | H102: 0.1
A103: SA | B103: Carer allowance | C103: 28 | D103: 0.5 | E103: 88 | F103: 1 | G103: 116 | H103: 0.9
A104: SA | B104: Carer Payment | C104: 81 | D104: 1.6 | E104: 270 | F104: 3.2 | G104: 351 | H104: 2.6
A105: SA | B105: DVA pension or payment | C105: 17 | D105: 0.3 | E105: 15 | F105: 0.2 | G105: 32 | H105: 0.2
A106: SA | B106: Other government pensions and allowances nec | C106: 106 | D106: 2 | E106: 468 | F106: 5.6 | G106: 574 | H106: 4.2
A107: SA | B107: Employee income | C107: 438 | D107: 8.4 | E107: 886 | F107: 10.5 | G107: 1324 | H107: 9.7
A108: SA | B108: Unincorporated business income | C108: — | D108: — | E108: 4 | F108: 0 | G108: 4 | H108: 0
A109: SA | B109: Other income nec | C109: 35 | D109: 0.7 | E109: 50 | F109: 0.6 | G109: 85 | H109: 0.6
A110: SA | B110: Awaiting government benefit | C110: 110 | D110: 2.1 | E110: 144 | F110: 1.7 | G110: 254 | H110: 1.9
A111: SA | B111: Nil income | C111: 542 | D111: 10.4 | E111: 695 | F111: 8.3 | G111: 1237 | H111: 9.1
A112: SA | B112: Not stated | C112: 325 | D112: . . | E112: 690 | F112: . . | G112: 1015 | H112: . .
A113: SA | B113: Total | C113: 5524 | D113: 100 | E113: 9097 | F113: 100 | G113: 14621 | H113: 100
A114: Tas | B114: JobSeeker payment | C114: 806 | D114: 32.8 | E114: 598 | F114: 18.5 | G114: 1404 | H114: 24.7
A115: Tas | B115: Parenting payment | C115: 46 | D115: 1.9 | E115: 763 | F115: 23.7 | G115: 809 | H115: 14.2
A116: Tas | B116: Disability support pension (Centrelink) | C116: 786 | D116: 32 | E116: 671 | F116: 20.8 | G116: 1457 | H116: 25.6
...

Sheet CLIENTS.17
A1: Table of contents
A2: Table CLIENTS.17: Clients by National Disability Insurance Scheme status, and by state and territory, 2023–24
A4: State/territory | B4: National Disability Insurance Scheme status | C4: Number | D4: Per cent
A5: National | B5: Yes | C5: 14283 | D5: 5.8
A6: National | B6: No | C6: 232702 | D6: 94.2
A7: National | B7: Not stated | C7: 31691 | D7: . .
A8: National | B8: Total | C8: 278676 | D8: 100
A9: NSW | B9: Yes | C9: 3217 | D9: 5.3
A10: NSW | B10: No | C10: 57633 | D10: 94.7
A11: NSW | B11: Not stated | C11: 6848 | D11: . .
A12: NSW | B12: Total | C12: 67698 | D12: 100
A13: Vic | B13: Yes | C13: 6634 | D13: 7.6
A14: Vic | B14: No | C14: 80348 | D14: 92.4
A15: Vic | B15: Not stated | C15: 14233 | D15: . .
A16: Vic | B16: Total | C16: 101215 | D16: 100
A17: Qld | B17: Yes | C17: 2091 | D17: 4.7
A18: Qld | B18: No | C18: 42559 | D18: 95.3
A19: Qld | B19: Not stated | C19: 4049 | D19: . .
A20: Qld | B20: Total | C20: 48699 | D20: 100
A21: WA | B21: Yes | C21: 775 | D21: 3.3
A22: WA | B22: No | C22: 22673 | D22: 96.7
A23: WA | B23: Not stated | C23: 1510 | D23: . .
A24: WA | B24: Total | C24: 24958 | D24: 100
A25: SA | B25: Yes | C25: 821 | D25: 5.4
A26: SA | B26: No | C26: 14479 | D26: 94.6
A27: SA | B27: Not stated | C27: 3409 | D27: . .
A28: SA | B28: Total | C28: 18709 | D28: 100
A29: Tas | B29: Yes | C29: 513 | D29: 8.2
A30: Tas | B30: No | C30: 5780 | D30: 91.8
A31: Tas | B31: Not stated | C31: 265 | D31: . .
A32: Tas | B32: Total | C32: 6558 | D32: 100
A33: ACT | B33: Yes | C33: 191 | D33: 5.3
A34: ACT | B34: No | C34: 3402 | D34: 94.7
A35: ACT | B35: Not stated | C35: 310 | D35: . .
A36: ACT | B36: Total | C36: 3903 | D36: 100
A37: NT | B37: Yes | C37: 276 | D37: 3.1
A38: NT | B38: No | C38: 8636 | D38: 96.9
A39: NT | B39: Not stated | C39: 1087 | D39: . .
A40: NT | B40: Total | C40: 9999 | D40: 100
A42: Notes
A43: 1. Percentages are calculated using total clients excluding 'Not stated'.
A44: 2. Excludes 1,402 clients who only had support period(s) starting before 1 July 2019.
A45: . . not applicable

Sheet CLIENTS.18
A1: Table of contents
A2: Table CLIENTS.18: Clients, by educational enrolment status at beginning of support and age, and by state and territory, 2023–24
C4: Age group | D4: Age group | E4: Age group | F4: Age group | H4: All clients | I4: All clients
A5: State/territory | B5: Education and enrolment status | C5: 0–4 | D5: 5–14 | E5: 15–24 | F5: 25+ | H5: Number | I5: Per cent
A6: National | B6: Yes, preschool student | C6: 1585 | D6: 1307 | E6: — | F6: — | H6: 2892 | I6: 1.1
A7: National | B7: Yes, primary school student | C7: 255 | D7: 22044 | E7: — | F7: — | H7: 22299 | I7: 8.7
A8: National | B8: Yes, secondary school student | C8: — | D8: 6988 | E8: 9849 | F8: — | H8: 16837 | I8: 6.6
A9: National | B9: Yes, university student | C9: — | D9: — | E9: 1018 | F9: 799 | H9: 1817 | I9: 0.7
A10: National | B10: Yes, vocational education and training | C10: — | D10: — | E10: 2396 | F10: 1480 | H10: 3876 | I10: 1.5
A11: National | B11: Yes, other education or training | C11: 84 | D11: 210 | E11: 828 | F11: 661 | H11: 1783 | I11: 0.7
A12: National | B12: Yes, not stated | C12: 107 | D12: 575 | E12: 449 | F12: 143 | H12: 1274 | I12: 0.5
A13: National | B13: No | C13: 19453 | D13: 3150 | E13: 33831 | F13: 148586 | H13: 205020 | I13: 80.1
A14: National | B14: Not stated | C14: 2011 | D14: 3509 | E14: 4685 | F14: 14075 | H14: 24280 | I14: . .
A15: National | B15: Total | C15: 23495 | D15: 37783 | E15: 53056 | F15: 165744 | H15: 280078 | I15: 100
A16: NSW | B16: Yes, preschool student | C16: 436 | D16: 202 | E16: — | F16: — | H16: 638 | I16: 1
A17: NSW | B17: Yes, primary school student | C17: 48 | D17: 5284 | E17: — | F17: — | H17: 5332 | I17: 8.5
A18: NSW | B18: Yes, secondary school student | C18: — | D18: 2381 | E18: 3732 | F18: — | H18: 6113 | I18: 9.7
A19: NSW | B19: Yes, university student | C19: — | D19: — | E19: 419 | F19: 224 | H19: 643 | I19: 1
A20: NSW | B20: Yes, vocational education and training | C20: — | D20: — | E20: 1026 | F20: 480 | H20: 1506 | I20: 2.4
A21: NSW | B21: Yes, other education or training | C21: 32 | D21: 43 | E21: 253 | F21: 180 | H21: 508 | I21: 0.8
A22: NSW | B22: Yes, not stated | C22: 29 | D22: 84 | E22: 88 | F22: 29 | H22: 230 | I22: 0.4
A23: NSW | B23: No | C23: 5161 | D23: 750 | E23: 10288 | F23: 31768 | H23: 47967 | I23: 76.2
A24: NSW | B24: Not stated | C24: 543 | D24: 1003 | E24: 1256 | F24: 2152 | H24: 4954 | I24: . .
A25: NSW | B25: Total | C25: 6249 | D25: 9747 | E25: 17062 | F25: 34833 | H25: 67891 | I25: 100
A26: Vic | B26: Yes, preschool student | C26: 653 | D26: 527 | E26: — | F26: — | H26: 1180 | I26: 1.3
A27: Vic | B27: Yes, primary school student | C27: 77 | D27: 7877 | E27: — | F27: — | H27: 7954 | I27: 8.8
A28: Vic | B28: Yes, secondary school student | C28: — | D28: 2032 | E28: 2790 | F28: — | H28: 4822 | I28: 5.3
A29: Vic | B29: Yes, university student | C29: — | D29: — | E29: 369 | F29: 336 | H29: 705 | I29: 0.8
A30: Vic | B30: Yes, vocational education and training | C30: — | D30: — | E30: 684 | F30: 496 | H30: 1180 | I30: 1.3
A31: Vic | B31: Yes, other education or training | C31: 17 | D31: 62 | E31: 309 | F31: 237 | H31: 625 | I31: 0.7
A32: Vic | B32: Yes, not stated | C32: 36 | D32: 214 | E32: 187 | F32: 75 | H32: 512 | I32: 0.6
A33: Vic | B33: No | C33: 5422 | D33: 796 | E33: 9833 | F33: 57546 | H33: 73597 | I33: 81.3
A34: Vic | B34: Not stated | C34: 915 | D34: 1392 | E34: 1931 | F34: 7151 | H34: 11389 | I34: . .
A35: Vic | B35: Total | C35: 7120 | D35: 12900 | E35: 16103 | F35: 65841 | H35: 101964 | I35: 100
A36: Qld | B36: Yes, preschool student | C36: 183 | D36: 226 | E36: — | F36: — | H36: 409 | I36: 0.9
A37: Qld | B37: Yes, primary school student | C37: 42 | D37: 4350 | E37: — | F37: — | H37: 4392 | I37: 9.5
A38: Qld | B38: Yes, secondary school student | C38: — | D38: 1271 | E38: 1291 | F38: — | H38: 2562 | I38: 5.5
A39: Qld | B39: Yes, university student | C39: — | D39: — | E39: 109 | F39: 109 | H39: 218 | I39: 0.5
A40: Qld | B40: Yes, vocational education and training | C40: — | D40: — | E40: 313 | F40: 228 | H40: 541 | I40: 1.2
A41: Qld | B41: Yes, other education or training | C41: 18 | D41: 82 | E41: 140 | F41: 122 | H41: 362 | I41: 0.8
A42: Qld | B42: Yes, not stated | C42: 31 | D42: 162 | E42: 57 | F42: 20 | H42: 270 | I42: 0.6
A43: Qld | B43: No | C43: 4224 | D43: 654 | E43: 6588 | F43: 26130 | H43: 37596 | I43: 81.1
A44: Qld | B44: Not stated | C44: 177 | D44: 318 | E44: 526 | F44: 1447 | H44: 2468 | I44: . .
A45: Qld | B45: Total | C45: 4675 | D45: 7063 | E45: 9024 | F45: 28056 | H45: 48818 | I45: 100
A46: WA | B46: Yes, preschool student | C46: 144 | D46: 174 | E46: — | F46: — | H46: 318 | I46: 1.3
A47: WA | B47: Yes, primary school student | C47: 45 | D47: 2066 | E47: — | F47: — | H47: 2111 | I47: 8.9
A48: WA | B48: Yes, secondary school student | C48: — | D48: 659 | E48: 586 | F48: — | H48: 1245 | I48: 5.3
A49: WA | B49: Yes, university student | C49: — | D49: — | E49: 59 | F49: 66 | H49: 125 | I49: 0.5
A50: WA | B50: Yes, vocational education and training | C50: — | D50: — | E50: 142 | F50: 156 | H50: 298 | I50: 1.3
A51: WA | B51: Yes, other education or training | C51: 3 | D51: 10 | E51: 60 | F51: 64 | H51: 137 | I51: 0.6
A52: WA | B52: Yes, not stated | C52: 6 | D52: 42 | E52: 16 | F52: 9 | H52: 73 | I52: 0.3
A53: WA | B53: No | C53: 2116 | D53: 500 | E53: 2670 | F53: 14095 | H53: 19381 | I53: 81.8
A54: WA | B54: Not stated | C54: 52 | D54: 128 | E54: 165 | F54: 960 | H54: 1305 | I54: . .
A55: WA | B55: Total | C55: 2366 | D55: 3579 | E55: 3698 | F55: 15350 | H55: 24993 | I55: 100
A56: SA | B56: Yes, preschool student | C56: 89 | D56: 92 | E56: — | F56: — | H56: 181 | I56: 1.2
A57: SA | B57: Yes, primary school student | C57: 10 | D57: 1266 | E57: — | F57: — | H57: 1276 | I57: 8.3
A58: SA | B58: Yes, secondary school student | C58: — | D58: 327 | E58: 814 | F58: — | H58: 1141 | I58: 7.4
A59: SA | B59: Yes, university student | C59: — | D59: — | E59: 16 | F59: 19 | H59: 35 | I59: 0.2
A60: SA | B60: Yes, vocational education and training | C60: — | D60: — | E60: 70 | F60: 30 | H60: 100 | I60: 0.7
A61: SA | B61: Yes, other education or training | C61: 8 | D61: 6 | E61: 35 | F61: 18 | H61: 67 | I61: 0.4
A62: SA | B62: Yes, not stated | C62: 3 | D62: 30 | E62: 79 | F62: 2 | H62: 114 | I62: 0.7
A63: SA | B63: No | C63: 1320 | D63: 122 | E63: 2017 | F63: 8978 | H63: 12437 | I63: 81
A64: SA | B64: Not stated | C64: 269 | D64: 554 | E64: 640 | F64: 1903 | H64: 3366 | I64: . .
A65: SA | B65: Total | C65: 1699 | D65: 2397 | E65: 3671 | F65: 10950 | H65: 18717 | I65: 100
A66: Tas | B66: Yes, preschool student | C66: 15 | D66: 20 | E66: — | F66: — | H66: 35 | I66: 0.5
A67: Tas | B67: Yes, primary school student | C67: 7 | D67: 287 | E67: — | F67: — | H67: 294 | I67: 4.5
A68: Tas | B68: Yes, secondary school student | C68: — | D68: 114 | E68: 332 | F68: — | H68: 446 | I68: 6.8
A69: Tas | B69: Yes, university student | C69: — | D69: — | E69: 22 | F69: 20 | H69: 42 | I69: 0.6
A70: Tas | B70: Yes, vocational education and training | C70: — | D70: — | E70: 90 | F70: 37 | H70: 127 | I70: 1.9
A71: Tas | B71: Yes, other education or training | C71: — | D71: n.p. | E71: n.p. | F71: 14 | H71: 27 | I71: 0.4
A72: Tas | B72: Yes, not stated | C72: — | D72: n.p. | E72: n.p. | F72: — | H72: 11 | I72: 0.2
A73: Tas | B73: No | C73: 299 | D73: 40 | E73: 1119 | F73: 4082 | H73: 5540 | I73: 84.9
A74: Tas | B74: Not stated | C74: 6 | D74: 16 | E74: 30 | F74: 98 | H74: 150 | I74: . .
A75: Tas | B75: Total | C75: 327 | D75: 488 | E75: 1606 | F75: 4251 | H75: 6672 | I75: 100
A76: ACT | B76: Yes, preschool student | C76: 21 | D76: 21 | E76: — | F76: — | H76: 42 | I76: 1.1
A77: ACT | B77: Yes, primary school student | C77: 3 | D77: 260 | E77: — | F77: — | H77: 263 | I77: 7
A78: ACT | B78: Yes, secondary school student | C78: — | D78: 39 | E78: 198 | F78: — | H78: 237 | I78: 6.3
A79: ACT | B79: Yes, university student | C79: — | D79: — | E79: 15 | F79: 22 | H79: 37 | I79: 1
A80: ACT | B80: Yes, vocational education and training | C80: — | D80: — | E80: 52 | F80: 43 | H80: 95 | I80: 2.5
A81: ACT | B81: Yes, other education or training | C81: 2 | D81: 1 | E81: 15 | F81: 14 | H81: 32 | I81: 0.9
A82: ACT | B82: Yes, not stated | C82: — | D82: 4 | E82: 17 | F82: 9 | H82: 30 | I82: 0.8
A83: ACT | B83: No | C83: 215 | D83: 60 | E83: 478 | F83: 2271 | H83: 3024 | I83: 80.4
A84: ACT | B84: Not stated | C84: 15 | D84: 29 | E84: 68 | F84: 134 | H84: 246 | I84: . .
A85: ACT | B85: Total | C85: 256 | D85: 414 | E85: 843 | F85: 2493 | H85: 4006 | I85: 100
A86: NT | B86: Yes, preschool student | C86: 49 | D86: 47 | E86: — | F86: — | H86: 96 | I86: 1
A87: NT | B87: Yes, primary school student | C87: 23 | D87: 743 | E87: — | F87: — | H87: 766 | I87: 8.1
A88: NT | B88: Yes, secondary school student | C88: — | D88: 178 | E88: 162 | F88: — | H88: 340 | I88: 3.6
A89: NT | B89: Yes, university student | C89: — | D89: — | E89: 9 | F89: 10 | H89: 19 | I89: 0.2
A90: NT | B90: Yes, vocational education and training | C90: — | D90: — | E90: 36 | F90: 24 | H90: 60 | I90: 0.6
A91: NT | B91: Yes, other education or training | C91: 4 | D91: 6 | E91: 11 | F91: 18 | H91: 39 | I91: 0.4
A92: NT | B92: Yes, not stated | C92: 5 | D92: 36 | E92: 9 | F92: 2 | H92: 52 | I92: 0.6
A93: NT | B93: No | C93: 802 | D93: 259 | E93: 1298 | F93: 5703 | H93: 8062 | I93: 85.5
A94: NT | B94: Not stated | C94: 54 | D94: 89 | E94: 108 | F94: 395 | H94: 646 | I94: . .
A95: NT | B95: Total | C95: 937 | D95: 1358 | E95: 1633 | F95: 6152 | H95: 10080 | I95: 100
A97: Notes
A98: 1. Clients formally enrolled in an academic institution or technical college, or other accredited teaching institution, and/or engaged in employment related formal training.
A99: 2. Clients with a missing or invalid education status are recorded under 'Not stated'.
A100: 3. Per cent calculations based on total clients less 'Not stated'.
A101: — nil or rounded to zero
A102: . . not applicable
...

Sheet CLIENTS.19
A1: Table of contents
A2: Table CLIENTS.19: Clients aged 15 or over, by labour force status, and by state and territory, 2023–24
C4: Males | D4: Males | E4: Females | F4: Females | G4: All clients | H4: All clients
A5: State/territory | B5: Labour force status | C5: Number | D5: Per cent | E5: Number | F5: Per cent | G5: Number | H5: Per cent
A6: National | B6: Employed full-time | C6: 3746 | D6: 5 | E6: 6851 | F6: 5.6 | G6: 10597 | H6: 5.4
A7: National | B7: Employed part-time | C7: 4688 | D7: 6.3 | E7: 14909 | F7: 12.1 | G7: 19597 | H7: 9.9
A8: National | B8: Employed don't know | C8: 848 | D8: 1.1 | E8: 2024 | F8: 1.6 | G8: 2872 | H8: 1.5
A9: National | B9: Unemployed | C9: 41480 | D9: 55.4 | E9: 60090 | F9: 48.9 | G9: 101570 | H9: 51.4
A10: National | B10: Not in labour force | C10: 24146 | D10: 32.2 | E10: 38910 | F10: 31.7 | G10: 63056 | H10: 31.9
A11: National | B11: Not stated | C11: 7224 | D11: . . | E11: 13884 | F11: . . | G11: 21108 | H11: . .
A12: National | B12: Total | C12: 82132 | D12: 100 | E12: 136668 | F12: 100 | G12: 218800 | H12: 100
A13: NSW | B13: Employed full-time | C13: 796 | D13: 4.5 | E13: 1555 | F13: 5.2 | G13: 2351 | H13: 4.9
A14: NSW | B14: Employed part-time | C14: 1313 | D14: 7.4 | E14: 4080 | F14: 13.5 | G14: 5393 | H14: 11.3
A15: NSW | B15: Employed don't know | C15: 104 | D15: 0.6 | E15: 239 | F15: 0.8 | G15: 343 | H15: 0.7
A16: NSW | B16: Unemployed | C16: 11977 | D16: 67.4 | E16: 16727 | F16: 55.5 | G16: 28704 | H16: 59.9
A17: NSW | B17: Not in labour force | C17: 3579 | D17: 20.1 | E17: 7513 | F17: 24.9 | G17: 11092 | H17: 23.2
A18: NSW | B18: Not stated | C18: 1837 | D18: . . | E18: 2175 | F18: . . | G18: 4012 | H18: . .
A19: NSW | B19: Total | C19: 19606 | D19: 100 | E19: 32289 | F19: 100 | G19: 51895 | H19: 100
A20: Vic | B20: Employed full-time | C20: 1677 | D20: 5.8 | E20: 2894 | F20: 6.9 | G20: 4571 | H20: 6.4
A21: Vic | B21: Employed part-time | C21: 1719 | D21: 5.9 | E21: 5610 | F21: 13.4 | G21: 7329 | H21: 10.3
A22: Vic | B22: Employed don't know | C22: 520 | D22: 1.8 | E22: 1297 | F22: 3.1 | G22: 1817 | H22: 2.6
A23: Vic | B23: Unemployed | C23: 12686 | D23: 43.8 | E23: 17352 | F23: 41.3 | G23: 30038 | H23: 42.4
A24: Vic | B24: Not in labour force | C24: 12332 | D24: 42.6 | E24: 14838 | F24: 35.3 | G24: 27170 | H24: 38.3
A25: Vic | B25: Not stated | C25: 3396 | D25: . . | E25: 7623 | F25: . . | G25: 11019 | H25: . .
A26: Vic | B26: Total | C26: 32330 | D26: 100 | E26: 49614 | F26: 100 | G26: 81944 | H26: 100
A27: Qld | B27: Employed full-time | C27: 645 | D27: 4.9 | E27: 950 | F27: 4.4 | G27: 1595 | H27: 4.6
A28: Qld | B28: Employed part-time | C28: 767 | D28: 5.8 | E28: 2240 | F28: 10.4 | G28: 3007 | H28: 8.7
A29: Qld | B29: Employed don't know | C29: 116 | D29: 0.9 | E29: 210 | F29: 1 | G29: 326 | H29: 0.9
A30: Qld | B30: Unemployed | C30: 8389 | D30: 63.8 | E30: 11502 | F30: 53.4 | G30: 19891 | H30: 57.3
A31: Qld | B31: Not in labour force | C31: 3229 | D31: 24.6 | E31: 6652 | F31: 30.9 | G31: 9881 | H31: 28.5
A32: Qld | B32: Not stated | C32: 804 | D32: . . | E32: 1576 | F32: . . | G32: 2380 | H32: . .
A33: Qld | B33: Total | C33: 13950 | D33: 100 | E33: 23130 | F33: 100 | G33: 37080 | H33: 100
A34: WA | B34: Employed full-time | C34: 200 | D34: 3.9 | E34: 753 | F34: 6 | G34: 953 | H34: 5.4
A35: WA | B35: Employed part-time | C35: 276 | D35: 5.4 | E35: 1232 | F35: 9.8 | G35: 1508 | H35: 8.5
A36: WA | B36: Employed don't know | C36: 23 | D36: 0.4 | E36: 103 | F36: 0.8 | G36: 126 | H36: 0.7
A37: WA | B37: Unemployed | C37: 3698 | D37: 71.8 | E37: 7422 | F37: 59.2 | G37: 11120 | H37: 62.9
A38: WA | B38: Not in labour force | C38: 954 | D38: 18.5 | E38: 3021 | F38: 24.1 | G38: 3975 | H38: 22.5
A39: WA | B39: Not stated | C39: 475 | D39: . . | E39: 891 | F39: . . | G39: 1366 | H39: . .
A40: WA | B40: Total | C40: 5626 | D40: 100 | E40: 13422 | F40: 100 | G40: 19048 | H40: 100
A41: SA | B41: Employed full-time | C41: 214 | D41: 4.3 | E41: 322 | F41: 3.9 | G41: 536 | H41: 4
A42: SA | B42: Employed part-time | C42: 331 | D42: 6.6 | E42: 940 | F42: 11.4 | G42: 1271 | H42: 9.6
A43: SA | B43: Employed don't know | C43: 40 | D43: 0.8 | E43: 93 | F43: 1.1 | G43: 133 | H43: 1
A44: SA | B44: Unemployed | C44: 2702 | D44: 53.7 | E44: 3453 | F44: 42 | G44: 6155 | H44: 46.5
A45: SA | B45: Not in labour force | C45: 1747 | D45: 34.7 | E45: 3404 | F45: 41.5 | G45: 5151 | H45: 38.9
A46: SA | B46: Not stated | C46: 490 | D46: . . | E46: 885 | F46: . . | G46: 1375 | H46: . .
A47: SA | B47: Total | C47: 5524 | D47: 100 | E47: 9097 | F47: 100 | G47: 14621 | H47: 100
A48: Tas | B48: Employed full-time | C48: 81 | D48: 3.3 | E48: 53 | F48: 1.6 | G48: 134 | H48: 2.4
A49: Tas | B49: Employed part-time | C49: 155 | D49: 6.4 | E49: 374 | F49: 11.6 | G49: 529 | H49: 9.4
A50: Tas | B50: Employed don't know | C50: 20 | D50: 0.8 | E50: 15 | F50: 0.5 | G50: 35 | H50: 0.6
A51: Tas | B51: Unemployed | C51: 1162 | D51: 47.7 | E51: 1186 | F51: 36.9 | G51: 2348 | H51: 41.5
A52: Tas | B52: Not in labour force | C52: 1020 | D52: 41.8 | E52: 1589 | F52: 49.4 | G52: 2609 | H52: 46.1
A53: Tas | B53: Not stated | C53: 119 | D53: . . | E53: 83 | F53: . . | G53: 202 | H53: . .
A54: Tas | B54: Total | C54: 2557 | D54: 100 | E54: 3300 | F54: 100 | G54: 5857 | H54: 100
A55: ACT | B55: Employed full-time | C55: 78 | D55: 5.9 | E55: 127 | F55: 7.1 | G55: 205 | H55: 6.6
A56: ACT | B56: Employed part-time | C56: 103 | D56: 7.8 | E56: 268 | F56: 15.1 | G56: 371 | H56: 12
A57: ACT | B57: Employed don't know | C57: 18 | D57: 1.4 | E57: 29 | F57: 1.6 | G57: 47 | H57: 1.5
A58: ACT | B58: Unemployed | C58: 800 | D58: 60.4 | E58: 859 | F58: 48.3 | G58: 1659 | H58: 53.5
A59: ACT | B59: Not in labour force | C59: 325 | D59: 24.5 | E59: 494 | F59: 27.8 | G59: 819 | H59: 26.4
A60: ACT | B60: Not stated | C60: 86 | D60: . . | E60: 149 | F60: . . | G60: 235 | H60: . .
A61: ACT | B61: Total | C61: 1410 | D61: 100 | E61: 1926 | F61: 100 | G61: 3336 | H61: 100
A62: NT | B62: Employed full-time | C62: 73 | D62: 3.4 | E62: 225 | F62: 4.6 | G62: 298 | H62: 4.2
A63: NT | B63: Employed part-time | C63: 65 | D63: 3 | E63: 243 | F63: 5 | G63: 308 | H63: 4.4
A64: NT | B64: Employed don't know | C64: 11 | D64: 0.5 | E64: 49 | F64: 1 | G64: 60 | H64: 0.9
A65: NT | B65: Unemployed | C65: 756 | D65: 34.8 | E65: 2478 | F65: 50.9 | G65: 3234 | H65: 46
A66: NT | B66: Not in labour force | C66: 1266 | D66: 58.3 | E66: 1870 | F66: 38.4 | G66: 3136 | H66: 44.6
A67: NT | B67: Not stated | C67: 98 | D67: . . | E67: 651 | F67: . . | G67: 749 | H67: . .
A68: NT | B68: Total | C68: 2269 | D68: 100 | E68: 5516 | F68: 100 | G68: 7785 | H68: 100
A70: Notes
A71: 1. The labour force status at the beginning of support for clients 15 years and over.
A72: 2. Clients engaged in employment with unknown employment status (full-time/part-time) are recorded under 'Employed don't know'.
A73: 3. Clients aged 15 and over with missing or invalid information are recorded under 'Not stated'.
A74: 4. Number of clients aged under 15 excluded: Aust 61,278, NSW 15,996, Vic 20,020, Qld 11,738, WA 5,945, SA 4,096, Tas 815, ACT 670, NT 2,295.
A75: 5. Per cent calculations based on total clients less 'Not stated'.
A76: . . not applicable

Sheet CLIENTS.20
A1: Table of contents
A2: Table CLIENTS.20: Clients, by educational enrolment status at beginning of support and labour force status, and by state and territory, 2023–24
A4: State/territory | B4: Education and enrolment status | C4: Employed full-time | D4: Employed part-time | E4: Employed don't know | F4: Unemployed | G4: Not in labour force | H4: Not stated | I4: Under 15 | J4: Total
A5: National | B5: Yes, preschool student | C5: — | D5: — | E5: — | F5: — | G5: — | H5: — | I5: 2892 | J5: 2892
A6: National | B6: Yes, primary school student | C6: — | D6: — | E6: — | F6: — | G6: — | H6: — | I6: 22299 | J6: 22299
A7: National | B7: Yes, secondary school student | C7: 17 | D7: 1175 | E7: 49 | F7: 2667 | G7: 4223 | H7: 1718 | I7: 6988 | J7: 16837
A8: National | B8: Yes, university student | C8: 88 | D8: 572 | E8: 39 | F8: 690 | G8: 357 | H8: 71 | I8: — | J8: 1817
A9: National | B9: Yes, vocational education and training | C9: 370 | D9: 793 | E9: 44 | F9: 1886 | G9: 708 | H9: 75 | I9: — | J9: 3876
A10: National | B10: Yes, other education or training | C10: 130 | D10: 249 | E10: 22 | F10: 730 | G10: 311 | H10: 47 | I10: 294 | J10: 1783
A11: National | B11: Yes, not stated | C11: 9 | D11: 22 | E11: 7 | F11: 135 | G11: 192 | H11: 227 | I11: 682 | J11: 1274
A12: National | B12: No | C12: 9501 | D12: 15942 | E12: 2137 | F12: 91958 | G12: 55025 | H12: 7854 | I12: 22603 | J12: 205020
A13: National | B13: Not stated | C13: 482 | D13: 844 | E13: 574 | F13: 3504 | G13: 2240 | H13: 11116 | I13: 5520 | J13: 24280
A14: National | B14: Total | C14: 10597 | D14: 19597 | E14: 2872 | F14: 101570 | G14: 63056 | H14: 21108 | I14: 61278 | J14: 280078
A15: NSW | B15: Yes, preschool student | C15: — | D15: — | E15: — | F15: — | G15: — | H15: — | I15: 638 | J15: 638
A16: NSW | B16: Yes, primary school student | C16: — | D16: — | E16: — | F16: — | G16: — | H16: — | I16: 5332 | J16: 5332
A17: NSW | B17: Yes, secondary school student | C17: 5 | D17: 471 | E17: 12 | F17: 1129 | G17: 1351 | H17: 764 | I17: 2381 | J17: 6113
A18: NSW | B18: Yes, university student | C18: 28 | D18: 248 | E18: 3 | F18: 255 | G18: 97 | H18: 12 | I18: — | J18: 643
A19: NSW | B19: Yes, vocational education and training | C19: 174 | D19: 303 | E19: 12 | F19: 807 | G19: 192 | H19: 18 | I19: — | J19: 1506
A20: NSW | B20: Yes, other education or training | C20: 54 | D20: 67 | E20: 5 | F20: 242 | G20: 59 | H20: 6 | I20: 75 | J20: 508
A21: NSW | B21: Yes, not stated | C21: 3 | D21: 6 | E21: 2 | F21: 42 | G21: 31 | H21: 33 | I21: 113 | J21: 230
A22: NSW | B22: No | C22: 2027 | D22: 4175 | E22: 240 | F22: 25541 | G22: 9090 | H22: 983 | I22: 5911 | J22: 47967
A23: NSW | B23: Not stated | C23: 60 | D23: 123 | E23: 69 | F23: 688 | G23: 272 | H23: 2196 | I23: 1546 | J23: 4954
A24: NSW | B24: Total | C24: 2351 | D24: 5393 | E24: 343 | F24: 28704 | G24: 11092 | H24: 4012 | I24: 15996 | J24: 67891
A25: Vic | B25: Yes, preschool student | C25: — | D25: — | E25: — | F25: — | G25: — | H25: — | I25: 1180 | J25: 1180
A26: Vic | B26: Yes, primary school student | C26: — | D26: — | E26: — | F26: — | G26: — | H26: — | I26: 7954 | J26: 7954
A27: Vic | B27: Yes, secondary school student | C27: 8 | D27: 296 | E27: 20 | F27: 673 | G27: 1163 | H27: 630 | I27: 2032 | J27: 4822
A28: Vic | B28: Yes, university student | C28: 38 | D28: 196 | E28: 25 | F28: 256 | G28: 151 | H28: 39 | I28: — | J28: 705
A29: Vic | B29: Yes, vocational education and training | C29: 83 | D29: 259 | E29: 19 | F29: 537 | G29: 240 | H29: 42 | I29: — | J29: 1180
A30: Vic | B30: Yes, other education or training | C30: 36 | D30: 95 | E30: 14 | F30: 255 | G30: 121 | H30: 25 | I30: 79 | J30: 625
A31: Vic | B31: Yes, not stated | C31: 3 | D31: 9 | E31: 1 | F31: 43 | G31: 56 | H31: 150 | I31: 250 | J31: 512
A32: Vic | B32: No | C32: 4168 | D32: 6088 | E32: 1365 | F32: 26687 | G32: 24377 | H32: 4694 | I32: 6218 | J32: 73597
A33: Vic | B33: Not stated | C33: 235 | D33: 386 | E33: 373 | F33: 1587 | G33: 1062 | H33: 5439 | I33: 2307 | J33: 11389
A34: Vic | B34: Total | C34: 4571 | D34: 7329 | E34: 1817 | F34: 30038 | G34: 27170 | H34: 11019 | I34: 20020 | J34: 101964
A35: Qld | B35: Yes, preschool student | C35: — | D35: — | E35: — | F35: — | G35: — | H35: — | I35: 409 | J35: 409
A36: Qld | B36: Yes, primary school student | C36: — | D36: — | E36: — | F36: — | G36: — | H36: — | I36: 4392 | J36: 4392
A37: Qld | B37: Yes, secondary school student | C37: 2 | D37: 148 | E37: 4 | F37: 371 | G37: 623 | H37: 143 | I37: 1271 | J37: 2562
A38: Qld | B38: Yes, university student | C38: 9 | D38: 54 | E38: 6 | F38: 95 | G38: 43 | H38: 11 | I38: — | J38: 218
A39: Qld | B39: Yes, vocational education and training | C39: 50 | D39: 101 | E39: 4 | F39: 265 | G39: 115 | H39: 6 | I39: — | J39: 541
A40: Qld | B40: Yes, other education or training | C40: 27 | D40: 46 | E40: 3 | F40: 114 | G40: 66 | H40: 6 | I40: 100 | J40: 362
A41: Qld | B41: Yes, not stated | C41: — | D41: 2 | E41: 1 | F41: 27 | G41: 25 | H41: 22 | I41: 193 | J41: 270
A42: Qld | B42: No | C42: 1476 | D42: 2599 | E42: 260 | F42: 18671 | G42: 8778 | H42: 934 | I42: 4878 | J42: 37596
A43: Qld | B43: Not stated | C43: 31 | D43: 57 | E43: 48 | F43: 348 | G43: 231 | H43: 1258 | I43: 495 | J43: 2468
A44: Qld | B44: Total | C44: 1595 | D44: 3007 | E44: 326 | F44: 19891 | G44: 9881 | H44: 2380 | I44: 11738 | J44: 48818
A45: WA | B45: Yes, preschool student | C45: — | D45: — | E45: — | F45: — | G45: — | H45: — | I45: 318 | J45: 318
A46: WA | B46: Yes, primary school student | C46: — | D46: — | E46: — | F46: — | G46: — | H46: — | I46: 2111 | J46: 2111
A47: WA | B47: Yes, secondary school student | C47: 1 | D47: 59 | E47: 2 | F47: 183 | G47: 271 | H47: 70 | I47: 659 | J47: 1245
A48: WA | B48: Yes, university student | C48: 10 | D48: 48 | E48: — | F48: 40 | G48: 27 | H48: — | I48: — | J48: 125
A49: WA | B49: Yes, vocational education and training | C49: 22 | D49: 66 | E49: 4 | F49: 145 | G49: 60 | H49: 1 | I49: — | J49: 298
A50: WA | B50: Yes, other education or training | C50: 5 | D50: 20 | E50: — | F50: 70 | G50: 28 | H50: 1 | I50: 13 | J50: 137
A51: WA | B51: Yes, not stated | C51: 2 | D51: 1 | E51: 1 | F51: 13 | G51: 5 | H51: 3 | I51: 48 | J51: 73
A52: WA | B52: No | C52: 899 | D52: 1296 | E52: 107 | F52: 10560 | G52: 3549 | H52: 354 | I52: 2616 | J52: 19381
A53: WA | B53: Not stated | C53: 14 | D53: 18 | E53: 12 | F53: 109 | G53: 35 | H53: 937 | I53: 180 | J53: 1305
A54: WA | B54: Total | C54: 953 | D54: 1508 | E54: 126 | F54: 11120 | G54: 3975 | H54: 1366 | I54: 5945 | J54: 24993
A55: SA | B55: Yes, preschool student | C55: — | D55: — | E55: — | F55: — | G55: — | H55: — | I55: 181 | J55: 181
A56: SA | B56: Yes, primary school student | C56: — | D56: — | E56: — | F56: — | G56: — | H56: — | I56: 1276 | J56: 1276
A57: SA | B57: Yes, secondary school student | C57: — | D57: 113 | E57: 4 | F57: 114 | G57: 525 | H57: 58 | I57: 327 | J57: 1141
A58: SA | B58: Yes, university student | C58: — | D58: 2 | E58: 1 | F58: 16 | G58: 10 | H58: 6 | I58: — | J58: 35
A59: SA | B59: Yes, vocational education and training | C59: 3 | D59: 14 | E59: 1 | F59: 37 | G59: 39 | H59: 6 | I59: — | J59: 100
A60: SA | B60: Yes, other education or training | C60: 3 | D60: 7 | E60: — | F60: 16 | G60: 24 | H60: 3 | I60: 14 | J60: 67
A61: SA | B61: Yes, not stated | C61: — | D61: 1 | E61: — | F61: 3 | G61: 69 | H61: 8 | I61: 33 | J61: 114
A62: SA | B62: No | C62: 410 | D62: 893 | E62: 73 | F62: 5309 | G62: 3909 | H62: 401 | I62: 1442 | J62: 12437
A63: SA | B63: Not stated | C63: 120 | D63: 241 | E63: 54 | F63: 660 | G63: 575 | H63: 893 | I63: 823 | J63: 3366
A64: SA | B64: Total | C64: 536 | D64: 1271 | E64: 133 | F64: 6155 | G64: 5151 | H64: 1375 | I64: 4096 | J64: 18717
A65: Tas | B65: Yes, preschool student | C65: — | D65: — | E65: — | F65: — | G65: — | H65: — | I65: 35 | J65: 35
A66: Tas | B66: Yes, primary school student | C66: — | D66: — | E66: — | F66: — | G66: — | H66: — | I66: 294 | J66: 294
A67: Tas | B67: Yes, secondary school student | C67: — | D67: 60 | E67: n.p. | F67: 98 | G67: 160 | H67: n.p. | I67: 114 | J67: 446
A68: Tas | B68: Yes, university student | C68: — | D68: 6 | E68: — | F68: 17 | G68: 19 | H68: — | I68: — | J68: 42
A69: Tas | B69: Yes, vocational education and training | C69: 20 | D69: 22 | E69: n.p. | F69: 51 | G69: 31 | H69: n.p. | I69: — | J69: 127
A70: Tas | B70: Yes, other education or training | C70: n.p. | D70: 6 | E70: — | F70: 12 | G70: 6 | H70: n.p. | I70: n.p. | J70: 27
A71: Tas | B71: Yes, not stated | C71: n.p. | D71: n.p. | E71: — | F71: — | G71: — | H71: — | I71: n.p. | J71: 11
A72: Tas | B72: No | C72: 113 | D72: 429 | E72: 27 | F72: 2141 | G72: 2372 | H72: 119 | I72: 339 | J72: 5540
A73: Tas | B73: Not stated | C73: — | D73: n.p. | E73: n.p. | F73: 29 | G73: 21 | H73: 70 | I73: 22 | J73: 150
A74: Tas | B74: Total | C74: 134 | D74: 529 | E74: 35 | F74: 2348 | G74: 2609 | H74: 202 | I74: 815 | J74: 6672
A75: ACT | B75: Yes, preschool student | C75: — | D75: — | E75: — | F75: — | G75: — | H75: — | I75: 42 | J75: 42
A76: ACT | B76: Yes, primary school student | C76: — | D76: — | E76: — | F76: — | G76: — | H76: — | I76: 263 | J76: 263
A77: ACT | B77: Yes, secondary school student | C77: — | D77: 22 | E77: 3 | F77: 66 | G77: 79 | H77: 28 | I77: 39 | J77: 237
A78: ACT | B78: Yes, university student | C78: — | D78: 15 | E78: 2 | F78: 11 | G78: 8 | H78: 1 | I78: — | J78: 37
A79: ACT | B79: Yes, vocational education and training | C79: 12 | D79: 19 | E79: 1 | F79: 37 | G79: 25 | H79: 1 | I79: — | J79: 95
A80: ACT | B80: Yes, other education or training | C80: 1 | D80: 6 | E80: — | F80: 15 | G80: 5 | H80: 2 | I80: 3 | J80: 32
A81: ACT | B81: Yes, not stated | C81: 1 | D81: 2 | E81: 2 | F81: 8 | G81: 6 | H81: 7 | I81: 4 | J81: 30
A82: ACT | B82: No | C82: 182 | D82: 299 | E82: 34 | F82: 1449 | G82: 675 | H82: 110 | I82: 275 | J82: 3024
A83: ACT | B83: Not stated | C83: 9 | D83: 8 | E83: 5 | F83: 73 | G83: 21 | H83: 86 | I83: 44 | J83: 246
A84: ACT | B84: Total | C84: 205 | D84: 371 | E84: 47 | F84: 1659 | G84: 819 | H84: 235 | I84: 670 | J84: 4006
A85: NT | B85: Yes, preschool student | C85: — | D85: — | E85: — | F85: — | G85: — | H85: — | I85: 96 | J85: 96
A86: NT | B86: Yes, primary school student | C86: — | D86: — | E86: — | F86: — | G86: — | H86: — | I86: 766 | J86: 766
A87: NT | B87: Yes, secondary school student | C87: 1 | D87: 9 | E87: — | F87: 57 | G87: 78 | H87: 17 | I87: 178 | J87: 340
A88: NT | B88: Yes, university student | C88: 4 | D88: 3 | E88: 2 | F88: 5 | G88: 3 | H88: 2 | I88: — | J88: 19
A89: NT | B89: Yes, vocational education and training | C89: 8 | D89: 12 | E89: 2 | F89: 26 | G89: 12 | H89: — | I89: — | J89: 60
A90: NT | B90: Yes, other education or training | C90: 5 | D90: 4 | E90: — | F90: 14 | G90: 3 | H90: 3 | I90: 10 | J90: 39
A91: NT | B91: Yes, not stated | C91: — | D91: — | E91: — | F91: 4 | G91: 2 | H91: 5 | I91: 41 | J91: 52
A92: NT | B92: No | C92: 263 | D92: 270 | E92: 42 | F92: 3071 | G92: 2987 | H92: 368 | I92: 1061 | J92: 8062
A93: NT | B93: Not stated | C93: 17 | D93: 10 | E93: 14 | F93: 57 | G93: 51 | H93: 354 | I93: 143 | J93: 646
A94: NT | B94: Total | C94: 298 | D94: 308 | E94: 60 | F94: 3234 | G94: 3136 | H94: 749 | I94: 2295 | J94: 10080
A96: Notes
A97: 1. The labour force status at the beginning of support for clients 15 years and over.
A98: 2. Clients engaged in employment with unknown employment status (full-time/part-time) are recorded under 'Employed don't know'.
A99: 3. Clients with a missing or invalid education status, and clients aged 15 and over with missing or invalid information are recorded under 'Not stated'.
A100: 4. Clients formally enrolled in an academic institution or technical college, or other accredited teaching institution, and/or engaged in employment related formal training.
A101: 5. Clients with a missing or invalid education status are recorded under 'Not stated'.
A102: 6. Clients may access services in more than one state or territory. Therefore, the total will be less than the sum of jurisdictions.
...

Sheet CLIENTS.21
A1: Table of contents
A2: Table CLIENTS.21: Clients, by reasons for seeking assistance, and by state and territory, 2023–24
A4: State/ territory | B4: Group | C4: Reason for seeking assistance | D4: Males | E4: Females | F4: Total clients (number) | G4: Total clients (per cent)
A5: National | B5: Financial | C5: Financial | D5: 61476 | E5: 85537 | F5: 147013 | G5: 52.8
A6: National | B6: Financial | C6: Financial difficulties | D6: 47128 | E6: 67111 | F6: 114239 | G6: 41.1
A7: National | B7: Financial | C7: Housing affordability stress | D7: 41595 | E7: 57802 | F7: 99397 | G7: 35.7
A8: National | B8: Financial | C8: Employment difficulties | D8: 7331 | E8: 8310 | F8: 15641 | G8: 5.6
A9: National | B9: Financial | C9: Unemployment | D9: 15494 | E9: 17748 | F9: 33242 | G9: 11.9
A10: National | B10: Financial | C10: Problematic gambling | D10: 408 | E10: 267 | F10: 675 | G10: 0.2
A11: National | B11: Accommodation | C11: Accommodation | D11: 67556 | E11: 86677 | F11: 154233 | G11: 55.4
A12: National | B12: Accommodation | C12: Housing crisis | D12: 44763 | E12: 59268 | F12: 104031 | G12: 37.4
A13: National | B13: Accommodation | C13: Inadequate or inappropriate dwelling conditions | D13: 34061 | E13: 41642 | F13: 75703 | G13: 27.2
A14: National | B14: Accommodation | C14: Previous accommodation ended | D14: 21470 | E14: 26824 | F14: 48294 | G14: 17.4
A15: National | B15: Interpersonal relationships | C15: Interpersonal relationships | D15: 41841 | E15: 96346 | F15: 138187 | G15: 49.7
A16: National | B16: Interpersonal relationships | C16: Time out from family/other situation | D16: 10335 | E16: 17563 | F16: 27898 | G16: 10
... A35: National | B35: Other | C35: Other | D35: 11235 | E35: 15057 | F35: 26292 | G35: 9.4
A36: National | B36: Not stated | C36: Not stated | D36: 874 | E36: 948 | F36: 1822 | G36: . .
A37: NSW | B37: Financial | C37: Financial | D37: 14862 | E37: 21115 | F37: 35977 | G37: 53.6
A38: NSW | B38: Financial | C38: Financial difficulties | D38: 10576 | E38: 15563 | F38: 26139 | G38: 38.9
A39: NSW | B39: Financial | C39: Housing affordability stress | D39: 9907 | E39: 14054 | F39: 23961 | G39: 35.7
A40: NSW | B40: Financial | C40: Employment difficulties | D40: 1636 | E40: 1954 | F40: 3590 | G40: 5.3
A41: NSW | B41: Financial | C41: Unemployment | D41: 3658 | E41: 4386 | F41: 8044 | G41: 12
A42: NSW | B42: Financial | C42: Problematic gambling | D42: 141 | E42: 69 | F42: 210 | G42: 0.3
A43: NSW | B43: Accommodation | C43: Accommodation | D43: 16095 | E43: 22056 | F43: 38151 | G43: 56.8
A44: NSW | B44: Accommodation | C44: Housing crisis | D44: 11306 | E44: 15965 | F44: 27271 | G44: 40.6
A45: NSW | B45: Accommodation | C45: Inadequate or inappropriate dwelling conditions | D45: 6273 | E45: 8599 | F45: 14872 | G45: 22.1
A46: NSW | B46: Accommodation | C46: Previous accommodation ended | D46: 4911 | E46: 6339 | F46: 11250 | G46: 16.7
A47: NSW | B47: Interpersonal relationships | C47: Interpersonal relationships | D47: 10593 | E47: 22815 | F47: 33408 | G47: 49.7
A48: NSW | B48: Interpersonal relationships | C48: Time out from family/other situation | D48: 2622 | E48: 4388 | F48: 7010 | G48: 10.4
... A67: NSW | B67: Other | C67: Other | D67: 2162 | E67: 3019 | F67: 5181 | G67: 7.7
A68: NSW | B68: Not stated | C68: Not stated | D68: 332 | E68: 388 | F68: 720 | G68: . .
A69: Vic | B69: Financial | C69: Financial | D69: 23963 | E69: 32616 | F69: 56579 | G69: 55.8
A70: Vic | B70: Financial | C70: Financial difficulties | D70: 20059 | E70: 27986 | F70: 48045 | G70: 47.3
A71: Vic | B71: Financial | C71: Housing affordability stress | D71: 16110 | E71: 21732 | F71: 37842 | G71: 37.3
A72: Vic | B72: Financial | C72: Employment difficulties | D72: 3183 | E72: 3665 | F72: 6848 | G72: 6.7
A73: Vic | B73: Financial | C73: Unemployment | D73: 6286 | E73: 7008 | F73: 13294 | G73: 13.1
A74: Vic | B74: Financial | C74: Problematic gambling | D74: 150 | E74: 111 | F74: 261 | G74: 0.3
A75: Vic | B75: Accommodation | C75: Accommodation | D75: 24197 | E75: 28645 | F75: 52842 | G75: 52.1
A76: Vic | B76: Accommodation | C76: Housing crisis | D76: 16403 | E76: 19924 | F76: 36327 | G76: 35.8
A77: Vic | B77: Accommodation | C77: Inadequate or inappropriate dwelling conditions | D77: 13920 | E77: 15539 | F77: 29459 | G77: 29
A78: Vic | B78: Accommodation | C78: Previous accommodation ended | D78: 9168 | E78: 10187 | F78: 19355 | G78: 19.1
A79: Vic | B79: Interpersonal relationships | C79: Interpersonal relationships | D79: 16902 | E79: 36327 | F79: 53229 | G79: 52.5
A80: Vic | B80: Interpersonal relationships | C80: Time out from family/other situation | D80: 3813 | E80: 5104 | F80: 8917 | G80: 8.8
... A99: Vic | B99: Other | C99: Other | D99: 4778 | E99: 5913 | F99: 10691 | G99: 10.5
A100: Vic | B100: Not stated | C100: Not stated | D100: 265 | E100: 230 | F100: 495 | G100: . .
A101: Qld | B101: Financial | C101: Financial | D101: 13104 | E101: 17857 | F101: 30961 | G101: 63.9
A102: Qld | B102: Financial | C102: Financial difficulties | D102: 10131 | E102: 13844 | F102: 23975 | G102: 49.5
A103: Qld | B103: Financial | C103: Housing affordability stress | D103: 9724 | E103: 13484 | F103: 23208 | G103: 47.9
A104: Qld | B104: Financial | C104: Employment difficulties | D104: 1116 | E104: 1248 | F104: 2364 | G104: 4.9
A105: Qld | B105: Financial | C105: Unemployment | D105: 2773 | E105: 3235 | F105: 6008 | G105: 12.4
A106: Qld | B106: Financial | C106: Problematic gambling | D106: 72 | E106: 45 | F106: 117 | G106: 0.2
A107: Qld | B107: Accommodation | C107: Accommodation | D107: 13343 | E107: 17155 | F107: 30498 | G107: 63
A108: Qld | B108: Accommodation | C108: Housing crisis | D108: 9034 | E108: 11949 | F108: 20983 | G108: 43.3
A109: Qld | B109: Accommodation | C109: Inadequate or inappropriate dwelling conditions | D109: 7290 | E109: 8969 | F109: 16259 | G109: 33.6
A110: Qld | B110: Accommodation | C110: Previous accommodation ended | D110: 4250 | E110: 5858 | F110: 10108 | G110: 20.9
A111: Qld | B111: Interpersonal relationships | C111: Interpersonal relationships | D111: 6438 | E111: 14434 | F111: 20872 | G111: 43.1
A112: Qld | B112: Interpersonal relationships | C112: Time out from family/other situation | D112: 1726 | E112: 3104 | F112: 4830 | G112: 10
... A131: Qld | B131: Other | C131: Other | D131: 1968 | E131: 2604 | F131: 4572 | G131: 9.4
A132: Qld | B132: Not stated | C132: Not stated | D132: 162 | E132: 218 | F132: 380 | G132: . .
A133: WA | B133: Financial | C133: Financial | D133: 3919 | E133: 6738 | F133: 10657 | G133: 42.9
A134: WA | B134: Financial | C134: Financial difficulties | D134: 3201 | E134: 5515 | F134: 8716 | G134: 35.1
A135: WA | B135: Financial | C135: Housing affordability stress | D135: 2624 | E135: 4127 | F135: 6751 | G135: 27.2
A136: WA | B136: Financial | C136: Employment difficulties | D136: 896 | E136: 950 | F136: 1846 | G136: 7.4
A137: WA | B137: Financial | C137: Unemployment | D137: 1408 | E137: 1795 | F137: 3203 | G137: 12.9
A138: WA | B138: Financial | C138: Problematic gambling | D138: 12 | E138: 8 | F138: 20 | G138: 0.1
A139: WA | B139: Accommodation | C139: Accommodation | D139: 3822 | E139: 6031 | F139: 9853 | G139: 39.6
A140: WA | B140: Accommodation | C140: Housing crisis | D140: 2062 | E140: 3349 | F140: 5411 | G140: 21.8
A141: WA | B141: Accommodation | C141: Inadequate or inappropriate dwelling conditions | D141: 2340 | E141: 3396 | F141: 5736 | G141: 23.1
A142: WA | B142: Accommodation | C142: Previous accommodation ended | D142: 1275 | E142: 2079 | F142: 3354 | G142: 13.5
A143: WA | B143: Interpersonal relationships | C143: Interpersonal relationships | D143: 3595 | E143: 10856 | F143: 14451 | G143: 58.1
A144: WA | B144: Interpersonal relationships | C144: Time out from family/other situation | D144: 1163 | E144: 2784 | F144: 3947 | G144: 15.9
... A163: WA | B163: Other | C163: Other | D163: 1588 | E163: 2480 | F163: 4068 | G163: 16.4
A164: WA | B164: Not stated | C164: Not stated | D164: 67 | E164: 64 | F164: 131 | G164: . .
A165: SA | B165: Financial | C165: Financial | D165: 2416 | E165: 3185 | F165: 5601 | G165: 29.9
A166: SA | B166: Financial | C166: Financial difficulties | D166: 1021 | E166: 1513 | F166: 2534 | G166: 13.5
A167: SA | B167: Financial | C167: Housing affordability stress | D167: 1279 | E167: 1747 | F167: 3026 | G167: 16.2
A168: SA | B168: Financial | C168: Employment difficulties | D168: 246 | E168: 220 | F168: 466 | G168: 2.5
A169: SA | B169: Financial | C169: Unemployment | D169: 910 | E169: 884 | F169: 1794 | G169: 9.6
A170: SA | B170: Financial | C170: Problematic gambling | D170: 30 | E170: 27 | F170: 57 | G170: 0.3
A171: SA | B171: Accommodation | C171: Accommodation | D171: 5891 | E171: 7538 | F171: 13429 | G171: 71.8
A172: SA | B172: Accommodation | C172: Housing crisis | D172: 4374 | E172: 5674 | F172: 10048 | G172: 53.7
A173: SA | B173: Accommodation | C173: Inadequate or inappropriate dwelling conditions | D173: 1561 | E173: 1895 | F173: 3456 | G173: 18.5
A174: SA | B174: Accommodation | C174: Previous accommodation ended | D174: 873 | E174: 1184 | F174: 2057 | G174: 11
A175: SA | B175: Interpersonal relationships | C175: Interpersonal relationships | D175: 1794 | E175: 5219 | F175: 7013 | G175: 37.5
A176: SA | B176: Interpersonal relationships | C176: Time out from family/other situation | D176: 176 | E176: 307 | F176: 483 | G176: 2.6
... A195: SA | B195: Other | C195: Other | D195: 209 | E195: 287 | F195: 496 | G195: 2.7
A196: SA | B196: Not stated | C196: Not stated | D196: 162 | E196: 1 | F196: 1 | G196: . .
A197: Tas | B197: Financial | C197: Financial | D197: 1674 | E197: 2145 | F197: 3819 | G197: 57.6
A198: Tas | B198: Financial | C198: Financial difficulties | D198: 1023 | E198: 1344 | F198: 2367 | G198: 35.7
A199: Tas | B199: Financial | C199: Housing affordability stress | D199: 1414 | E199: 1908 | F199: 3322 | G199: 50.1
A200: Tas | B200: Financial | C200: Employment difficulties | D200: 117 | E200: 129 | F200: 246 | G200: 3.7
A201: Tas | B201: Financial | C201: Unemployment | D201: 328 | E201: 303 | F201: 631 | G201: 9.5
A202: Tas | B202: Financial | C202: Problematic gambling | D202: n.p. | E202: n.p. | F202: 13 | G202: 0.2
A203: Tas | B203: Accommodation | C203: Accommodation | D203: 2247 | E203: 2798 | F203: 5045 | G203: 76.1
A204: Tas | B204: Accommodation | C204: Housing crisis | D204: 1320 | E204: 1851 | F204: 3171 | G204: 47.8
A205: Tas | B205: Accommodation | C205: Inadequate or inappropriate dwelling conditions | D205: 1338 | E205: 1586 | F205: 2924 | G205: 44.1
A206: Tas | B206: Accommodation | C206: Previous accommodation ended | D206: 1008 | E206: 1203 | F206: 2211 | G206: 33.4
A207: Tas | B207: Interpersonal relationships | C207: Interpersonal relationships | D207: 1213 | E207: 2064 | F207: 3277 | G207: 49.4
A208: Tas | B208: Interpersonal relationships | C208: Time out from family/other situation | D208: 464 | E208: 607 | F208: 1071 | G208: 16.2
A209: Tas | B209: Interpersonal relationships | C209: Relationship/family breakdown | D209: 818 | E209: 1208 | F209: 2026 | G209: 30.6
...

Sheet CLIENTS.22
A1: Table of contents
A2: Table CLIENTS.22: Clients, by main reasons for seeking assistance, and by state and territory, 2023–24
A4: State/ territory | B4: Group | C4: Main reason for seeking assistance | D4: Males | E4: Females | F4: Total clients (number) | G4: Total clients (per cent)
A5: National | B5: Financial | C5: Financial | D5: 23629 | E5: 31409 | F5: 55038 | G5: 19.8
A6: National | B6: Financial | C6: Financial difficulties | D6: 12306 | E6: 16720 | F6: 29026 | G6: 10.5
A7: National | B7: Financial | C7: Housing affordability stress | D7: 10625 | E7: 14168 | F7: 24793 | G7: 8.9
A8: National | B8: Financial | C8: Employment difficulties | D8: 268 | E8: 225 | F8: 493 | G8: 0.2
A9: National | B9: Financial | C9: Unemployment | D9: 406 | E9: 283 | F9: 689 | G9: 0.2
A10: National | B10: Financial | C10: Problematic gambling | D10: 24 | E10: 13 | F10: 37 | G10: 0
A11: National | B11: Accommodation | C11: Accommodation | D11: 44399 | E11: 52184 | F11: 96583 | G11: 34.8
A12: National | B12: Accommodation | C12: Housing crisis | D12: 23130 | E12: 28984 | F12: 52114 | G12: 18.8
A13: National | B13: Accommodation | C13: Inadequate or inappropriate dwelling conditions | D13: 15704 | E13: 16986 | F13: 32690 | G13: 11.8
A14: National | B14: Accommodation | C14: Previous accommodation ended | D14: 5565 | E14: 6214 | F14: 11779 | G14: 4.2
A15: National | B15: Interpersonal relationships | C15: Interpersonal relationships | D15: 23064 | E15: 64824 | F15: 87888 | G15: 31.6
A16: National | B16: Interpersonal relationships | C16: Time out from family/other situation | D16: 1321 | E16: 2153 | F16: 3474 | G16: 1.3
... A35: National | B35: Other | C35: Other | D35: 6461 | E35: 7600 | F35: 14061 | G35: 5.1
A36: National | B36: Not stated | C36: Not stated | D36: 1115 | E36: 1270 | F36: 2385 | G36: . .
A37: NSW | B37: Financial | C37: Financial | D37: 5893 | E37: 7537 | F37: 13430 | G37: 20
A38: NSW | B38: Financial | C38: Financial difficulties | D38: 2866 | E38: 3731 | F38: 6597 | G38: 9.8
A39: NSW | B39: Financial | C39: Housing affordability stress | D39: 2828 | E39: 3670 | F39: 6498 | G39: 9.7
A40: NSW | B40: Financial | C40: Employment difficulties | D40: 68 | E40: 60 | F40: 128 | G40: 0.2
A41: NSW | B41: Financial | C41: Unemployment | D41: 121 | E41: 69 | F41: 190 | G41: 0.3
A42: NSW | B42: Financial | C42: Problematic gambling | D42: 10 | E42: 7 | F42: 17 | G42: 0
A43: NSW | B43: Accommodation | C43: Accommodation | D43: 10130 | E43: 12873 | F43: 23003 | G43: 34.3
A44: NSW | B44: Accommodation | C44: Housing crisis | D44: 6344 | E44: 8336 | F44: 14680 | G44: 21.9
A45: NSW | B45: Accommodation | C45: Inadequate or inappropriate dwelling conditions | D45: 2582 | E45: 3180 | F45: 5762 | G45: 8.6
A46: NSW | B46: Accommodation | C46: Previous accommodation ended | D46: 1204 | E46: 1357 | F46: 2561 | G46: 3.8
A47: NSW | B47: Interpersonal relationships | C47: Interpersonal relationships | D47: 5965 | E47: 14907 | F47: 20872 | G47: 31.1
A48: NSW | B48: Interpersonal relationships | C48: Time out from family/other situation | D48: 292 | E48: 467 | F48: 759 | G48: 1.1
... A67: NSW | B67: Other | C67: Other | D67: 1451 | E67: 1674 | F67: 3125 | G67: 4.7
A68: NSW | B68: Not stated | C68: Not stated | D68: 384 | E68: 474 | F68: 858 | G68: . .
A69: Vic | B69: Financial | C69: Financial | D69: 8987 | E69: 12501 | F69: 21488 | G69: 21.2
A70: Vic | B70: Financial | C70: Financial difficulties | D70: 4969 | E70: 7122 | F70: 12091 | G70: 11.9
A71: Vic | B71: Financial | C71: Housing affordability stress | D71: 3704 | E71: 5100 | F71: 8804 | G71: 8.7
A72: Vic | B72: Financial | C72: Employment difficulties | D72: 145 | E72: 131 | F72: 276 | G72: 0.3
A73: Vic | B73: Financial | C73: Unemployment | D73: 162 | E73: 145 | F73: 307 | G73: 0.3
A74: Vic | B74: Financial | C74: Problematic gambling | D74: 7 | E74: 3 | F74: 10 | G74: 0
A75: Vic | B75: Accommodation | C75: Accommodation | D75: 15107 | E75: 16167 | F75: 31274 | G75: 30.9
A76: Vic | B76: Accommodation | C76: Housing crisis | D76: 7415 | E76: 8578 | F76: 15993 | G76: 15.8
A77: Vic | B77: Accommodation | C77: Inadequate or inappropriate dwelling conditions | D77: 5634 | E77: 5630 | F77: 11264 | G77: 11.1
A78: Vic | B78: Accommodation | C78: Previous accommodation ended | D78: 2058 | E78: 1959 | F78: 4017 | G78: 4
A79: Vic | B79: Interpersonal relationships | C79: Interpersonal relationships | D79: 9502 | E79: 25481 | F79: 34983 | G79: 34.6
A80: Vic | B80: Interpersonal relationships | C80: Time out from family/other situation | D80: 346 | E80: 422 | F80: 768 | G80: 0.8
... A99: Vic | B99: Other | C99: Other | D99: 2000 | E99: 2153 | F99: 4153 | G99: 4.1
A100: Vic | B100: Not stated | C100: Not stated | D100: 400 | E100: 356 | F100: 756 | G100: . .
A101: Qld | B101: Financial | C101: Financial | D101: 5506 | E101: 7194 | F101: 12700 | G101: 26.3
A102: Qld | B102: Financial | C102: Financial difficulties | D102: 2896 | E102: 3857 | F102: 6753 | G102: 14
A103: Qld | B103: Financial | C103: Housing affordability stress | D103: 2526 | E103: 3273 | F103: 5799 | G103: 12
A104: Qld | B104: Financial | C104: Employment difficulties | D104: 29 | E104: 23 | F104: 52 | G104: 0.1
A105: Qld | B105: Financial | C105: Unemployment | D105: 54 | E105: 40 | F105: 94 | G105: 0.2
A106: Qld | B106: Financial | C106: Problematic gambling | D106: 1 | E106: 1 | F106: 2 | G106: 0
A107: Qld | B107: Accommodation | C107: Accommodation | D107: 8748 | E107: 10659 | F107: 19407 | G107: 40.2
A108: Qld | B108: Accommodation | C108: Housing crisis | D108: 4292 | E108: 5630 | F108: 9922 | G108: 20.5
A109: Qld | B109: Accommodation | C109: Inadequate or inappropriate dwelling conditions | D109: 3367 | E109: 3668 | F109: 7035 | G109: 14.6
A110: Qld | B110: Accommodation | C110: Previous accommodation ended | D110: 1089 | E110: 1361 | F110: 2450 | G110: 5.1
A111: Qld | B111: Interpersonal relationships | C111: Interpersonal relationships | D111: 2783 | E111: 7713 | F111: 10496 | G111: 21.7
A112: Qld | B112: Interpersonal relationships | C112: Time out from family/other situation | D112: 192 | E112: 305 | F112: 497 | G112: 1
... A131: Qld | B131: Other | C131: Other | D131: 1295 | E131: 1495 | F131: 2790 | G131: 5.8
A132: Qld | B132: Not stated | C132: Not stated | D132: 191 | E132: 295 | F132: 486 | G132: . .
A133: WA | B133: Financial | C133: Financial | D133: 1833 | E133: 2350 | F133: 4183 | G133: 16.8
A134: WA | B134: Financial | C134: Financial difficulties | D134: 1344 | E134: 1654 | F134: 2998 | G134: 12.1
A135: WA | B135: Financial | C135: Housing affordability stress | D135: 450 | E135: 681 | F135: 1131 | G135: 4.6
A136: WA | B136: Financial | C136: Employment difficulties | D136: 9 | E136: 3 | F136: 12 | G136: 0
A137: WA | B137: Financial | C137: Unemployment | D137: 27 | E137: 12 | F137: 39 | G137: 0.2
A138: WA | B138: Financial | C138: Problematic gambling | D138: 3 | E138: — | F138: 3 | G138: 0
A139: WA | B139: Accommodation | C139: Accommodation | D139: 1991 | E139: 2818 | F139: 4809 | G139: 19.4
A140: WA | B140: Accommodation | C140: Housing crisis | D140: 512 | E140: 900 | F140: 1412 | G140: 5.7
A141: WA | B141: Accommodation | C141: Inadequate or inappropriate dwelling conditions | D141: 1194 | E141: 1427 | F141: 2621 | G141: 10.6
A142: WA | B142: Accommodation | C142: Previous accommodation ended | D142: 285 | E142: 491 | F142: 776 | G142: 3.1
A143: WA | B143: Interpersonal relationships | C143: Interpersonal relationships | D143: 2304 | E143: 8124 | F143: 10428 | G143: 42
A144: WA | B144: Interpersonal relationships | C144: Time out from family/other situation | D144: 248 | E144: 505 | F144: 753 | G144: 3
A145: WA | B145: Interpersonal relationships | C145: Relationship/family breakdown | D145: 237 | E145: 554 | F145: 791 | G145: 3.2
A146: WA | B146: Interpersonal relationships | C146: Sexual abuse | D146: 3 | E146: 34 | F146: 37 | G146: 0.1
A147: WA | B147: Interpersonal relationships | C147: Family and domestic violence | D147: 1795 | E147: 6960 | F147: 8755 | G147: 35.2
A148: WA | B148: Interpersonal relationships | C148: Non-family violence | D148: 21 | E148: 71 | F148: 92 | G148: 0.4
A149: WA | B149: Health | C149: Health | D149: 471 | E149: 676 | F149: 1147 | G149: 4.6
A150: WA | B150: Health | C150: Mental health issues | D150: 92 | E150: 139 | F150: 231 | G150: 0.9
... A157: WA | B157: Other | C157: Transition from other care arrangements | D157: 36 | E157: 38 | F157: 74 | G157: 0.3
A158: WA | B158: Other | C158: Discrimination including racial discrimination | D158: 1 | E158: — | F158: 1 | G158: 0
A159: WA | B159: Other | C159: Itinerant | D159: 438 | E159: 366 | F159: 804 | G159: 3.2
A160: WA | B160: Other | C160: Unable to return home due to environmental reasons | D160: 8 | E160: 29 | F160: 37 | G160: 0.1
A161: WA | B161: Other | C161: Disengagement with school or other education and training | D161: 10 | E161: 19 | F161: 29 | G161: 0.1
A162: WA | B162: Other | C162: Lack of family and/or community support | D162: 80 | E162: 227 | F162: 307 | G162: 1.2
A163: WA | B163: Other | C163: Other | D163: 1203 | E163: 1694 | F163: 2897 | G163: 11.7
A164: WA | B164: Not stated | C164: Not stated | D164: 71 | E164: 81 | F164: 152 | G164: . .
A165: SA | B165: Financial | C165: Financial | D165: 646 | E165: 786 | F165: 1432 | G165: 7.7
A166: SA | B166: Financial | C166: Financial difficulties | D166: 75 | E166: 76 | F166: 151 | G166: 0.8
A167: SA | B167: Financial | C167: Housing affordability stress | D167: 559 | E167: 705 | F167: 1264 | G167: 6.8
A168: SA | B168: Financial | C168: Employment difficulties | D168: 3 | E168: 1 | F168: 4 | G168: 0
A169: SA | B169: Financial | C169: Unemployment | D169: 9 | E169: 3 | F169: 12 | G169: 0.1
A170: SA | B170: Financial | C170: Problematic gambling | D170: — | E170: 1 | F170: 1 | G170: 0
A171: SA | B171: Accommodation | C171: Accommodation | D171: 5185 | E171: 6140 | F171: 11325 | G171: 60.5
A172: SA | B172: Accommodation | C172: Housing crisis | D172: 3612 | E172: 4271 | F172: 7883 | G172: 42.1
A173: SA | B173: Accommodation | C173: Inadequate or inappropriate dwelling conditions | D173: 1033 | E173: 1178 | F173: 2211 | G173: 11.8
A174: SA | B174: Accommodation | C174: Previous accommodation ended | D174: 540 | E174: 691 | F174: 1231 | G174: 6.6
A175: SA | B175: Interpersonal relationships | C175: Interpersonal relationships | D175: 910 | E175: 3555 | F175: 4465 | G175: 23.9
A176: SA | B176: Interpersonal relationships | C176: Time out from family/other situation | D176: 29 | E176: 32 | F176: 61 | G176: 0.3
A177: SA | B177: Interpersonal relationships | C177: Relationship/family breakdown | D177: 201 | E177: 354 | F177: 555 | G177: 3
A178: SA | B178: Interpersonal relationships | C178: Sexual abuse | D178: 3 | E178: 61 | F178: 64 | G178: 0.3
A179: SA | B179: Interpersonal relationships | C179: Family and domestic violence | D179: 672 | E179: 3094 | F179: 3766 | G179: 20.1
...

Sheet CLIENTS.23
A1: Table of contents
A2: Table CLIENTS.23: Clients, by homeless status at first presentation and main reasons for seeking assistance, 2023–24
A4: Homeless/ At risk | B4: Group | C4: Main reason for seeking assistance | D4: Males | E4: Females | F4: Total clients (number) | G4: Total clients (per cent)
A5: Homeless | B5: Financial | C5: Financial | D5: 10480 | E5: 9853 | F5: 20333 | G5: 16.3
A6: Homeless | B6: Financial | C6: Financial difficulties | D6: 4257 | E6: 3473 | F6: 7730 | G6: 6.2
A7: Homeless | B7: Financial | C7: Housing affordability stress | D7: 5896 | E7: 6241 | F7: 12137 | G7: 9.7
A8: Homeless | B8: Financial | C8: Employment difficulties | D8: 81 | E8: 41 | F8: 122 | G8: 0.1
A9: Homeless | B9: Financial | C9: Unemployment | D9: 232 | E9: 93 | F9: 325 | G9: 0.3
A10: Homeless | B10: Financial | C10: Problematic gambling | D10: 14 | E10: 5 | F10: 19 | G10: 0
A11: Homeless | B11: Accommodation | C11: Accommodation | D11: 29647 | E11: 29826 | F11: 59473 | G11: 47.7
A12: Homeless | B12: Accommodation | C12: Housing crisis | D12: 13692 | E12: 14514 | F12: 28206 | G12: 22.6
A13: Homeless | B13: Accommodation | C13: Inadequate or inappropriate dwelling conditions | D13: 12037 | E13: 11269 | F13: 23306 | G13: 18.7
A14: Homeless | B14: Accommodation | C14: Previous accommodation ended | D14: 3918 | E14: 4043 | F14: 7961 | G14: 6.4
A15: Homeless | B15: Interpersonal relationships | C15: Interpersonal relationships | D15: 9818 | E15: 20750 | F15: 30568 | G15: 24.5
A16: Homeless | B16: Interpersonal relationships | C16: Time out from family/other situation | D16: 727 | E16: 952 | F16: 1679 | G16: 1.3
... A35: Homeless | B35: Other | C35: Other | D35: 2209 | E35: 2028 | F35: 4237 | G35: 3.4
A36: Homeless | B36: Not stated | C36: Not stated | D36: 318 | E36: 304 | F36: 622 | G36: . .
A37: At risk | B37: Financial | C37: Financial | D37: 12185 | E37: 20357 | F37: 32542 | G37: 23.6
A38: At risk | B38: Financial | C38: Financial difficulties | D38: 7289 | E38: 12280 | F38: 19569 | G38: 14.2
A39: At risk | B39: Financial | C39: Housing affordability stress | D39: 4543 | E39: 7709 | F39: 12252 | G39: 8.9
A40: At risk | B40: Financial | C40: Employment difficulties | D40: 178 | E40: 181 | F40: 359 | G40: 0.3
A41: At risk | B41: Financial | C41: Unemployment | D41: 165 | E41: 179 | F41: 344 | G41: 0.2
A42: At risk | B42: Financial | C42: Problematic gambling | D42: 10 | E42: 8 | F42: 18 | G42: 0
A43: At risk | B43: Accommodation | C43: Accommodation | D43: 13926 | E43: 21415 | F43: 35341 | G43: 25.7
A44: At risk | B44: Accommodation | C44: Housing crisis | D44: 8949 | E44: 13909 | F44: 22858 | G44: 16.6
A45: At risk | B45: Accommodation | C45: Inadequate or inappropriate dwelling conditions | D45: 3414 | E45: 5437 | F45: 8851 | G45: 6.4
A46: At risk | B46: Accommodation | C46: Previous accommodation ended | D46: 1563 | E46: 2069 | F46: 3632 | G46: 2.6
A47: At risk | B47: Interpersonal relationships | C47: Interpersonal relationships | D47: 11423 | E47: 36774 | F47: 48197 | G47: 35
A48: At risk | B48: Interpersonal relationships | C48: Time out from family/other situation | D48: 567 | E48: 1146 | F48: 1713 | G48: 1.2
... A67: At risk | B67: Other | C67: Other | D67: 3383 | E67: 4841 | F67: 8224 | G67: 6
A68: At risk | B68: Not stated | C68: Not stated | D68: 240 | E68: 262 | F68: 502 | G68: . .
A69: Not stated | B69: Financial | C69: Financial | D69: 964 | E69: 1199 | F69: 2163 | G69: . .
A70: Not stated | B70: Financial | C70: Financial difficulties | D70: 760 | E70: 967 | F70: 1727 | G70: . .
A71: Not stated | B71: Financial | C71: Housing affordability stress | D71: 186 | E71: 218 | F71: 404 | G71: . .
A72: Not stated | B72: Financial | C72: Employment difficulties | D72: 9 | E72: 3 | F72: 12 | G72: . .
A73: Not stated | B73: Financial | C73: Unemployment | D73: 9 | E73: 11 | F73: 20 | G73: . .
A74: Not stated | B74: Accommodation | C74: Accommodation | D74: 826 | E74: 943 | F74: 1769 | G74: . .
A75: Not stated | B75: Accommodation | C75: Housing crisis | D75: 489 | E75: 561 | F75: 1050 | G75: . .
A76: Not stated | B76: Accommodation | C76: Inadequate or inappropriate dwelling conditions | D76: 253 | E76: 280 | F76: 533 | G76: . .
A77: Not stated | B77: Accommodation | C77: Previous accommodation ended | D77: 84 | E77: 102 | F77: 186 | G77: . .
A78: Not stated | B78: Interpersonal relationships | C78: Interpersonal relationships | D78: 1823 | E78: 7300 | F78: 9123 | G78: . .
A79: Not stated | B79: Interpersonal relationships | C79: Time out from family/other situation | D79: 27 | E79: 55 | F79: 82 | G79: . .
... A98: Not stated | B98: Not stated | C98: Not stated | D98: 557 | E98: 704 | F98: 1261 | G98: . .
A100: Notes
A101: 1. The client's homelessness status and main reason for seeking assistance at the beginning of support.
A102: 2. Where more than one reason for seeking assistance has been provided, the client chooses the main reason.
A103: 3. Percentages have been calculated using total number of homeless or at risk clients as the denominator (less not stated): Homeless: 124,659 At risk: 137,643.
A104: — nil or rounded to zero
A105: . . not applicable

Sheet CLIENTS.24
A1: Table of contents
A2: Table CLIENTS.24: Clients, by need for services and assistance and service provision status, and by state and territory, 2023–24
A4: State/ territory | B4: Group | C4: Service and assistance type | D4: Need identified | E4: Need identified as % of clients | F4: Provided | G4: Provided as % of need identified | H4: Referred only | I4: Referred only as % of need identified | J4: Not provided or referred | K4: Not provided or referred as % of need identified
A5: National | B5: Accommodation provision | C5: Accommodation provision | D5: 162535 | E5: 58 | F5: 82073 | G5: 50.5 | H5: 27170 | I5: 16.7 | J5: 53292 | K5: 32.8
A6: National | B6: Accommodation provision | C6: Short-term or emergency accommodation | D6: 109480 | E6: 39.1 | F6: 63119 | G6: 57.7 | H6: 12001 | I6: 11 | J6: 34360 | K6: 31.4
A7: National | B7: Accommodation provision | C7: Medium-term/transitional housing | D7: 82387 | E7: 29.4 | F7: 19937 | G7: 24.2 | H7: 14705 | I7: 17.8 | J7: 47745 | K7: 58
A8: National | B8: Accommodation provision | C8: Long-term housing | D8: 109557 | E8: 39.1 | F8: 4937 | G8: 4.5 | H8: 27932 | I8: 25.5 | J8: 76688 | K8: 70
A9: National | B9: Assistance to sustain housing tenure | C9: Assistance to sustain housing tenure | D9: 85228 | E9: 30.4 | F9: 71558 | G9: 84 | H9: 2766 | I9: 3.2 | J9: 10904 | K9: 12.8
A10: National | B10: Assistance to sustain housing tenure | C10: Assistance to sustain tenancy or prevent tenancy failure or eviction | D10: 84499 | E10: 30.2 | F10: 70935 | G10: 83.9 | H10: 2729 | I10: 3.2 | J10: 10835 | K10: 12.8
A11: National | B11: Assistance to sustain housing tenure | C11: Assistance to prevent foreclosures or for mortgage arrears | D11: 2688 | E11: 1 | F11: 1758 | G11: 65.4 | H11: 142 | I11: 5.3 | J11: 788 | K11: 29.3
A12: National | B12: Mental health | C12: Mental health | D12: 25040 | E12: 8.9 | F12: 11881 | G12: 47.4 | H12: 5018 | I12: 20 | J12: 8141 | K12: 32.5
A13: National | B13: Mental health | C13: Psychological services | D13: 7778 | E13: 2.8 | F13: 2593 | G13: 33.3 | H13: 1814 | I13: 23.3 | J13: 3371 | K13: 43.3
A14: National | B14: Mental health | C14: Psychiatric services | D14: 4873 | E14: 1.7 | F14: 1550 | G14: 31.8 | H14: 970 | I14: 19.9 | J14: 2353 | K14: 48.3
A15: National | B15: Mental health | C15: Mental health services | D15: 22729 | E15: 8.1 | F15: 10757 | G15: 47.3 | H15: 4361 | I15: 19.2 | J15: 7611 | K15: 33.5
A16: National | B16: Family | C16: Family | D16: 16788 | E16: 6 | F16: 10560 | G16: 62.9 | H16: 3252 | I16: 19.4 | J16: 2976 | K16: 17.7
... A281: WA | B281: Legal/financial services | C281: Financial advice and counselling | D281: 1253 | E281: 5 | F281: 521 | G281: 41.6 | H281: 451 | I281: 36 | J281: 281 | K281: 22.4
A282: WA | B282: Legal/financial services | C282: Counselling for problem gambling | D282: 67 | E282: 0.3 | F282: 33 | G282: n.p. | H282: 13 | I282: n.p. | J282: 21 | K282: n.p.
A283: WA | B283: Immigration/cultural services | C283: Immigration/cultural services | D283: 5199 | E283: 20.8 | F283: 4536 | G283: 87.2 | H283: 564 | I283: 10.8 | J283: 99 | K283: 1.9
A284: WA | B284: Immigration/cultural services | C284: Interpreter services | D284: 308 | E284: 1.2 | F284: 273 | G284: 88.6 | H284: 27 | I284: 8.8 | J284: 8 | K284: 2.6
A285: WA | B285: Immigration/cultural services | C285: Assistance with immigration services | D285: 216 | E285: 0.9 | F285: 155 | G285: 71.8 | H285: 27 | I285: 12.5 | J285: 34 | K285: 15.7
A286: WA | B286: Immigration/cultural services | C286: Culturally specific services | D286: 3356 | E286: 13.4 | F286: 2690 | G286: 80.2 | H286: 585 | I286: 17.4 | J286: 81 | K286: 2.4
A287: WA | B287: Immigration/cultural services | C287: Assistance to connect culturally | D287: 3852 | E287: 15.4 | F287: 3209 | G287: 83.3 | H287: 583 | I287: 15.1 | J287: 60 | K287: 1.6
A288: WA | B288: Other specialist services | C288: Other specialist services | D288: 5611 | E288: 22.5 | F288: 4149 | G288: 73.9 | H288: 887 | I288: 15.8 | J288: 575 | K288: 10.2
A289: WA | B289: Other specialist services | C289: Health/medical services | D289: 2812 | E289: 11.3 | F289: 1823 | G289: 64.8 | H289: 491 | I289: 17.5 | J289: 498 | K289: 17.7
A290: WA | B290: Other specialist services | C290: Specialist counselling services | D290: 1876 | E290: 7.5 | F290: 1151 | G290: 61.4 | H290: 465 | I290: 24.8 | J290: 260 | K290: 13.9
A291: WA | B291: Other specialist services | C291: Other specialised service | D291: 3374 | E291: 13.5 | F291: 2673 | G291: 79.2 | H291: 486 | I291: 14.4 | J291: 215 | K291: 6.4
A292: WA | B292: General services | C292: General services | D292: 24398 | E292: 97.6 | F292: 24252 | G292: 99.4 | H292: 80 | I292: 0.3 | J292: 66 | K292: 0.3
A293: WA | B293: General services | C293: Assertive outreach for rough sleepers | D293: 1955 | E293: 7.8 | F293: 1483 | G293: 75.9 | H293: 367 | I293: 18.8 | J293: 105 | K293: 5.4
A294: WA | B294: General services | C294: Assistance to obtain/maintain government allowance | D294: 2043 | E294: 8.2 | F294: 1750 | G294: 85.7 | H294: 133 | I294: 6.5 | J294: 160 | K294: 7.8
... A325: SA | B325: Assistance to sustain housing tenure | C325: Assistance to sustain tenancy or prevent tenancy failure or eviction | D325: 4506 | E325: 24.1 | F325: 4430 | G325: 98.3 | H325: 11 | I325: 0.2 | J325: 65 | K325: 1.4
A326: SA | B326: Assistance to sustain housing tenure | C326: Assistance to prevent foreclosures or for mortgage arrears | D326: 52 | E326: 0.3 | F326: 46 | G326: n.p. | H326: — | I326: n.p. | J326: 6 | K326: n.p.
A327: SA | B327: Mental health | C327: Mental health | D327: 738 | E327: 3.9 | F327: 35 | G327: 4.7 | H327: 601 | I327: 81.4 | J327: 102 | K327: 13.8
A328: SA | B328: Mental health | C328: Psychological services | D328: 119 | E328: 0.6 | F328: 3 | G328: 2.5 | H328: 87 | I328: 73.1 | J328: 29 | K328: 24.4
A329: SA | B329: Mental health | C329: Psychiatric services | D329: 37 | E329: 0.2 | F329: 6 | G329: n.p. | H329: 14 | I329: n.p. | J329: 17 | K329: n.p.
A330: SA | B330: Mental health | C330: Mental health services | D330: 649 | E330: 3.5 | F330: 31 | G330: 4.8 | H330: 530 | I330: 81.7 | J330: 88 | K330: 13.6
A331: SA | B331: Family | C331: Family | D331: 1424 | E331: 7.6 | F331: 625 | G331: 43.9 | H331: 665 | I331: 46.7 | J331: 134 | K331: 9.4
A332: SA | B332: Family | C332: Child protection services | D332: 489 | E332: 2.6 | F332: 16 | G332: 3.3 | H332: 390 | I332: 79.8 | J332: 83 | K332: 17
A333: SA | B333: Family | C333: Parenting skills education | D333: 429 | E333: 2.3 | F333: 338 | G333: 78.8 | H333: 61 | I333: 14.2 | J333: 30 | K333: 7
A334: SA | B334: Family | C334: Child specific specialist counselling services | D334: 420 | E334: 2.2 | F334: 94 | G334: 22.4 | H334: 285 | I334: 67.9 | J334: 41 | K334: 9.8
A335: SA | B335: Family | C335: Pregnancy assistance | D335: 150 | E335: 0.8 | F335: 130 | G335: 86.7 | H335: 12 | I335: 8 | J335: 8 | K335: 5.3
A336: SA | B336: Family | C336: Family planning support | D336: 189 | E336: 1 | F336: 147 | G336: 77.8 | H336: 30 | I336: 15.9 | J336: 12 | K336: 6.3
A337: SA | B337: Disability | C337: Disability | D337: 107 | E337: 0.6 | F337: 4 | G337: 3.7 | H337: 90 | I337: 84.1 | J337: 13 | K337: 12.1
A338: SA | B338: Disability | C338: Physical disability services | D338: 36 | E338: 0.2 | F338: 2 | G338: n.p. | H338: 25 | I338: n.p. | J338: 9 | K338: n.p.
A339: SA | B339: Disability | C339: Intellectual disability services | D339: 74 | E339: 0.4 | F339: 2 | G339: n.p. | H339: 67 | I339: n.p. | J339: 5 | K339: n.p.
A340: SA | B340: Drug/alcohol | C340: Drug/alcohol | D340: 333 | E340: 1.8 | F340: 13 | G340: 3.9 | H340: 268 | I340: 80.5 | J340: 52 | K340: 15.6
A341: SA | B341: Drug/alcohol | C341: Drug/alcohol counselling | D341: 333 | E341: 1.8 | F341: 13 | G341: 3.9 | H341: 268 | I341: 80.5 | J341: 52 | K341: 15.6
A342: SA | B342: Legal/financial services | C342: Legal/financial services | D342: 1716 | E342: 9.2 | F342: 215 | G342: 12.5 | H342: 1183 | I342: 68.9 | J342: 318 | K342: 18.5
A343: SA | B343: Legal/financial services | C343: Professional legal services | D343: 301 | E343: 1.6 | F343: 7 | G343: 2.3 | H343: 279 | I343: 92.7 | J343: 15 | K343: 5
A344: SA | B344: Legal/financial services | C344: Financial advice and counselling | D344: 1532 | E344: 8.2 | F344: 211 | G344: 13.8 | H344: 1004 | I344: 65.5 | J344: 317 | K344: 20.7
A345: SA | B345: Legal/financial services | C345: Counselling for problem gambling | D345: 10 | E345: 0.1 | F345: — | G345: n.p. | H345: 7 | I345: n.p. | J345: 3 | K345: n.p.
A346: SA | B346: Immigration/cultural services | C346: Immigration/cultural services | D346: 991 | E346: 5.3 | F346: 834 | G346: 84.2 | H346: 86 | I346: 8.7 | J346: 71 | K346: 7.2
A347: SA | B347: Immigration/cultural services | C347: Interpreter services | D347: 98 | E347: 0.5 | F347: 92 | G347: n.p. | H347: 5 | I347: n.p. | J347: 1 | K347: n.p.
A348: SA | B348: Immigration/cultural services | C348: Assistance with immigration services | D348: 18 | E348: 0.1 | F348: — | G348: n.p. | H348: 14 | I348: n.p. | J348: 4 | K348: n.p.
A349: SA | B349: Immigration/cultural services | C349: Culturally specific services | D349: 650 | E349: 3.5 | F349: 540 | G349: 83.1 | H349: 71 | I349: 10.9 | J349: 39 | K349: 6
A350: SA | B350: Immigration/cultural services | C350: Assistance to connect culturally | D350: 443 | E350: 2.4 | F350: 384 | G350: 86.7 | H350: 19 | I350: 4.3 | J350: 40 | K350: 9
A351: SA | B351: Other specialist services | C351: Other specialist services | D351: 4461 | E351: 23.8 | F351: 1660 | G351: 37.2 | H351: 2728 | I351: 61.2 | J351: 73 | K351: 1.6
A352: SA | B352: Other specialist services | C352: Health/medical services | D352: 1044 | E352: 5.6 | F352: 40 | G352: 3.8 | H352: 931 | I352: 89.2 | J352: 73 | K352: 7
A353: SA | B353: Other specialist services | C353: Specialist counselling services | D353: 1657 | E353: 8.9 | F353: 1465 | G353: 88.4 | H353: 145 | I353: 8.8 | J353: 47 | K353: 2.8
A354: SA | B354: Other specialist services | C354: Other specialised service | D354: 2906 | E354: 15.5 | F354: 191 | G354: 6.6 | H354: 2689 | I354: 92.5 | J354: 26 | K354: 0.9
A355: SA | B355: General services | C355: General services | D355: 18660 | E355: 99.7 | F355: 18651 | G355: 100 | H355: 5 | I355: 0 | J355: 4 | K355: 0
A356: SA | B356: General services | C356: Assertive outreach for rough sleepers | D356: 314 | E356: 1.7 | F356: 306 | G356: 97.5 | H356: 2 | I356: 0.6 | J356: 6 | K356: 1.9
A357: SA | B357: General services | C357: Assistance to obtain/maintain government allowance | D357: 1173 | E357: 6.3 | F357: 1123 | G357: 95.7 | H357: 6 | I357: 0.5 | J357: 44 | K357: 3.8
A358: SA | B358: General services | C358: Employment assistance | D358: 3075 | E358: 16.4 | F358: 2589 | G358: 84.2 | H358: 246 | I358: 8 | J358: 240 | K358: 7.8
A359: SA | B359: General services | C359: Training assistance | D359: 185 | E359: 1 | F359: 157 | G359: 84.9 | H359: 11 | I359: 5.9 | J359: 17 | K359: 9.2
A360: SA | B360: General services | C360: Educational assistance | D360: 2572 | E360: 13.7 | F360: 1985 | G360: 77.2 | H360: 435 | I360: 16.9 | J360: 152 | K360: 5.9
... A374: SA | B374: General services | C374: School liaison | D374: 417 | E374: 2.2 | F374: 398 | G374: 95.4 | H374: 1 | I374: 0.2 | J374: 18 | K374: 4.3
A375: SA | B375: General services | C375: Child care | D375: 204 | E375: 1.1 | F375: 156 | G375: 76.5 | H375: — | I375: 0 | J375: 48 | K375: 23.5
A376: SA | B376: General services | C376: Structured play/skills development | D376: 405 | E376: 2.2 | F376: 386 | G376: 95.3 | H376: 2 | I376: 0.5 | J376: 17 | K376: 4.2
A377: SA | B377: General services | C377: Child contact and residence arrangements | D377: 391 | E377: 2.1 | F377: 368 | G377: 94.1 | H377: 1 | I377: 0.3 | J377: 22 | K377: 5.6
A378: SA | B378: General services | C378: Meals | D378: 1550 | E378: 8.3 | F378: 1526 | G378: 98.5 | H378: 18 | I378: 1.2 | J378: 6 | K378: 0.4
A379: SA | B379: General services | C379: Laundry/shower facilities | D379: 514 | E379: 2.7 | F379: 499 | G379: 97.1 | H379: 12 | I379: 2.3 | J379: 3 | K379: 0.6
A380: SA | B380: General services | C380: Recreation | D380: 698 | E380: 3.7 | F380: 676 | G380: 96.8 | H380: 10 | I380: 1.4 | J380: 12 | K380: 1.7
A381: SA | B381: General services | C381: Transport | D381: 2287 | E381: 12.2 | F381: 2238 | G381: 97.9 | H381: 30 | I381: 1.3 | J381: 19 | K381: 0.8
A382: SA | B382: General services | C382: Other basic assistance | D382: 18004 | E382: 96.2 | F382: 17913 | G382: 99.5 | H382: — | I382: 0 | J382: 91 | K382: 0.5
A383: Tas | B383: Accommodation provision | C383: Accommodation provision | D383: 6291 | E383: 94.3 | F383: 3596 | G383: 57.2 | H383: 2013 | I383: 32 | J383: 682 | K383: 10.8
A384: Tas | B384: Accommodation provision | C384: Short-term or emergency accommodation | D384: 4451 | E384: 66.7 | F384: 2500 | G384: 56.2 | H384: 817 | I384: 18.4 | J384: 1134 | K384: 25.5
A385: Tas | B385: Accommodation provision | C385: Medium-term/transitional housing | D385: 4039 | E385: 60.5 | F385: 793 | G385: 19.6 | H385: 1543 | I385: 38.2 | J385: 1703 | K385: 42.2
A386: Tas | B386: Accommodation provision | C386: Long-term housing | D386: 5071 | E386: 76 | F386: 585 | G386: 11.5 | H386: 3031 | I386: 59.8 | J386: 1455 | K386: 28.7
A387: Tas | B387: Assistance to sustain housing tenure | C387: Assistance to sustain housing tenure | D387: 1001 | E387: 15 | F387: 721 | G387: 72 | H387: 83 | I387: 8.3 | J387: 197 | K387: 19.7
A388: Tas | B388: Assistance to sustain housing tenure | C388: Assistance to sustain tenancy or prevent tenancy failure or eviction | D388: 975 | E388: 14.6 | F388: 694 | G388: 71.2 | H388: 84 | I388: 8.6 | J388: 197 | K388: 20.2
A389: Tas | B389: Assistance to sustain housing tenure | C389: Assistance to prevent foreclosures or for mortgage arrears | D389: 44 | E389: 0.7 | F389: 36 | G389: n.p. | H389: — | I389: n.p. | J389: 8 | K389: n.p.
A390: Tas | B390: Mental health | C390: Mental health | D390: 843 | E390: 12.6 | F390: 351 | G390: 41.6 | H390: 137 | I390: 16.3 | J390: 355 | K390: 42.1
A391: Tas | B391: Mental health | C391: Psychological services | D391: 179 | E391: 2.7 | F391: 68 | G391: 38 | H391: 21 | I391: 11.7 | J391: 90 | K391: 50.3
A392: Tas | B392: Mental health | C392: Psychiatric services | D392: 160 | E392: 2.4 | F392: 52 | G392: 32.5 | H392: 17 | I392: 10.6 | J392: 91 | K392: 56.9
A393: Tas | B393: Mental health | C393: Mental health services | D393: 812 | E393: 12.2 | F393: 334 | G393: 41.1 | H393: 132 | I393: 16.3 | J393: 346 | K393: 42.6
A394: Tas | B394: Family | C394: Family | D394: 368 | E394: 5.5 | F394: 213 | G394: 57.9 | H394: 52 | I394: 14.1 | J394: 103 | K394: 28
A395: Tas | B395: Family | C395: Child protection services | D395: 257 | E395: 3.9 | F395: 178 | G395: 69.3 | H395: 33 | I395: 12.8 | J395: 46 | K395: 17.9
A396: Tas | B396: Family | C396: Parenting skills education | D396: 102 | E396: 1.5 | F396: 24 | G396: 23.5 | H396: 19 | I396: 18.6 | J396: 59 | K396: 57.8
A397: Tas | B397: Family | C397: Child specific specialist counselling services | D397: 36 | E397: 0.5 | F397: 22 | G397: n.p. | H397: 7 | I397: n.p. | J397: 7 | K397: n.p.
A398: Tas | B398: Family | C398: Pregnancy assistance | D398: 52 | E398: 0.8 | F398: 23 | G398: n.p. | H398: 7 | I398: n.p. | J398: 22 | K398: n.p.
A399: Tas | B399: Family | C399: Family planning support | D399: 47 | E399: 0.7 | F399: 20 | G399: n.p. | H399: 5 | I399: n.p. | J399: 22 | K399: n.p.
A400: Tas | B400: Disability | C400: Disability | D400: 167 | E400: 2.5 | F400: 66 | G400: 39.5 | H400: 24 | I400: 14.4 | J400: 77 | K400: 46.1
A401: Tas | B401: Disability | C401: Physical disability services | D401: 82 | E401: 1.2 | F401: 18 | G401: n.p. | H401: 13 | I401: n.p. | J401: 51 | K401: n.p.
A402: Tas | B402: Disability | C402: Intellectual disability services | D402: 100 | E402: 1.5 | F402: 52 | G402: 52 | H402: 14 | I402: 14 | J402: 34 | K402: 34
A403: Tas | B403: Drug/alcohol | C403: Drug/alcohol | D403: 384 | E403: 5.8 | F403: 200 | G403: 52.1 | H403: 41 | I403: 10.7 | J403: 143 | K403: 37.2
A404: Tas | B404: Drug/alcohol | C404: Drug/alcohol counselling | D404: 384 | E404: 5.8 | F404: 200 | G404: 52.1 | H404: 41 | I404: 10.7 | J404: 143 | K404: 37.2
A405: Tas | B405: Legal/financial services | C405: Legal/financial services | D405: 383 | E405: 5.7 | F405: 143 | G405: 37.3 | H405: 70 | I405: 18.3 | J405: 170 | K405: 44.4
A406: Tas | B406: Legal/financial services | C406: Professional legal services | D406: 133 | E406: 2 | F406: 54 | G406: 40.6 | H406: 25 | I406: 18.8 | J406: 54 | K406: 40.6
A407: Tas | B407: Legal/financial services | C407: Financial advice and counselling | D407: 274 | E407: 4.1 | F407: 97 | G407: 35.4 | H407: 49 | I407: 17.9 | J407: 128 | K407: 46.7
A408: Tas | B408: Legal/financial services | C408: Counselling for problem gambling | D408: 17 | E408: 0.3 | F408: 5 | G408: n.p. | H408: 5 | I408: n.p. | J408: 7 | K408: n.p.
...

Sheet CLIENTS.25
A1: Table of contents
A2: Table CLIENTS.25: Clients, by total nights of accommodation, and by state and territory, 2023–24
A4: State/territory | B4: Accommodation nights | C4: Males | D4: Females | E4: All clients (number) | F4: All clients (per cent)
A5: National | B5: No accommodation | C5: 78488 | D5: 119517 | E5: 198005 | F5: 70.7
A6: National | B6: Up to 5 nights | C6: 8878 | D6: 11893 | E6: 20771 | F6: 7.4
A7: National | B7: 6–45 nights | C7: 10178 | D7: 14099 | E7: 24277 | F7: 8.7
A8: National | B8: 46–90 nights | C8: 4080 | D8: 5691 | E8: 9771 | F8: 3.5
A9: National | B9: 91–180 nights | C9: 4304 | D9: 6294 | E9: 10598 | F9: 3.8
A10: National | B10: Over 180 nights | C10: 6945 | D10: 9711 | E10: 16656 | F10: 5.9
A11: National | B11: Total | C11: 112873 | D11: 167205 | E11: 280078 | F11: 100
A12: National | B12: Mean | C12: 92.4 | D12: 93.4 | E12: 93 | F12: . .
A13: National | B13: Median | C13: 31 | D13: 34 | E13: 33 | F13: . .
A14: NSW | B14: No accommodation | C14: 21342 | D14: 31530 | E14: 52872 | F14: 77.9
A15: NSW | B15: Up to 5 nights | C15: 723 | D15: 832 | E15: 1555 | F15: 2.3
A16: NSW | B16: 6–45 nights | C16: 1845 | D16: 2343 | E16: 4188 | F16: 6.2
A17: NSW | B17: 46–90 nights | C17: 1102 | D17: 1578 | E17: 2680 | F17: 3.9
A18: NSW | B18: 91–180 nights | C18: 1078 | D18: 1618 | E18: 2696 | F18: 4
A19: NSW | B19: Over 180 nights | C19: 1396 | D19: 2504 | E19: 3900 | F19: 5.7
A20: NSW | B20: Total | C20: 27486 | D20: 40405 | E20: 67891 | F20: 100
A21: NSW | B21: Mean | C21: 109.8 | D21: 125.4 | E21: 119 | F21: . .
A22: NSW | B22: Median | C22: 63 | D22: 79 | E22: 73 | F22: . .
A23: Vic | B23: No accommodation | C23: 29291 | D23: 44751 | E23: 74042 | F23: 72.6
A24: Vic | B24: Up to 5 nights | C24: 4694 | D24: 3850 | E24: 8544 | F24: 8.4
A25: Vic | B25: 6–45 nights | C25: 3947 | D25: 4704 | E25: 8651 | F25: 8.5
A26: Vic | B26: 46–90 nights | C26: 1024 | D26: 1407 | E26: 2431 | F26: 2.4
A27: Vic | B27: 91–180 nights | C27: 1141 | D27: 1681 | E27: 2822 | F27: 2.8
A28: Vic | B28: Over 180 nights | C28: 2335 | D28: 3139 | E28: 5474 | F28: 5.4
A29: Vic | B29: Total | C29: 42432 | D29: 59532 | E29: 101964 | F29: 100
A30: Vic | B30: Mean | C30: 78.9 | D30: 95.4 | E30: 87.6 | F30: . .
A31: Vic | B31: Median | C31: 14 | D31: 27 | E31: 19 | F31: . .
A32: Qld | B32: No accommodation | C32: 13788 | D32: 19954 | E32: 33742 | F32: 69.1
A33: Qld | B33: Up to 5 nights | C33: 731 | D33: 1229 | E33: 1960 | F33: 4
A34: Qld | B34: 6–45 nights | C34: 1881 | D34: 2594 | E34: 4475 | F34: 9.2
A35: Qld | B35: 46–90 nights | C35: 1023 | D35: 1345 | E35: 2368 | F35: 4.9
A36: Qld | B36: 91–180 nights | C36: 1120 | D36: 1605 | E36: 2725 | F36: 5.6
A37: Qld | B37: Over 180 nights | C37: 1460 | D37: 2088 | E37: 3548 | F37: 7.3
A38: Qld | B38: Total | C38: 20003 | D38: 28815 | E38: 48818 | F38: 100
A39: Qld | B39: Mean | C39: 110.9 | D39: 110.1 | E39: 110.4 | F39: . .
A40: Qld | B40: Median | C40: 66 | D40: 63 | E40: 65 | F40: . .
A41: WA | B41: No accommodation | C41: 4437 | D41: 9283 | E41: 13720 | F41: 54.9
A42: WA | B42: Up to 5 nights | C42: 1602 | D42: 3148 | E42: 4750 | F42: 19
A43: WA | B43: 6–45 nights | C43: 1264 | D43: 2361 | E43: 3625 | F43: 14.5
A44: WA | B44: 46–90 nights | C44: 380 | D44: 540 | E44: 920 | F44: 3.7
A45: WA | B45: 91–180 nights | C45: 337 | D45: 498 | E45: 835 | F45: 3.3
A46: WA | B46: Over 180 nights | C46: 506 | D46: 637 | E46: 1143 | F46: 4.6
A47: WA | B47: Total | C47: 8526 | D47: 16467 | E47: 24993 | F47: 100
A48: WA | B48: Mean | C48: 58.8 | D48: 46.8 | E48: 51.1 | F48: . .
A49: WA | B49: Median | C49: 10 | D49: 7 | E49: 8 | F49: . .
A50: SA | B50: No accommodation | C50: 6462 | D50: 9159 | E50: 15621 | F50: 83.5
A51: SA | B51: Up to 5 nights | C51: 536 | D51: 908 | E51: 1444 | F51: 7.7
A52: SA | B52: 6–45 nights | C52: 282 | D52: 500 | E52: 782 | F52: 4.2
A53: SA | B53: 46–90 nights | C53: 135 | D53: 243 | E53: 378 | F53: 2
A54: SA | B54: 91–180 nights | C54: 125 | D54: 196 | E54: 321 | F54: 1.7
A55: SA | B55: Over 180 nights | C55: 71 | D55: 100 | E55: 171 | F55: 0.9
A56: SA | B56: Total | C56: 7611 | D56: 11106 | E56: 18717 | F56: 100
A57: SA | B57: Mean | C57: 43.2 | D57: 39.5 | E57: 40.8 | F57: . .
A58: SA | B58: Median | C58: 10 | D58: 8 | E58: 9 | F58: . .
A59: Tas | B59: No accommodation | C59: 1241 | D59: 1869 | E59: 3110 | F59: 46.6
A60: Tas | B60: Up to 5 nights | C60: 286 | D60: 265 | E60: 551 | F60: 8.3
A61: Tas | B61: 6–45 nights | C61: 453 | D61: 478 | E61: 931 | F61: 14
A62: Tas | B62: 46–90 nights | C62: 247 | D62: 310 | E62: 557 | F62: 8.3
A63: Tas | B63: 91–180 nights | C63: 238 | D63: 345 | E63: 583 | F63: 8.7
A64: Tas | B64: Over 180 nights | C64: 510 | D64: 430 | E64: 940 | F64: 14.1
A65: Tas | B65: Total | C65: 2975 | D65: 3697 | E65: 6672 | F65: 100
A66: Tas | B66: Mean | C66: 127.5 | D66: 113.1 | E66: 120.1 | F66: . .
A67: Tas | B67: Median | C67: 67 | D67: 66 | E67: 67 | F67: . .
A68: ACT | B68: No accommodation | C68: 926 | D68: 1380 | E68: 2306 | F68: 57.6
A69: ACT | B69: Up to 5 nights | C69: 36 | D69: 23 | E69: 59 | F69: 1.5
A70: ACT | B70: 6–45 nights | C70: 233 | D70: 118 | E70: 351 | F70: 8.8
A71: ACT | B71: 46–90 nights | C71: 79 | D71: 123 | E71: 202 | F71: 5
A72: ACT | B72: 91–180 nights | C72: 122 | D72: 177 | E72: 299 | F72: 7.5
A73: ACT | B73: Over 180 nights | C73: 354 | D73: 435 | E73: 789 | F73: 19.7
A74: ACT | B74: Total | C74: 1750 | D74: 2256 | E74: 4006 | F74: 100
A75: ACT | B75: Mean | C75: 169.8 | D75: 193.6 | E75: 182.1 | F75: . .
A76: ACT | B76: Median | C76: 139 | D76: 177 | E76: 159 | F76: . .
A77: NT | B77: No accommodation | C77: 2063 | D77: 3073 | E77: 5136 | F77: 51
A78: NT | B78: Up to 5 nights | C78: 388 | D78: 1798 | E78: 2186 | F78: 21.7
A79: NT | B79: 6–45 nights | C79: 369 | D79: 1131 | E79: 1500 | F79: 14.9
A80: NT | B80: 46–90 nights | C80: 112 | D80: 164 | E80: 276 | F80: 2.7
A81: NT | B81: 91–180 nights | C81: 143 | D81: 169 | E81: 312 | F81: 3.1
A82: NT | B82: Over 180 nights | C82: 303 | D82: 367 | E82: 670 | F82: 6.6
A83: NT | B83: Total | C83: 3378 | D83: 6702 | E83: 10080 | F83: 100
A84: NT | B84: Mean | C84: 95.4 | D84: 45.9 | E84: 59 | F84: . .
A85: NT | B85: Median | C85: 22 | D85: 6 | E85: 7 | F85: . .
A87: Note: The length of accommodation for a client is calculated by adding each night of accommodation (short-term/emergency, medium-term and long-term accommodation) provided across all support periods during the reporting period.
A88: . . not applicable

Sheet CLIENTS.26
A1: Table of contents
A2: Table CLIENTS.26: Average amount of financial assistance provided to clients, by type of financial assistance, and by state and territory, 2023–24
C4: Males | D4: Males | E4: Females | F4: Females | G4: All clients | H4: All clients
A5: State/territory | B5: Type of financial assistance | C5: Number | D5: Average ($) | E5: Number | F5: Average ($) | G5: Number | H5: Average ($)
A6: National | B6: Payment for short-term or emergency accommodation | C6: 9219 | D6: 1089.2732 | E6: 13679 | F6: 2333.8204 | G6: 23060 | H6: 1827.4144
A7: National | B7: Payment for establishing/maintaining tenancy | C7: 8822 | D7: 1200.6521 | E7: 19292 | F7: 1586.4855 | G7: 28332 | H7: 1461.2709
A8: National | B8: Payment for training/education/employment | C8: 751 | D8: 394.52996 | E8: 1562 | F8: 479.27785 | G8: 2351 | H8: 451.15866
A9: National | B9: Payment for accessing external specialist services | C9: 756 | D9: 666.04365 | E9: 2973 | F9: 733.10696 | G9: 3779 | H9: 718.04234
A10: National | B10: Other payment | C10: 12397 | D10: 322.36428 | E10: 28979 | F10: 646.07226 | G10: 41773 | H10: 547.00364
A11: National | B11: Total | C11: 25128 | D11: 1012.0318 | E11: 48820 | F11: 1724.3239 | G11: 74581 | H11: 1477.1194
A12: NSW | B12: Payment for short-term or emergency accommodation | C12: 415 | D12: 304.03133 | E12: 1057 | F12: 395.96405 | G12: 1479 | H12: 370.35091
A13: NSW | B13: Payment for establishing/maintaining tenancy | C13: 1363 | D13: 711.29567 | E13: 2855 | F13: 797.11804 | G13: 4267 | H13: 767.67565
A14: NSW | B14: Payment for training/education/employment | C14: 219 | D14: 362.26484 | E14: 391 | F14: 313.1202 | G14: 624 | H14: 331.98237
A15: NSW | B15: Payment for accessing external specialist services | C15: 227 | D15: 254.70044 | E15: 789 | F15: 274.35361 | G15: 1038 | H15: 274.90366
A16: NSW | B16: Other payment | C16: 2573 | D16: 208.79984 | E16: 6155 | F16: 321.49992 | G16: 8852 | H16: 288.91279
A17: NSW | B17: Total | C17: 3887 | D17: 455.3805 | E17: 8630 | F17: 580.7686 | G17: 12669 | H17: 542.53564
... A59: NT | B59: Total | C59: 181 | D59: 593.37569 | E59: 1087 | F59: 605.55566 | G59: 1271 | H59: 603.14241
A61: Notes
A62: 1. Includes financial assistance, material aid, brokerage and vouchers provided to, or on behalf, of the client during the reporting period.
A63: 2. The total is a unique count of clients within all financial assistance categories; therefore it is not the sum of the components.

Sheet CLIENTS.27
A1: Table of contents
A2: Table CLIENTS.27: Clients, by number of support periods, and by state and territory, 2023–24
A4: State/territory | B4: Number of support periods | C4: Males | D4: Females | E4: All clients (number) | F4: All clients (per cent)
A5: National | B5: 1 support period | C5: 75372 | D5: 107466 | E5: 182838 | F5: 65.3
A6: National | B6: 2 support periods | C6: 21506 | D6: 33015 | E6: 54521 | F6: 19.5
A7: National | B7: 3 support periods | C7: 7907 | D7: 13068 | E7: 20975 | F7: 7.5
A8: National | B8: 4 support periods | C8: 3593 | D8: 6005 | E8: 9598 | F8: 3.4
A9: National | B9: 5 support periods | C9: 1678 | D9: 3000 | E9: 4678 | F9: 1.7
A10: National | B10: 6 or more support periods | C10: 2817 | D10: 4651 | E10: 7468 | F10: 2.7
A11: National | B11: Total | C11: 112873 | D11: 167205 | E11: 280078 | F11: 100
A12: NSW | B12: 1 support period | C12: 21057 | D12: 29476 | E12: 50533 | F12: 74.4
A13: NSW | B13: 2 support periods | C13: 4170 | D13: 6848 | E13: 11018 | F13: 16.2
A14: NSW | B14: 3 support periods | C14: 1204 | D14: 2234 | E14: 3438 | F14: 5.1
A15: NSW | B15: 4 support periods | C15: 487 | D15: 942 | E15: 1429 | F15: 2.1
A16: NSW | B16: 5 support periods | C16: 219 | D16: 398 | E16: 617 | F16: 0.9
... A67: NT | B67: Total | C67: 3378 | D67: 6702 | E67: 10080 | F67: 100
A69: Notes
A70: 1. The period of time a client receives services from a specialist homelessness agency is referred to as a support period. A support period starts on the day the client first receives a service and ends when: • the relationship between the client and the agency ends, • the client has reached their maximum amount of support the agency can offer, or • a client has not received any services from the agency for a whole calendar month and there is no ongoing relationship. The end of the support period is the day the client last received services from the agency. A client can have multiple support periods within a reporting period.
A71: 2. Excludes support periods with an invalid SLK that could not be used to derive client information.

Sheet CLIENTS.28
A1: Table of contents
A2: Table CLIENTS.28: Support periods, by indicative duration over the reporting period, and by state and territory, 2023–24
A4: State/ territory | B4: Support periods | C4: Status of support periods | D4: Males | E4: Females | F4: All clients
A5: National | B5: Support periods that were ongoing on 1 July 2023 | C5: Closed in 2023–24 | D5: 23639 | E5: 37819 | F5: 61458
A6: National | B6: Support periods that were ongoing on 1 July 2023 | C6: Remained open on 30 June 2024 | D6: 5459 | E6: 7915 | F6: 13374
A7: National | B7: Support periods that opened in 2023–24 | C7: Closed in 2023–24 | D7: 136929 | E7: 205624 | F7: 342553
A8: National | B8: Support periods that opened in 2023–24 | C8: Remained open on 30 June 2024 | D8: 25815 | E8: 42420 | F8: 68235
A9: National | B9: Total | C9: Total | D9: 191842 | E9: 293778 | F9: 485620
A10: NSW | B10: Support periods that were ongoing on 1 July 2023 | C10: Closed in 2023–24 | D10: 6344 | E10: 9677 | F10: 16021
A11: NSW | B11: Support periods that were ongoing on 1 July 2023 | C11: Remained open on 30 June 2024 | D11: 1413 | E11: 2260 | F11: 3673
A12: NSW | B12: Support periods that opened in 2023–24 | C12: Closed in 2023–24 | D12: 23603 | E12: 35737 | F12: 59340
A13: NSW | B13: Support periods that opened in 2023–24 | C13: Remained open on 30 June 2024 | D13: 6649 | E13: 10620 | F13: 17269
A14: NSW | B14: Total | C14: Total | D14: 38009 | E14: 58294 | F14: 96303
A15: Vic | B15: Support periods that were ongoing on 1 July 2023 | C15: Closed in 2023–24 | D15: 7858 | E15: 13158 | F15: 21016
A16: Vic | B16: Support periods that were ongoing on 1 July 2023 | C16: Remained open on 30 June 2024 | D16: 1659 | E16: 2348 | F16: 4007
... A49: NT | B49: Total | C49: Total | D49: 4627 | E49: 11024 | F49: 15651
A51: Note: Includes support periods with an invalid SLK that could not be used to derive client information.

Sheet CLIENTS.29
A1: Table of contents
A2: Table CLIENTS.29: Clients, by total days of support, and by state and territory, 2023–24
A4: State/territory | B4: Length of support | C4: Males | D4: Females | E4: All clients (number) | F4: All clients (per cent)
A5: National | B5: Up to 5 days | C5: 20442 | D5: 26386 | E5: 46828 | F5: 16.7
A6: National | B6: 6–45 days | C6: 31921 | D6: 45417 | E6: 77338 | F6: 27.6
A7: National | B7: 46–90 days | C7: 19568 | D7: 29218 | E7: 48786 | F7: 17.4
A8: National | B8: 91–180 days | C8: 19211 | D8: 30734 | E8: 49945 | F8: 17.8
A9: National | B9: Over 180 days | C9: 21731 | D9: 35450 | E9: 57181 | F9: 20.4
A10: National | B10: Total | C10: 112873 | D10: 167205 | E10: 280078 | F10: 100
A11: National | B11: Mean | C11: 98.7 | D11: 107.1 | E11: 103.7 | F11: . .
A12: National | B12: Median | C12: 53 | D12: 61 | E12: 58 | F12: . .
A13: NSW | B13: Up to 5 days | C13: 3265 | D13: 4318 | E13: 7583 | F13: 11.2
A14: NSW | B14: 6–45 days | C14: 7911 | D14: 11090 | E14: 19001 | F14: 28
A15: NSW | B15: 46–90 days | C15: 5530 | D15: 7891 | E15: 13421 | F15: 19.8
A16: NSW | B16: 91–180 days | C16: 5314 | D16: 8029 | E16: 13343 | F16: 19.7
A17: NSW | B17: Over 180 days | C17: 5466 | D17: 9077 | E17: 14543 | F17: 21.4
A18: NSW | B18: Total | C18: 27486 | D18: 40405 | E18: 67891 | F18: 100
A19: NSW | B19: Mean | C19: 104.2 | D19: 112.8 | E19: 109.3 | F19: . .
A20: NSW | B20: Median | C20: 62 | D20: 70 | E20: 67 | F20: . .
A21: Vic | B21: Up to 5 days | C21: 10702 | D21: 11438 | E21: 22140 | F21: 21.7
A22: Vic | B22: 6–45 days | C22: 12569 | D22: 16114 | E22: 28683 | F22: 28.1
A23: Vic | B23: 46–90 days | C23: 6382 | D23: 9830 | E23: 16212 | F23: 15.9
A24: Vic | B24: 91–180 days | C24: 5947 | D24: 10520 | E24: 16467 | F24: 16.1
A25: Vic | B25: Over 180 days | C25: 6832 | D25: 11630 | E25: 18462 | F25: 18.1
A26: Vic | B26: Total | C26: 42432 | D26: 59532 | E26: 101964 | F26: 100
A27: Vic | B27: Mean | C27: 85.1 | D27: 101.7 | E27: 94.8 | F27: . .
A28: Vic | B28: Median | C28: 35 | D28: 54 | E28: 46 | F28: . .
A29: Qld | B29: Up to 5 days | C29: 2638 | D29: 3762 | E29: 6400 | F29: 13.1
A30: Qld | B30: 6–45 days | C30: 5538 | D30: 7779 | E30: 13317 | F30: 27.3
A31: Qld | B31: 46–90 days | C31: 3849 | D31: 5343 | E31: 9192 | F31: 18.8
A32: Qld | B32: 91–180 days | C32: 4138 | D32: 5943 | E32: 10081 | F32: 20.7
A33: Qld | B33: Over 180 days | C33: 3840 | D33: 5988 | E33: 9828 | F33: 20.1
A34: Qld | B34: Total | C34: 20003 | D34: 28815 | E34: 48818 | F34: 100
A35: Qld | B35: Mean | C35: 101.9 | D35: 106.9 | E35: 104.8 | F35: . .
A36: Qld | B36: Median | C36: 63 | D36: 66 | E36: 65 | F36: . .
A37: WA | B37: Up to 5 days | C37: 2694 | D37: 4648 | E37: 7342 | F37: 29.4
A38: WA | B38: 6–45 days | C38: 2172 | D38: 4545 | E38: 6717 | F38: 26.9
A39: WA | B39: 46–90 days | C39: 1008 | D39: 2037 | E39: 3045 | F39: 12.2
A40: WA | B40: 91–180 days | C40: 1081 | D40: 2210 | E40: 3291 | F40: 13.2
A41: WA | B41: Over 180 days | C41: 1571 | D41: 3027 | E41: 4598 | F41: 18.4
A42: WA | B42: Total | C42: 8526 | D42: 16467 | E42: 24993 | F42: 100
A43: WA | B43: Mean | C43: 90.5 | D43: 91.8 | E43: 91.4 | F43: . .
A44: WA | B44: Median | C44: 27 | D44: 31 | E44: 31 | F44: . .
A45: SA | B45: Up to 5 days | C45: 588 | D45: 734 | E45: 1322 | F45: 7.1
A46: SA | B46: 6–45 days | C46: 2326 | D46: 3437 | E46: 5763 | F46: 30.8
A47: SA | B47: 46–90 days | C47: 1610 | D47: 2414 | E47: 4024 | F47: 21.5
A48: SA | B48: 91–180 days | C48: 1420 | D48: 2037 | E48: 3457 | F48: 18.5
A49: SA | B49: Over 180 days | C49: 1667 | D49: 2484 | E49: 4151 | F49: 22.2
A50: SA | B50: Total | C50: 7611 | D50: 11106 | E50: 18717 | F50: 100
A51: SA | B51: Mean | C51: 106.6 | D51: 109.9 | E51: 108.6 | F51: . .
A52: SA | B52: Median | C52: 67 | D52: 67 | E52: 67 | F52: . .
A53: Tas | B53: Up to 5 days | C53: 217 | D53: 239 | E53: 456 | F53: 6.8
A54: Tas | B54: 6–45 days | C54: 731 | D54: 867 | E54: 1598 | F54: 24
A55: Tas | B55: 46–90 days | C55: 619 | D55: 765 | E55: 1384 | F55: 20.7
A56: Tas | B56: 91–180 days | C56: 517 | D56: 817 | E56: 1334 | F56: 20
A57: Tas | B57: Over 180 days | C57: 891 | D57: 1009 | E57: 1900 | F57: 28.5
A58: Tas | B58: Total | C58: 2975 | D58: 3697 | E58: 6672 | F58: 100
A59: Tas | B59: Mean | C59: 141.1 | D59: 136.6 | E59: 138.6 | F59: . .
A60: Tas | B60: Median | C60: 83 | D60: 89 | E60: 87 | F60: . .
A61: ACT | B61: Up to 5 days | C61: 61 | D61: 68 | E61: 129 | F61: 3.2
A62: ACT | B62: 6–45 days | C62: 400 | D62: 464 | E62: 864 | F62: 21.6
A63: ACT | B63: 46–90 days | C63: 275 | D63: 384 | E63: 659 | F63: 16.5
A64: ACT | B64: 91–180 days | C64: 382 | D64: 445 | E64: 827 | F64: 20.6
A65: ACT | B65: Over 180 days | C65: 632 | D65: 895 | E65: 1527 | F65: 38.1
A66: ACT | B66: Total | C66: 1750 | D66: 2256 | E66: 4006 | F66: 100
A67: ACT | B67: Mean | C67: 160 | D67: 172.9 | E67: 167.3 | F67: . .
A68: ACT | B68: Median | C68: 120 | D68: 125 | E68: 123 | F68: . .
A69: NT | B69: Up to 5 days | C69: 726 | D69: 1688 | E69: 2414 | F69: 23.9
A70: NT | B70: 6–45 days | C70: 931 | D70: 2026 | E70: 2957 | F70: 29.3
A71: NT | B71: 46–90 days | C71: 523 | D71: 920 | E71: 1443 | F71: 14.3
A72: NT | B72: 91–180 days | C72: 457 | D72: 885 | E72: 1342 | F72: 13.3
A73: NT | B73: Over 180 days | C73: 741 | D73: 1183 | E73: 1924 | F73: 19.1
A74: NT | B74: Total | C74: 3378 | D74: 6702 | E74: 10080 | F74: 100
A75: NT | B75: Mean | C75: 102.8 | D75: 88.4 | E75: 93.2 | F75: . .
A76: NT | B76: Median | C76: 47 | D76: 32 | E76: 37 | F76: . .
A78: Note: If the support period start or end dates are outside of the reporting period, total days are calculated using a start date of the 1 July and an end date of the 30 June of the financial year.
A79: . . not applicable

Sheet CLIENTS.30
A1: Table of contents
